{"box_data": [{"position": {"minX": 32.0, "minY": 38.75, "maxX": 616.5, "maxY": 631.0}, "class_id": 0, "box_caption": "Page 0.926", "scores": {"class_score": 0.92626953125}, "domain": "pixel"}, {"position": {"minX": 17.25, "minY": -14.25, "maxX": 649.0, "maxY": 382.75}, "class_id": 0, "box_caption": "Page 0.005", "scores": {"class_score": 0.004573822021484375}, "domain": "pixel"}, {"position": {"minX": 40.0, "minY": 312.5, "maxX": 632.0, "maxY": 728.5}, "class_id": 0, "box_caption": "Page 0.003", "scores": {"class_score": 0.003337860107421875}, "domain": "pixel"}], "class_labels": {"0": "Page"}}