{"box_data": [{"position": {"minX": 57.25, "minY": 43.0, "maxX": 622.0, "maxY": 652.5}, "class_id": 0, "box_caption": "Page 0.905", "scores": {"class_score": 0.9052734375}, "domain": "pixel"}, {"position": {"minX": 47.75, "minY": 365.0, "maxX": 637.0, "maxY": 672.0}, "class_id": 0, "box_caption": "Page 0.016", "scores": {"class_score": 0.015899658203125}, "domain": "pixel"}, {"position": {"minX": 33.75, "minY": 9.875, "maxX": 644.0, "maxY": 370.0}, "class_id": 0, "box_caption": "Page 0.012", "scores": {"class_score": 0.0115966796875}, "domain": "pixel"}, {"position": {"minX": 318.5, "minY": 49.5, "maxX": 711.5, "maxY": 675.5}, "class_id": 0, "box_caption": "Page 0.001", "scores": {"class_score": 0.0013151168823242188}, "domain": "pixel"}, {"position": {"minX": -107.5, "minY": -34.375, "maxX": 278.5, "maxY": 182.125}, "class_id": 0, "box_caption": "Page 0.001", "scores": {"class_score": 0.0010204315185546875}, "domain": "pixel"}], "class_labels": {"0": "Page"}}