{"box_data": [{"position": {"minX": 91.0, "minY": 25.5, "maxX": 659.0, "maxY": 583.5}, "class_id": 0, "box_caption": "Page 0.867", "scores": {"class_score": 0.8671875}, "domain": "pixel"}, {"position": {"minX": 105.5, "minY": 302.5, "maxX": 690.0, "maxY": 660.0}, "class_id": 0, "box_caption": "Page 0.023", "scores": {"class_score": 0.0226287841796875}, "domain": "pixel"}, {"position": {"minX": 50.0, "minY": 22.75, "maxX": 453.75, "maxY": 634.0}, "class_id": 0, "box_caption": "Page 0.014", "scores": {"class_score": 0.0141754150390625}, "domain": "pixel"}, {"position": {"minX": 386.0, "minY": 324.0, "maxX": 662.0, "maxY": 639.0}, "class_id": 0, "box_caption": "Page 0.009", "scores": {"class_score": 0.0087127685546875}, "domain": "pixel"}, {"position": {"minX": 93.0, "minY": -9.125, "maxX": 654.5, "maxY": 327.0}, "class_id": 0, "box_caption": "Page 0.005", "scores": {"class_score": 0.005218505859375}, "domain": "pixel"}, {"position": {"minX": 90.25, "minY": 313.0, "maxX": 454.75, "maxY": 653.0}, "class_id": 0, "box_caption": "Page 0.004", "scores": {"class_score": 0.0037212371826171875}, "domain": "pixel"}], "class_labels": {"0": "Page"}}