{"box_data": [{"position": {"minX": 40.25, "minY": 40.5, "maxX": 623.0, "maxY": 703.5}, "class_id": 0, "box_caption": "Page 0.848", "scores": {"class_score": 0.84765625}, "domain": "pixel"}, {"position": {"minX": 169.5, "minY": 90.5, "maxX": 522.5, "maxY": 641.5}, "class_id": 0, "box_caption": "Page 0.729", "scores": {"class_score": 0.728515625}, "domain": "pixel"}, {"position": {"minX": 53.75, "minY": 13.5, "maxX": 608.0, "maxY": 409.5}, "class_id": 0, "box_caption": "Page 0.247", "scores": {"class_score": 0.24658203125}, "domain": "pixel"}, {"position": {"minX": 195.25, "minY": 70.875, "maxX": 486.75, "maxY": 477.5}, "class_id": 0, "box_caption": "Page 0.197", "scores": {"class_score": 0.1973876953125}, "domain": "pixel"}, {"position": {"minX": 165.25, "minY": 78.25, "maxX": 504.25, "maxY": 332.0}, "class_id": 0, "box_caption": "Page 0.162", "scores": {"class_score": 0.162109375}, "domain": "pixel"}, {"position": {"minX": 139.625, "minY": 294.0, "maxX": 542.5, "maxY": 637.5}, "class_id": 0, "box_caption": "Page 0.074", "scores": {"class_score": 0.0740966796875}, "domain": "pixel"}, {"position": {"minX": 74.875, "minY": 63.875, "maxX": 417.0, "maxY": 361.0}, "class_id": 0, "box_caption": "Page 0.024", "scores": {"class_score": 0.0243377685546875}, "domain": "pixel"}, {"position": {"minX": 40.375, "minY": 313.25, "maxX": 372.0, "maxY": 668.0}, "class_id": 0, "box_caption": "Page 0.022", "scores": {"class_score": 0.0220794677734375}, "domain": "pixel"}, {"position": {"minX": 93.75, "minY": 273.5, "maxX": 634.0, "maxY": 720.0}, "class_id": 0, "box_caption": "Page 0.019", "scores": {"class_score": 0.0194244384765625}, "domain": "pixel"}, {"position": {"minX": 64.0, "minY": 418.75, "maxX": 602.5, "maxY": 750.0}, "class_id": 0, "box_caption": "Page 0.018", "scores": {"class_score": 0.01751708984375}, "domain": "pixel"}, {"position": {"minX": 7.375, "minY": 358.0, "maxX": 289.0, "maxY": 688.0}, "class_id": 0, "box_caption": "Page 0.014", "scores": {"class_score": 0.01433563232421875}, "domain": "pixel"}, {"position": {"minX": 81.1875, "minY": 344.75, "maxX": 265.5, "maxY": 652.0}, "class_id": 0, "box_caption": "Page 0.012", "scores": {"class_score": 0.01177978515625}, "domain": "pixel"}, {"position": {"minX": 69.375, "minY": 100.25, "maxX": 410.5, "maxY": 646.0}, "class_id": 0, "box_caption": "Page 0.011", "scores": {"class_score": 0.01146697998046875}, "domain": "pixel"}, {"position": {"minX": 123.75, "minY": 218.25, "maxX": 539.0, "maxY": 461.75}, "class_id": 0, "box_caption": "Page 0.011", "scores": {"class_score": 0.01111602783203125}, "domain": "pixel"}, {"position": {"minX": 107.625, "minY": 520.5, "maxX": 556.5, "maxY": 723.5}, "class_id": 0, "box_caption": "Page 0.010", "scores": {"class_score": 0.00974273681640625}, "domain": "pixel"}, {"position": {"minX": 303.5, "minY": 371.5, "maxX": 621.5, "maxY": 689.5}, "class_id": 0, "box_caption": "Page 0.008", "scores": {"class_score": 0.007549285888671875}, "domain": "pixel"}, {"position": {"minX": 251.25, "minY": 64.5, "maxX": 625.0, "maxY": 366.0}, "class_id": 0, "box_caption": "Page 0.007", "scores": {"class_score": 0.007373809814453125}, "domain": "pixel"}, {"position": {"minX": 382.25, "minY": 149.75, "maxX": 789.0, "maxY": 653.0}, "class_id": 0, "box_caption": "Page 0.006", "scores": {"class_score": 0.006488800048828125}, "domain": "pixel"}, {"position": {"minX": 393.0, "minY": 294.5, "maxX": 724.0, "maxY": 703.5}, "class_id": 0, "box_caption": "Page 0.006", "scores": {"class_score": 0.006488800048828125}, "domain": "pixel"}, {"position": {"minX": 115.75, "minY": -5.9375, "maxX": 567.0, "maxY": 231.25}, "class_id": 0, "box_caption": "Page 0.006", "scores": {"class_score": 0.0058441162109375}, "domain": "pixel"}, {"position": {"minX": -44.0625, "minY": 545.0, "maxX": 269.25, "maxY": 704.0}, "class_id": 0, "box_caption": "Page 0.005", "scores": {"class_score": 0.0053863525390625}, "domain": "pixel"}, {"position": {"minX": 47.4375, "minY": 21.875, "maxX": 243.5, "maxY": 394.5}, "class_id": 0, "box_caption": "Page 0.005", "scores": {"class_score": 0.0048675537109375}, "domain": "pixel"}, {"position": {"minX": 130.625, "minY": 43.875, "maxX": 609.5, "maxY": 302.0}, "class_id": 0, "box_caption": "Page 0.005", "scores": {"class_score": 0.004756927490234375}, "domain": "pixel"}, {"position": {"minX": 85.5, "minY": -78.125, "maxX": 645.5, "maxY": 168.875}, "class_id": 0, "box_caption": "Page 0.005", "scores": {"class_score": 0.004718780517578125}, "domain": "pixel"}, {"position": {"minX": -37.9375, "minY": 374.0, "maxX": 136.25, "maxY": 740.0}, "class_id": 0, "box_caption": "Page 0.004", "scores": {"class_score": 0.00443267822265625}, "domain": "pixel"}, {"position": {"minX": 147.875, "minY": 168.25, "maxX": 514.0, "maxY": 393.25}, "class_id": 0, "box_caption": "Page 0.004", "scores": {"class_score": 0.004398345947265625}, "domain": "pixel"}, {"position": {"minX": 12.625, "minY": 511.5, "maxX": 277.5, "maxY": 669.5}, "class_id": 0, "box_caption": "Page 0.004", "scores": {"class_score": 0.004364013671875}, "domain": "pixel"}, {"position": {"minX": 53.125, "minY": 473.75, "maxX": 306.0, "maxY": 696.0}, "class_id": 0, "box_caption": "Page 0.004", "scores": {"class_score": 0.00428009033203125}, "domain": "pixel"}, {"position": {"minX": -19.25, "minY": 48.5, "maxX": 370.75, "maxY": 698.5}, "class_id": 0, "box_caption": "Page 0.004", "scores": {"class_score": 0.004039764404296875}, "domain": "pixel"}, {"position": {"minX": 103.0625, "minY": 501.75, "maxX": 262.5, "maxY": 669.5}, "class_id": 0, "box_caption": "Page 0.004", "scores": {"class_score": 0.00400543212890625}, "domain": "pixel"}, {"position": {"minX": 74.3125, "minY": 67.375, "maxX": 278.5, "maxY": 357.5}, "class_id": 0, "box_caption": "Page 0.004", "scores": {"class_score": 0.00399017333984375}, "domain": "pixel"}, {"position": {"minX": -17.0625, "minY": 507.5, "maxX": 224.75, "maxY": 741.5}, "class_id": 0, "box_caption": "Page 0.004", "scores": {"class_score": 0.0037364959716796875}, "domain": "pixel"}, {"position": {"minX": 474.25, "minY": 395.75, "maxX": 697.0, "maxY": 715.0}, "class_id": 0, "box_caption": "Page 0.004", "scores": {"class_score": 0.0037364959716796875}, "domain": "pixel"}, {"position": {"minX": 236.375, "minY": 420.5, "maxX": 690.5, "maxY": 756.5}, "class_id": 0, "box_caption": "Page 0.004", "scores": {"class_score": 0.0037212371826171875}, "domain": "pixel"}, {"position": {"minX": -91.4375, "minY": 327.0, "maxX": 176.5, "maxY": 737.0}, "class_id": 0, "box_caption": "Page 0.004", "scores": {"class_score": 0.0036220550537109375}, "domain": "pixel"}, {"position": {"minX": -41.0, "minY": 564.0, "maxX": 206.0, "maxY": 682.0}, "class_id": 0, "box_caption": "Page 0.004", "scores": {"class_score": 0.0035381317138671875}, "domain": "pixel"}, {"position": {"minX": 458.5, "minY": 360.0, "maxX": 663.5, "maxY": 635.0}, "class_id": 0, "box_caption": "Page 0.003", "scores": {"class_score": 0.0034427642822265625}, "domain": "pixel"}, {"position": {"minX": 441.5, "minY": 169.5, "maxX": 619.5, "maxY": 427.5}, "class_id": 0, "box_caption": "Page 0.003", "scores": {"class_score": 0.0033893585205078125}, "domain": "pixel"}, {"position": {"minX": 58.625, "minY": -68.5625, "maxX": 414.0, "maxY": 229.75}, "class_id": 0, "box_caption": "Page 0.003", "scores": {"class_score": 0.003337860107421875}, "domain": "pixel"}, {"position": {"minX": 437.0, "minY": 384.5, "maxX": 756.0, "maxY": 801.5}, "class_id": 0, "box_caption": "Page 0.003", "scores": {"class_score": 0.0033111572265625}, "domain": "pixel"}, {"position": {"minX": 506.75, "minY": 537.5, "maxX": 605.5, "maxY": 597.5}, "class_id": 0, "box_caption": "Page 0.003", "scores": {"class_score": 0.0032596588134765625}, "domain": "pixel"}, {"position": {"minX": 515.5, "minY": 467.5, "maxX": 669.5, "maxY": 658.5}, "class_id": 0, "box_caption": "Page 0.003", "scores": {"class_score": 0.0030517578125}, "domain": "pixel"}, {"position": {"minX": -63.25, "minY": 443.75, "maxX": 291.0, "maxY": 731.0}, "class_id": 0, "box_caption": "Page 0.003", "scores": {"class_score": 0.002811431884765625}, "domain": "pixel"}, {"position": {"minX": 515.0, "minY": 529.0, "maxX": 598.0, "maxY": 574.0}, "class_id": 0, "box_caption": "Page 0.003", "scores": {"class_score": 0.00269317626953125}, "domain": "pixel"}, {"position": {"minX": 282.25, "minY": -106.875, "maxX": 688.0, "maxY": 184.375}, "class_id": 0, "box_caption": "Page 0.003", "scores": {"class_score": 0.0026531219482421875}, "domain": "pixel"}, {"position": {"minX": -48.8125, "minY": 443.75, "maxX": 208.75, "maxY": 672.0}, "class_id": 0, "box_caption": "Page 0.003", "scores": {"class_score": 0.00263214111328125}, "domain": "pixel"}, {"position": {"minX": 388.5, "minY": -44.125, "maxX": 786.5, "maxY": 401.5}, "class_id": 0, "box_caption": "Page 0.003", "scores": {"class_score": 0.002590179443359375}, "domain": "pixel"}, {"position": {"minX": -34.21875, "minY": 291.75, "maxX": 73.5, "maxY": 685.0}, "class_id": 0, "box_caption": "Page 0.002", "scores": {"class_score": 0.0024814605712890625}, "domain": "pixel"}, {"position": {"minX": 167.0, "minY": 525.5, "maxX": 626.0, "maxY": 786.5}, "class_id": 0, "box_caption": "Page 0.002", "scores": {"class_score": 0.0024623870849609375}, "domain": "pixel"}, {"position": {"minX": 527.5, "minY": 539.5, "maxX": 618.5, "maxY": 571.5}, "class_id": 0, "box_caption": "Page 0.002", "scores": {"class_score": 0.0024051666259765625}, "domain": "pixel"}, {"position": {"minX": -13.34375, "minY": 496.25, "maxX": 113.25, "maxY": 685.5}, "class_id": 0, "box_caption": "Page 0.002", "scores": {"class_score": 0.0023975372314453125}, "domain": "pixel"}, {"position": {"minX": 284.5, "minY": 525.5, "maxX": 638.0, "maxY": 719.5}, "class_id": 0, "box_caption": "Page 0.002", "scores": {"class_score": 0.0023784637451171875}, "domain": "pixel"}, {"position": {"minX": 468.25, "minY": 518.0, "maxX": 613.0, "maxY": 620.0}, "class_id": 0, "box_caption": "Page 0.002", "scores": {"class_score": 0.0023784637451171875}, "domain": "pixel"}, {"position": {"minX": 30.75, "minY": 72.75, "maxX": 389.0, "maxY": 481.75}, "class_id": 0, "box_caption": "Page 0.002", "scores": {"class_score": 0.002368927001953125}, "domain": "pixel"}, {"position": {"minX": 68.375, "minY": 539.5, "maxX": 467.0, "maxY": 778.5}, "class_id": 0, "box_caption": "Page 0.002", "scores": {"class_score": 0.0023059844970703125}, "domain": "pixel"}, {"position": {"minX": 403.0, "minY": 402.75, "maxX": 642.0, "maxY": 648.0}, "class_id": 0, "box_caption": "Page 0.002", "scores": {"class_score": 0.00229644775390625}, "domain": "pixel"}, {"position": {"minX": 7.5625, "minY": 4.625, "maxX": 215.0, "maxY": 467.5}, "class_id": 0, "box_caption": "Page 0.002", "scores": {"class_score": 0.0021915435791015625}, "domain": "pixel"}, {"position": {"minX": 140.5, "minY": 584.0, "maxX": 522.5, "maxY": 726.0}, "class_id": 0, "box_caption": "Page 0.002", "scores": {"class_score": 0.002132415771484375}, "domain": "pixel"}, {"position": {"minX": 481.25, "minY": 516.0, "maxX": 596.5, "maxY": 590.0}, "class_id": 0, "box_caption": "Page 0.002", "scores": {"class_score": 0.001987457275390625}, "domain": "pixel"}, {"position": {"minX": 492.25, "minY": 485.25, "maxX": 626.5, "maxY": 636.5}, "class_id": 0, "box_caption": "Page 0.002", "scores": {"class_score": 0.001972198486328125}, "domain": "pixel"}, {"position": {"minX": 61.875, "minY": 27.0625, "maxX": 417.5, "maxY": 269.5}, "class_id": 0, "box_caption": "Page 0.002", "scores": {"class_score": 0.001972198486328125}, "domain": "pixel"}, {"position": {"minX": 297.0, "minY": 503.5, "maxX": 747.0, "maxY": 781.5}, "class_id": 0, "box_caption": "Page 0.002", "scores": {"class_score": 0.001972198486328125}, "domain": "pixel"}, {"position": {"minX": 109.0, "minY": 258.5, "maxX": 490.0, "maxY": 551.0}, "class_id": 0, "box_caption": "Page 0.002", "scores": {"class_score": 0.001941680908203125}, "domain": "pixel"}, {"position": {"minX": 27.9375, "minY": 75.5, "maxX": 210.75, "maxY": 351.75}, "class_id": 0, "box_caption": "Page 0.002", "scores": {"class_score": 0.001926422119140625}, "domain": "pixel"}, {"position": {"minX": 198.75, "minY": 235.25, "maxX": 297.75, "maxY": 325.75}, "class_id": 0, "box_caption": "Page 0.002", "scores": {"class_score": 0.001926422119140625}, "domain": "pixel"}, {"position": {"minX": -56.8125, "minY": -60.125, "maxX": 150.5, "maxY": 404.0}, "class_id": 0, "box_caption": "Page 0.002", "scores": {"class_score": 0.001918792724609375}, "domain": "pixel"}, {"position": {"minX": 461.5, "minY": 117.375, "maxX": 777.5, "maxY": 541.0}, "class_id": 0, "box_caption": "Page 0.002", "scores": {"class_score": 0.001918792724609375}, "domain": "pixel"}, {"position": {"minX": 270.0, "minY": 124.0, "maxX": 647.0, "maxY": 618.5}, "class_id": 0, "box_caption": "Page 0.002", "scores": {"class_score": 0.0019121170043945312}, "domain": "pixel"}, {"position": {"minX": 92.0, "minY": 356.0, "maxX": 451.5, "maxY": 636.0}, "class_id": 0, "box_caption": "Page 0.002", "scores": {"class_score": 0.0018968582153320312}, "domain": "pixel"}, {"position": {"minX": 77.5, "minY": 75.5625, "maxX": 410.5, "maxY": 217.0}, "class_id": 0, "box_caption": "Page 0.002", "scores": {"class_score": 0.0018892288208007812}, "domain": "pixel"}, {"position": {"minX": -74.1875, "minY": 176.25, "maxX": 170.0, "maxY": 678.0}, "class_id": 0, "box_caption": "Page 0.002", "scores": {"class_score": 0.0018749237060546875}, "domain": "pixel"}, {"position": {"minX": 71.875, "minY": 371.25, "maxX": 204.625, "maxY": 604.0}, "class_id": 0, "box_caption": "Page 0.002", "scores": {"class_score": 0.0018529891967773438}, "domain": "pixel"}, {"position": {"minX": -3.75, "minY": -141.875, "maxX": 548.0, "maxY": 170.625}, "class_id": 0, "box_caption": "Page 0.002", "scores": {"class_score": 0.0018463134765625}, "domain": "pixel"}, {"position": {"minX": -26.625, "minY": -133.25, "maxX": 316.5, "maxY": 298.75}, "class_id": 0, "box_caption": "Page 0.002", "scores": {"class_score": 0.0018243789672851562}, "domain": "pixel"}, {"position": {"minX": 145.5, "minY": -165.375, "maxX": 718.5, "maxY": 191.125}, "class_id": 0, "box_caption": "Page 0.002", "scores": {"class_score": 0.0017824172973632812}, "domain": "pixel"}, {"position": {"minX": -114.75, "minY": -38.5, "maxX": 199.25, "maxY": 463.0}, "class_id": 0, "box_caption": "Page 0.002", "scores": {"class_score": 0.0017824172973632812}, "domain": "pixel"}, {"position": {"minX": 220.75, "minY": -2.71875, "maxX": 522.0, "maxY": 99.625}, "class_id": 0, "box_caption": "Page 0.002", "scores": {"class_score": 0.0017747879028320312}, "domain": "pixel"}, {"position": {"minX": -133.375, "minY": 258.5, "maxX": 281.5, "maxY": 738.0}, "class_id": 0, "box_caption": "Page 0.002", "scores": {"class_score": 0.0017480850219726562}, "domain": "pixel"}, {"position": {"minX": 449.5, "minY": 66.25, "maxX": 611.5, "maxY": 365.0}, "class_id": 0, "box_caption": "Page 0.002", "scores": {"class_score": 0.0017414093017578125}, "domain": "pixel"}, {"position": {"minX": 459.75, "minY": 519.5, "maxX": 657.0, "maxY": 654.5}, "class_id": 0, "box_caption": "Page 0.002", "scores": {"class_score": 0.0017414093017578125}, "domain": "pixel"}, {"position": {"minX": 396.0, "minY": 42.875, "maxX": 598.5, "maxY": 323.0}, "class_id": 0, "box_caption": "Page 0.002", "scores": {"class_score": 0.0017137527465820312}, "domain": "pixel"}, {"position": {"minX": -26.5, "minY": 448.5, "maxX": 67.25, "maxY": 719.5}, "class_id": 0, "box_caption": "Page 0.002", "scores": {"class_score": 0.0017137527465820312}, "domain": "pixel"}, {"position": {"minX": 179.875, "minY": 399.25, "maxX": 549.5, "maxY": 654.5}, "class_id": 0, "box_caption": "Page 0.002", "scores": {"class_score": 0.0016813278198242188}, "domain": "pixel"}, {"position": {"minX": 576.5, "minY": 359.75, "maxX": 741.5, "maxY": 681.0}, "class_id": 0, "box_caption": "Page 0.002", "scores": {"class_score": 0.001674652099609375}, "domain": "pixel"}, {"position": {"minX": 385.0, "minY": 81.375, "maxX": 709.0, "maxY": 536.5}, "class_id": 0, "box_caption": "Page 0.002", "scores": {"class_score": 0.0016489028930664062}, "domain": "pixel"}, {"position": {"minX": -80.0, "minY": -113.9375, "maxX": 429.5, "maxY": 148.75}, "class_id": 0, "box_caption": "Page 0.002", "scores": {"class_score": 0.001628875732421875}, "domain": "pixel"}, {"position": {"minX": -32.25, "minY": -47.25, "maxX": 67.6875, "maxY": 383.25}, "class_id": 0, "box_caption": "Page 0.002", "scores": {"class_score": 0.001628875732421875}, "domain": "pixel"}, {"position": {"minX": -34.125, "minY": 65.875, "maxX": 268.0, "maxY": 484.0}, "class_id": 0, "box_caption": "Page 0.002", "scores": {"class_score": 0.0016231536865234375}, "domain": "pixel"}, {"position": {"minX": 265.0, "minY": -20.0, "maxX": 662.0, "maxY": 250.5}, "class_id": 0, "box_caption": "Page 0.002", "scores": {"class_score": 0.0015735626220703125}, "domain": "pixel"}, {"position": {"minX": 164.25, "minY": 76.5, "maxX": 507.75, "maxY": 224.5}, "class_id": 0, "box_caption": "Page 0.002", "scores": {"class_score": 0.0015668869018554688}, "domain": "pixel"}, {"position": {"minX": 362.5, "minY": 242.75, "maxX": 481.0, "maxY": 319.75}, "class_id": 0, "box_caption": "Page 0.002", "scores": {"class_score": 0.0015668869018554688}, "domain": "pixel"}, {"position": {"minX": 386.0, "minY": 325.5, "maxX": 585.0, "maxY": 652.0}, "class_id": 0, "box_caption": "Page 0.002", "scores": {"class_score": 0.0015611648559570312}, "domain": "pixel"}, {"position": {"minX": 50.625, "minY": 550.0, "maxX": 425.5, "maxY": 701.0}, "class_id": 0, "box_caption": "Page 0.002", "scores": {"class_score": 0.00154876708984375}, "domain": "pixel"}, {"position": {"minX": 590.5, "minY": 1.875, "maxX": 675.5, "maxY": 72.875}, "class_id": 0, "box_caption": "Page 0.002", "scores": {"class_score": 0.0015363693237304688}, "domain": "pixel"}, {"position": {"minX": 114.6875, "minY": 241.25, "maxX": 189.25, "maxY": 321.25}, "class_id": 0, "box_caption": "Page 0.002", "scores": {"class_score": 0.0015306472778320312}, "domain": "pixel"}, {"position": {"minX": 6.0, "minY": -98.75, "maxX": 398.5, "maxY": 104.625}, "class_id": 0, "box_caption": "Page 0.002", "scores": {"class_score": 0.0015306472778320312}, "domain": "pixel"}, {"position": {"minX": 94.0, "minY": -120.75, "maxX": 504.5, "maxY": 128.5}, "class_id": 0, "box_caption": "Page 0.002", "scores": {"class_score": 0.0015192031860351562}, "domain": "pixel"}, {"position": {"minX": 462.25, "minY": 103.875, "maxX": 627.0, "maxY": 490.0}, "class_id": 0, "box_caption": "Page 0.002", "scores": {"class_score": 0.001506805419921875}, "domain": "pixel"}, {"position": {"minX": 45.125, "minY": 559.5, "maxX": 312.0, "maxY": 675.5}, "class_id": 0, "box_caption": "Page 0.002", "scores": {"class_score": 0.0015010833740234375}, "domain": "pixel"}, {"position": {"minX": 207.5, "minY": 496.75, "maxX": 583.5, "maxY": 689.5}, "class_id": 0, "box_caption": "Page 0.002", "scores": {"class_score": 0.0015010833740234375}, "domain": "pixel"}, {"position": {"minX": 327.5, "minY": -7.28125, "maxX": 606.5, "maxY": 100.5}, "class_id": 0, "box_caption": "Page 0.002", "scores": {"class_score": 0.0015010833740234375}, "domain": "pixel"}, {"position": {"minX": 266.25, "minY": -149.125, "maxX": 855.0, "maxY": 179.375}, "class_id": 0, "box_caption": "Page 0.001", "scores": {"class_score": 0.00147247314453125}, "domain": "pixel"}, {"position": {"minX": -26.75, "minY": 571.5, "maxX": 128.5, "maxY": 678.5}, "class_id": 0, "box_caption": "Page 0.001", "scores": {"class_score": 0.00147247314453125}, "domain": "pixel"}, {"position": {"minX": -50.9375, "minY": 149.75, "maxX": 82.5625, "maxY": 631.0}, "class_id": 0, "box_caption": "Page 0.001", "scores": {"class_score": 0.00147247314453125}, "domain": "pixel"}, {"position": {"minX": -31.5, "minY": 583.5, "maxX": 317.75, "maxY": 730.5}, "class_id": 0, "box_caption": "Page 0.001", "scores": {"class_score": 0.0014667510986328125}, "domain": "pixel"}, {"position": {"minX": 455.0, "minY": 355.25, "maxX": 847.0, "maxY": 709.0}, "class_id": 0, "box_caption": "Page 0.001", "scores": {"class_score": 0.0014553070068359375}, "domain": "pixel"}, {"position": {"minX": 443.0, "minY": 502.75, "maxX": 598.0, "maxY": 637.0}, "class_id": 0, "box_caption": "Page 0.001", "scores": {"class_score": 0.0014324188232421875}, "domain": "pixel"}, {"position": {"minX": 110.375, "minY": -5.84375, "maxX": 439.0, "maxY": 106.25}, "class_id": 0, "box_caption": "Page 0.001", "scores": {"class_score": 0.0014324188232421875}, "domain": "pixel"}, {"position": {"minX": 193.375, "minY": 56.375, "maxX": 361.5, "maxY": 347.0}, "class_id": 0, "box_caption": "Page 0.001", "scores": {"class_score": 0.0014162063598632812}, "domain": "pixel"}, {"position": {"minX": 108.25, "minY": 98.375, "maxX": 687.0, "maxY": 455.5}, "class_id": 0, "box_caption": "Page 0.001", "scores": {"class_score": 0.0014104843139648438}, "domain": "pixel"}, {"position": {"minX": -30.75, "minY": 520.0, "maxX": 303.25, "maxY": 794.0}, "class_id": 0, "box_caption": "Page 0.001", "scores": {"class_score": 0.0013990402221679688}, "domain": "pixel"}, {"position": {"minX": -46.25, "minY": -77.375, "maxX": 326.75, "maxY": 81.625}, "class_id": 0, "box_caption": "Page 0.001", "scores": {"class_score": 0.0013990402221679688}, "domain": "pixel"}, {"position": {"minX": 371.0, "minY": -143.375, "maxX": 740.0, "maxY": 308.5}, "class_id": 0, "box_caption": "Page 0.001", "scores": {"class_score": 0.0013828277587890625}, "domain": "pixel"}, {"position": {"minX": 29.25, "minY": 324.5, "maxX": 505.25, "maxY": 731.5}, "class_id": 0, "box_caption": "Page 0.001", "scores": {"class_score": 0.0013666152954101562}, "domain": "pixel"}, {"position": {"minX": -38.78125, "minY": 431.25, "maxX": 78.375, "maxY": 634.0}, "class_id": 0, "box_caption": "Page 0.001", "scores": {"class_score": 0.0013666152954101562}, "domain": "pixel"}, {"position": {"minX": 10.25, "minY": 492.25, "maxX": 461.25, "maxY": 731.5}, "class_id": 0, "box_caption": "Page 0.001", "scores": {"class_score": 0.0013561248779296875}, "domain": "pixel"}, {"position": {"minX": 1.53125, "minY": 565.5, "maxX": 106.75, "maxY": 636.5}, "class_id": 0, "box_caption": "Page 0.001", "scores": {"class_score": 0.0013408660888671875}, "domain": "pixel"}, {"position": {"minX": 107.75, "minY": 205.0, "maxX": 179.0, "maxY": 318.0}, "class_id": 0, "box_caption": "Page 0.001", "scores": {"class_score": 0.0013303756713867188}, "domain": "pixel"}, {"position": {"minX": 552.0, "minY": -58.75, "maxX": 760.0, "maxY": 269.25}, "class_id": 0, "box_caption": "Page 0.001", "scores": {"class_score": 0.0013151168823242188}, "domain": "pixel"}, {"position": {"minX": 185.0, "minY": 233.625, "maxX": 281.75, "maxY": 298.5}, "class_id": 0, "box_caption": "Page 0.001", "scores": {"class_score": 0.0013151168823242188}, "domain": "pixel"}, {"position": {"minX": -146.75, "minY": 93.5, "maxX": 231.25, "maxY": 648.5}, "class_id": 0, "box_caption": "Page 0.001", "scores": {"class_score": 0.0013151168823242188}, "domain": "pixel"}, {"position": {"minX": 194.5, "minY": -128.875, "maxX": 597.0, "maxY": 137.625}, "class_id": 0, "box_caption": "Page 0.001", "scores": {"class_score": 0.0013093948364257812}, "domain": "pixel"}, {"position": {"minX": 120.625, "minY": 241.5, "maxX": 185.875, "maxY": 292.0}, "class_id": 0, "box_caption": "Page 0.001", "scores": {"class_score": 0.0012998580932617188}, "domain": "pixel"}, {"position": {"minX": 86.375, "minY": 260.25, "maxX": 116.625, "maxY": 276.75}, "class_id": 0, "box_caption": "Page 0.001", "scores": {"class_score": 0.0012845993041992188}, "domain": "pixel"}, {"position": {"minX": -37.1875, "minY": 529.0, "maxX": 73.1875, "maxY": 652.0}, "class_id": 0, "box_caption": "Page 0.001", "scores": {"class_score": 0.00127410888671875}, "domain": "pixel"}, {"position": {"minX": 112.1875, "minY": 558.0, "maxX": 254.0, "maxY": 680.0}, "class_id": 0, "box_caption": "Page 0.001", "scores": {"class_score": 0.0012445449829101562}, "domain": "pixel"}, {"position": {"minX": 346.0, "minY": 577.0, "maxX": 702.0, "maxY": 733.0}, "class_id": 0, "box_caption": "Page 0.001", "scores": {"class_score": 0.0012445449829101562}, "domain": "pixel"}, {"position": {"minX": 543.0, "minY": 158.875, "maxX": 781.0, "maxY": 501.5}, "class_id": 0, "box_caption": "Page 0.001", "scores": {"class_score": 0.0012445449829101562}, "domain": "pixel"}, {"position": {"minX": 467.25, "minY": 70.0625, "maxX": 713.0, "maxY": 290.75}, "class_id": 0, "box_caption": "Page 0.001", "scores": {"class_score": 0.001239776611328125}, "domain": "pixel"}, {"position": {"minX": 87.3125, "minY": 488.0, "maxX": 289.5, "maxY": 618.0}, "class_id": 0, "box_caption": "Page 0.001", "scores": {"class_score": 0.001239776611328125}, "domain": "pixel"}, {"position": {"minX": 441.75, "minY": 216.0, "maxX": 602.0, "maxY": 369.5}, "class_id": 0, "box_caption": "Page 0.001", "scores": {"class_score": 0.0012350082397460938}, "domain": "pixel"}, {"position": {"minX": 99.125, "minY": 255.625, "maxX": 136.625, "maxY": 281.75}, "class_id": 0, "box_caption": "Page 0.001", "scores": {"class_score": 0.0012350082397460938}, "domain": "pixel"}, {"position": {"minX": 473.5, "minY": 29.625, "maxX": 769.5, "maxY": 440.5}, "class_id": 0, "box_caption": "Page 0.001", "scores": {"class_score": 0.0012350082397460938}, "domain": "pixel"}, {"position": {"minX": 565.0, "minY": 18.75, "maxX": 753.0, "maxY": 157.0}, "class_id": 0, "box_caption": "Page 0.001", "scores": {"class_score": 0.0012254714965820312}, "domain": "pixel"}, {"position": {"minX": -43.3125, "minY": 18.25, "maxX": 73.0625, "maxY": 506.75}, "class_id": 0, "box_caption": "Page 0.001", "scores": {"class_score": 0.0012159347534179688}, "domain": "pixel"}, {"position": {"minX": 95.3125, "minY": 265.0, "maxX": 140.5, "maxY": 302.0}, "class_id": 0, "box_caption": "Page 0.001", "scores": {"class_score": 0.0012063980102539062}, "domain": "pixel"}, {"position": {"minX": 257.5, "minY": 247.125, "maxX": 339.5, "maxY": 315.0}, "class_id": 0, "box_caption": "Page 0.001", "scores": {"class_score": 0.0012063980102539062}, "domain": "pixel"}, {"position": {"minX": 41.0, "minY": 429.0, "maxX": 364.0, "maxY": 756.0}, "class_id": 0, "box_caption": "Page 0.001", "scores": {"class_score": 0.0011968612670898438}, "domain": "pixel"}, {"position": {"minX": 243.625, "minY": 574.0, "maxX": 613.5, "maxY": 737.0}, "class_id": 0, "box_caption": "Page 0.001", "scores": {"class_score": 0.0011968612670898438}, "domain": "pixel"}, {"position": {"minX": 583.0, "minY": 480.5, "maxX": 737.0, "maxY": 648.5}, "class_id": 0, "box_caption": "Page 0.001", "scores": {"class_score": 0.0011968612670898438}, "domain": "pixel"}, {"position": {"minX": 187.625, "minY": 100.1875, "maxX": 299.5, "maxY": 207.25}, "class_id": 0, "box_caption": "Page 0.001", "scores": {"class_score": 0.0011920928955078125}, "domain": "pixel"}, {"position": {"minX": 51.75, "minY": 425.5, "maxX": 252.25, "maxY": 671.5}, "class_id": 0, "box_caption": "Page 0.001", "scores": {"class_score": 0.0011920928955078125}, "domain": "pixel"}, {"position": {"minX": 101.0625, "minY": 252.25, "maxX": 169.75, "maxY": 313.25}, "class_id": 0, "box_caption": "Page 0.001", "scores": {"class_score": 0.0011882781982421875}, "domain": "pixel"}, {"position": {"minX": 355.75, "minY": 111.25, "maxX": 422.75, "maxY": 169.0}, "class_id": 0, "box_caption": "Page 0.001", "scores": {"class_score": 0.0011882781982421875}, "domain": "pixel"}, {"position": {"minX": 460.0, "minY": -34.375, "maxX": 842.0, "maxY": 267.0}, "class_id": 0, "box_caption": "Page 0.001", "scores": {"class_score": 0.001178741455078125}, "domain": "pixel"}, {"position": {"minX": 259.5, "minY": 291.5, "maxX": 668.0, "maxY": 647.0}, "class_id": 0, "box_caption": "Page 0.001", "scores": {"class_score": 0.001178741455078125}, "domain": "pixel"}, {"position": {"minX": 212.625, "minY": 355.5, "maxX": 586.5, "maxY": 585.0}, "class_id": 0, "box_caption": "Page 0.001", "scores": {"class_score": 0.0011692047119140625}, "domain": "pixel"}, {"position": {"minX": 88.25, "minY": 234.125, "maxX": 386.75, "maxY": 513.0}, "class_id": 0, "box_caption": "Page 0.001", "scores": {"class_score": 0.0011692047119140625}, "domain": "pixel"}, {"position": {"minX": 246.5, "minY": 81.0, "maxX": 626.0, "maxY": 218.75}, "class_id": 0, "box_caption": "Page 0.001", "scores": {"class_score": 0.001155853271484375}, "domain": "pixel"}, {"position": {"minX": 635.0, "minY": 61.375, "maxX": 691.0, "maxY": 392.0}, "class_id": 0, "box_caption": "Page 0.001", "scores": {"class_score": 0.001155853271484375}, "domain": "pixel"}, {"position": {"minX": 82.125, "minY": 201.25, "maxX": 140.125, "maxY": 320.25}, "class_id": 0, "box_caption": "Page 0.001", "scores": {"class_score": 0.0011425018310546875}, "domain": "pixel"}, {"position": {"minX": 93.75, "minY": 214.5, "maxX": 162.0, "maxY": 333.0}, "class_id": 0, "box_caption": "Page 0.001", "scores": {"class_score": 0.0011425018310546875}, "domain": "pixel"}, {"position": {"minX": 639.5, "minY": 142.0, "maxX": 687.5, "maxY": 471.5}, "class_id": 0, "box_caption": "Page 0.001", "scores": {"class_score": 0.0011425018310546875}, "domain": "pixel"}, {"position": {"minX": 490.5, "minY": -96.5, "maxX": 751.5, "maxY": 312.75}, "class_id": 0, "box_caption": "Page 0.001", "scores": {"class_score": 0.0011339187622070312}, "domain": "pixel"}, {"position": {"minX": 394.75, "minY": 484.0, "maxX": 911.0, "maxY": 829.0}, "class_id": 0, "box_caption": "Page 0.001", "scores": {"class_score": 0.0011157989501953125}, "domain": "pixel"}, {"position": {"minX": 81.625, "minY": 275.0, "maxX": 122.375, "maxY": 295.5}, "class_id": 0, "box_caption": "Page 0.001", "scores": {"class_score": 0.0011157989501953125}, "domain": "pixel"}, {"position": {"minX": 291.25, "minY": 248.5, "maxX": 369.25, "maxY": 315.0}, "class_id": 0, "box_caption": "Page 0.001", "scores": {"class_score": 0.0010986328125}, "domain": "pixel"}, {"position": {"minX": 125.5, "minY": 531.5, "maxX": 246.75, "maxY": 659.5}, "class_id": 0, "box_caption": "Page 0.001", "scores": {"class_score": 0.0010986328125}, "domain": "pixel"}, {"position": {"minX": 59.875, "minY": 159.375, "maxX": 357.0, "maxY": 379.5}, "class_id": 0, "box_caption": "Page 0.001", "scores": {"class_score": 0.0010652542114257812}, "domain": "pixel"}, {"position": {"minX": 207.25, "minY": 40.0625, "maxX": 596.0, "maxY": 206.0}, "class_id": 0, "box_caption": "Page 0.001", "scores": {"class_score": 0.0010652542114257812}, "domain": "pixel"}, {"position": {"minX": 131.75, "minY": 232.5, "maxX": 236.0, "maxY": 332.0}, "class_id": 0, "box_caption": "Page 0.001", "scores": {"class_score": 0.0010652542114257812}, "domain": "pixel"}, {"position": {"minX": 484.5, "minY": 239.25, "maxX": 758.5, "maxY": 673.0}, "class_id": 0, "box_caption": "Page 0.001", "scores": {"class_score": 0.001056671142578125}, "domain": "pixel"}, {"position": {"minX": 200.25, "minY": 110.1875, "maxX": 287.5, "maxY": 170.375}, "class_id": 0, "box_caption": "Page 0.001", "scores": {"class_score": 0.001056671142578125}, "domain": "pixel"}, {"position": {"minX": 580.0, "minY": -45.1875, "maxX": 730.0, "maxY": 191.75}, "class_id": 0, "box_caption": "Page 0.001", "scores": {"class_score": 0.0010480880737304688}, "domain": "pixel"}, {"position": {"minX": 265.0, "minY": 249.75, "maxX": 330.0, "maxY": 283.75}, "class_id": 0, "box_caption": "Page 0.001", "scores": {"class_score": 0.0010442733764648438}, "domain": "pixel"}, {"position": {"minX": 148.25, "minY": 521.0, "maxX": 216.75, "maxY": 614.0}, "class_id": 0, "box_caption": "Page 0.001", "scores": {"class_score": 0.0010404586791992188}, "domain": "pixel"}, {"position": {"minX": 134.5, "minY": 516.0, "maxX": 193.5, "maxY": 590.0}, "class_id": 0, "box_caption": "Page 0.001", "scores": {"class_score": 0.0010204315185546875}, "domain": "pixel"}, {"position": {"minX": 536.5, "minY": 3.625, "maxX": 781.5, "maxY": 337.5}, "class_id": 0, "box_caption": "Page 0.001", "scores": {"class_score": 0.0010166168212890625}, "domain": "pixel"}, {"position": {"minX": 72.875, "minY": -14.6875, "maxX": 457.5, "maxY": 183.5}, "class_id": 0, "box_caption": "Page 0.001", "scores": {"class_score": 0.0010166168212890625}, "domain": "pixel"}, {"position": {"minX": 535.0, "minY": 512.0, "maxX": 715.0, "maxY": 665.0}, "class_id": 0, "box_caption": "Page 0.001", "scores": {"class_score": 0.0010080337524414062}, "domain": "pixel"}, {"position": {"minX": 500.0, "minY": 458.5, "maxX": 588.0, "maxY": 627.5}, "class_id": 0, "box_caption": "Page 0.001", "scores": {"class_score": 0.0010042190551757812}, "domain": "pixel"}], "class_labels": {"0": "Page"}}