{"box_data": [{"position": {"minX": 70.125, "minY": 199.625, "maxX": 158.25, "maxY": 233.125}, "class_id": 2, "box_caption": "car 0.868", "scores": {"class_score": 0.8681640625}, "domain": "pixel"}, {"position": {"minX": 34.5, "minY": -12.25, "maxX": 636.5, "maxY": 451.25}, "class_id": 4, "box_caption": "airplane 0.834", "scores": {"class_score": 0.833984375}, "domain": "pixel"}, {"position": {"minX": 532.0, "minY": 196.125, "maxX": 563.0, "maxY": 211.375}, "class_id": 2, "box_caption": "car 0.620", "scores": {"class_score": 0.61962890625}, "domain": "pixel"}, {"position": {"minX": 494.25, "minY": 197.5, "maxX": 524.0, "maxY": 211.25}, "class_id": 2, "box_caption": "car 0.619", "scores": {"class_score": 0.61865234375}, "domain": "pixel"}, {"position": {"minX": 437.0, "minY": 96.25, "maxX": 661.0, "maxY": 155.25}, "class_id": 4, "box_caption": "airplane 0.557", "scores": {"class_score": 0.55712890625}, "domain": "pixel"}, {"position": {"minX": 557.5, "minY": 182.75, "maxX": 569.5, "maxY": 190.5}, "class_id": 2, "box_caption": "car 0.360", "scores": {"class_score": 0.3603515625}, "domain": "pixel"}, {"position": {"minX": 445.0, "minY": 180.5, "maxX": 462.5, "maxY": 188.5}, "class_id": 2, "box_caption": "car 0.335", "scores": {"class_score": 0.334716796875}, "domain": "pixel"}, {"position": {"minX": 56.21875, "minY": 198.5, "maxX": 66.8125, "maxY": 214.25}, "class_id": 0, "box_caption": "person 0.287", "scores": {"class_score": 0.286865234375}, "domain": "pixel"}, {"position": {"minX": 552.0, "minY": 183.0, "maxX": 572.0, "maxY": 191.0}, "class_id": 2, "box_caption": "car 0.201", "scores": {"class_score": 0.20068359375}, "domain": "pixel"}, {"position": {"minX": 530.0, "minY": 194.5, "maxX": 565.0, "maxY": 210.25}, "class_id": 7, "box_caption": "truck 0.188", "scores": {"class_score": 0.187744140625}, "domain": "pixel"}, {"position": {"minX": 436.5, "minY": 181.0, "maxX": 455.5, "maxY": 187.75}, "class_id": 2, "box_caption": "car 0.178", "scores": {"class_score": 0.177734375}, "domain": "pixel"}, {"position": {"minX": 502.0, "minY": 184.75, "maxX": 523.0, "maxY": 194.5}, "class_id": 2, "box_caption": "car 0.161", "scores": {"class_score": 0.160888671875}, "domain": "pixel"}, {"position": {"minX": 496.0, "minY": 181.375, "maxX": 520.5, "maxY": 193.125}, "class_id": 2, "box_caption": "car 0.136", "scores": {"class_score": 0.136474609375}, "domain": "pixel"}, {"position": {"minX": 464.0, "minY": 181.875, "maxX": 478.0, "maxY": 188.875}, "class_id": 2, "box_caption": "car 0.135", "scores": {"class_score": 0.1348876953125}, "domain": "pixel"}, {"position": {"minX": 557.5, "minY": 182.75, "maxX": 569.5, "maxY": 190.5}, "class_id": 7, "box_caption": "truck 0.128", "scores": {"class_score": 0.1280517578125}, "domain": "pixel"}, {"position": {"minX": 494.25, "minY": 196.0, "maxX": 525.0, "maxY": 210.5}, "class_id": 7, "box_caption": "truck 0.121", "scores": {"class_score": 0.12066650390625}, "domain": "pixel"}, {"position": {"minX": 530.5, "minY": 198.75, "maxX": 551.5, "maxY": 210.5}, "class_id": 2, "box_caption": "car 0.120", "scores": {"class_score": 0.12017822265625}, "domain": "pixel"}, {"position": {"minX": 68.3125, "minY": 199.125, "maxX": 162.25, "maxY": 230.875}, "class_id": 7, "box_caption": "truck 0.119", "scores": {"class_score": 0.11871337890625}, "domain": "pixel"}, {"position": {"minX": 466.0, "minY": 182.75, "maxX": 480.5, "maxY": 189.75}, "class_id": 2, "box_caption": "car 0.105", "scores": {"class_score": 0.104736328125}, "domain": "pixel"}, {"position": {"minX": 496.0, "minY": 181.125, "maxX": 511.5, "maxY": 190.625}, "class_id": 2, "box_caption": "car 0.092", "scores": {"class_score": 0.09234619140625}, "domain": "pixel"}, {"position": {"minX": 50.53125, "minY": 199.0, "maxX": 62.90625, "maxY": 213.25}, "class_id": 0, "box_caption": "person 0.090", "scores": {"class_score": 0.09014892578125}, "domain": "pixel"}, {"position": {"minX": 494.75, "minY": 177.625, "maxX": 518.5, "maxY": 189.875}, "class_id": 2, "box_caption": "car 0.089", "scores": {"class_score": 0.08856201171875}, "domain": "pixel"}, {"position": {"minX": 495.25, "minY": 191.0, "maxX": 524.0, "maxY": 208.75}, "class_id": 2, "box_caption": "car 0.086", "scores": {"class_score": 0.0858154296875}, "domain": "pixel"}, {"position": {"minX": 546.0, "minY": 191.125, "maxX": 566.0, "maxY": 210.125}, "class_id": 2, "box_caption": "car 0.079", "scores": {"class_score": 0.07928466796875}, "domain": "pixel"}, {"position": {"minX": 434.25, "minY": 180.25, "maxX": 458.75, "maxY": 189.0}, "class_id": 2, "box_caption": "car 0.072", "scores": {"class_score": 0.07232666015625}, "domain": "pixel"}, {"position": {"minX": 445.0, "minY": 180.5, "maxX": 462.5, "maxY": 188.5}, "class_id": 7, "box_caption": "truck 0.070", "scores": {"class_score": 0.06964111328125}, "domain": "pixel"}, {"position": {"minX": 545.5, "minY": 184.0, "maxX": 561.5, "maxY": 191.5}, "class_id": 2, "box_caption": "car 0.069", "scores": {"class_score": 0.0687255859375}, "domain": "pixel"}, {"position": {"minX": 474.0, "minY": 183.375, "maxX": 491.0, "maxY": 190.125}, "class_id": 2, "box_caption": "car 0.068", "scores": {"class_score": 0.0675048828125}, "domain": "pixel"}, {"position": {"minX": 108.5, "minY": 190.0, "maxX": 134.75, "maxY": 200.5}, "class_id": 2, "box_caption": "car 0.067", "scores": {"class_score": 0.06658935546875}, "domain": "pixel"}, {"position": {"minX": 495.5, "minY": 180.375, "maxX": 521.5, "maxY": 193.875}, "class_id": 7, "box_caption": "truck 0.049", "scores": {"class_score": 0.048858642578125}, "domain": "pixel"}, {"position": {"minX": 50.53125, "minY": 199.0, "maxX": 62.90625, "maxY": 213.25}, "class_id": 10, "box_caption": "fire hydrant 0.048", "scores": {"class_score": 0.04833984375}, "domain": "pixel"}, {"position": {"minX": 1.75, "minY": 5.375, "maxX": 615.0, "maxY": 429.5}, "class_id": 3, "box_caption": "motorcycle 0.044", "scores": {"class_score": 0.044036865234375}, "domain": "pixel"}, {"position": {"minX": 494.75, "minY": 177.625, "maxX": 518.5, "maxY": 189.875}, "class_id": 7, "box_caption": "truck 0.044", "scores": {"class_score": 0.043670654296875}, "domain": "pixel"}, {"position": {"minX": 552.0, "minY": 183.0, "maxX": 572.0, "maxY": 191.0}, "class_id": 7, "box_caption": "truck 0.043", "scores": {"class_score": 0.04254150390625}, "domain": "pixel"}, {"position": {"minX": 436.5, "minY": 181.0, "maxX": 455.5, "maxY": 187.75}, "class_id": 7, "box_caption": "truck 0.042", "scores": {"class_score": 0.041534423828125}, "domain": "pixel"}, {"position": {"minX": 495.0, "minY": 178.75, "maxX": 523.5, "maxY": 196.75}, "class_id": 2, "box_caption": "car 0.041", "scores": {"class_score": 0.04132080078125}, "domain": "pixel"}, {"position": {"minX": 513.0, "minY": 182.875, "maxX": 533.0, "maxY": 192.375}, "class_id": 2, "box_caption": "car 0.040", "scores": {"class_score": 0.039794921875}, "domain": "pixel"}, {"position": {"minX": 502.0, "minY": 184.75, "maxX": 523.0, "maxY": 194.5}, "class_id": 7, "box_caption": "truck 0.037", "scores": {"class_score": 0.03741455078125}, "domain": "pixel"}, {"position": {"minX": 519.0, "minY": 182.25, "maxX": 536.0, "maxY": 191.5}, "class_id": 2, "box_caption": "car 0.034", "scores": {"class_score": 0.0340576171875}, "domain": "pixel"}, {"position": {"minX": 480.25, "minY": 183.25, "maxX": 499.75, "maxY": 190.0}, "class_id": 2, "box_caption": "car 0.034", "scores": {"class_score": 0.0340576171875}, "domain": "pixel"}, {"position": {"minX": 54.09375, "minY": 199.375, "maxX": 66.75, "maxY": 213.125}, "class_id": 10, "box_caption": "fire hydrant 0.034", "scores": {"class_score": 0.033905029296875}, "domain": "pixel"}, {"position": {"minX": 571.5, "minY": 197.375, "maxX": 588.5, "maxY": 204.125}, "class_id": 2, "box_caption": "car 0.033", "scores": {"class_score": 0.033447265625}, "domain": "pixel"}, {"position": {"minX": 111.25, "minY": 189.125, "maxX": 135.75, "maxY": 199.125}, "class_id": 7, "box_caption": "truck 0.032", "scores": {"class_score": 0.03204345703125}, "domain": "pixel"}, {"position": {"minX": 56.46875, "minY": 199.375, "maxX": 66.875, "maxY": 213.375}, "class_id": 26, "box_caption": "handbag 0.029", "scores": {"class_score": 0.02899169921875}, "domain": "pixel"}, {"position": {"minX": 50.875, "minY": 197.75, "maxX": 69.3125, "maxY": 214.5}, "class_id": 0, "box_caption": "person 0.029", "scores": {"class_score": 0.0289459228515625}, "domain": "pixel"}, {"position": {"minX": 142.25, "minY": 65.75, "maxX": 683.0, "maxY": 424.25}, "class_id": 4, "box_caption": "airplane 0.028", "scores": {"class_score": 0.02825927734375}, "domain": "pixel"}, {"position": {"minX": 501.0, "minY": 177.875, "maxX": 523.0, "maxY": 190.625}, "class_id": 2, "box_caption": "car 0.028", "scores": {"class_score": 0.028045654296875}, "domain": "pixel"}, {"position": {"minX": 495.0, "minY": 179.5, "maxX": 512.5, "maxY": 188.75}, "class_id": 7, "box_caption": "truck 0.027", "scores": {"class_score": 0.0265045166015625}, "domain": "pixel"}, {"position": {"minX": 371.5, "minY": 143.375, "maxX": 415.5, "maxY": 165.625}, "class_id": 0, "box_caption": "person 0.026", "scores": {"class_score": 0.025909423828125}, "domain": "pixel"}, {"position": {"minX": 589.0, "minY": 179.75, "maxX": 600.0, "maxY": 185.75}, "class_id": 2, "box_caption": "car 0.023", "scores": {"class_score": 0.023040771484375}, "domain": "pixel"}, {"position": {"minX": 545.0, "minY": 191.375, "maxX": 567.0, "maxY": 210.125}, "class_id": 7, "box_caption": "truck 0.023", "scores": {"class_score": 0.023040771484375}, "domain": "pixel"}, {"position": {"minX": 487.75, "minY": 199.875, "maxX": 551.5, "maxY": 210.375}, "class_id": 2, "box_caption": "car 0.022", "scores": {"class_score": 0.022308349609375}, "domain": "pixel"}, {"position": {"minX": 493.5, "minY": 198.75, "maxX": 525.5, "maxY": 210.5}, "class_id": 5, "box_caption": "bus 0.022", "scores": {"class_score": 0.0220184326171875}, "domain": "pixel"}, {"position": {"minX": 439.0, "minY": 177.5, "maxX": 465.5, "maxY": 189.25}, "class_id": 2, "box_caption": "car 0.022", "scores": {"class_score": 0.02191162109375}, "domain": "pixel"}, {"position": {"minX": 548.0, "minY": 184.0, "maxX": 566.0, "maxY": 189.25}, "class_id": 2, "box_caption": "car 0.022", "scores": {"class_score": 0.02191162109375}, "domain": "pixel"}, {"position": {"minX": 539.0, "minY": 188.875, "maxX": 568.0, "maxY": 203.625}, "class_id": 2, "box_caption": "car 0.022", "scores": {"class_score": 0.0217437744140625}, "domain": "pixel"}, {"position": {"minX": 121.3125, "minY": 190.125, "maxX": 133.0, "maxY": 198.125}, "class_id": 2, "box_caption": "car 0.021", "scores": {"class_score": 0.0214385986328125}, "domain": "pixel"}, {"position": {"minX": 121.3125, "minY": 190.125, "maxX": 133.0, "maxY": 198.125}, "class_id": 0, "box_caption": "person 0.021", "scores": {"class_score": 0.0209197998046875}, "domain": "pixel"}, {"position": {"minX": 75.6875, "minY": 199.25, "maxX": 162.25, "maxY": 233.0}, "class_id": 0, "box_caption": "person 0.020", "scores": {"class_score": 0.020172119140625}, "domain": "pixel"}, {"position": {"minX": 543.0, "minY": 183.75, "maxX": 563.0, "maxY": 192.5}, "class_id": 7, "box_caption": "truck 0.020", "scores": {"class_score": 0.0198211669921875}, "domain": "pixel"}, {"position": {"minX": 50.875, "minY": 199.75, "maxX": 62.75, "maxY": 212.25}, "class_id": 26, "box_caption": "handbag 0.018", "scores": {"class_score": 0.017578125}, "domain": "pixel"}, {"position": {"minX": 464.0, "minY": 181.875, "maxX": 478.0, "maxY": 188.875}, "class_id": 7, "box_caption": "truck 0.017", "scores": {"class_score": 0.0170440673828125}, "domain": "pixel"}, {"position": {"minX": 500.75, "minY": 176.875, "maxX": 523.5, "maxY": 191.375}, "class_id": 7, "box_caption": "truck 0.016", "scores": {"class_score": 0.01561737060546875}, "domain": "pixel"}, {"position": {"minX": 493.25, "minY": 178.875, "maxX": 514.5, "maxY": 189.375}, "class_id": 4, "box_caption": "airplane 0.015", "scores": {"class_score": 0.01486968994140625}, "domain": "pixel"}, {"position": {"minX": 530.5, "minY": 197.75, "maxX": 559.5, "maxY": 211.25}, "class_id": 5, "box_caption": "bus 0.015", "scores": {"class_score": 0.01482391357421875}, "domain": "pixel"}, {"position": {"minX": 434.25, "minY": 180.25, "maxX": 458.75, "maxY": 189.0}, "class_id": 7, "box_caption": "truck 0.015", "scores": {"class_score": 0.0146942138671875}, "domain": "pixel"}, {"position": {"minX": 493.5, "minY": 199.375, "maxX": 510.0, "maxY": 210.375}, "class_id": 2, "box_caption": "car 0.014", "scores": {"class_score": 0.0143890380859375}, "domain": "pixel"}, {"position": {"minX": 110.5625, "minY": 190.25, "maxX": 133.25, "maxY": 200.5}, "class_id": 0, "box_caption": "person 0.014", "scores": {"class_score": 0.01416015625}, "domain": "pixel"}, {"position": {"minX": 492.5, "minY": 177.25, "maxX": 521.0, "maxY": 190.5}, "class_id": 4, "box_caption": "airplane 0.014", "scores": {"class_score": 0.01384735107421875}, "domain": "pixel"}, {"position": {"minX": 90.9375, "minY": 291.5, "maxX": 101.1875, "maxY": 305.0}, "class_id": 0, "box_caption": "person 0.014", "scores": {"class_score": 0.013671875}, "domain": "pixel"}, {"position": {"minX": 551.5, "minY": 195.75, "maxX": 564.5, "maxY": 209.0}, "class_id": 2, "box_caption": "car 0.013", "scores": {"class_score": 0.0133819580078125}, "domain": "pixel"}, {"position": {"minX": 557.0, "minY": 183.75, "maxX": 567.0, "maxY": 194.25}, "class_id": 2, "box_caption": "car 0.013", "scores": {"class_score": 0.01294708251953125}, "domain": "pixel"}, {"position": {"minX": 119.4375, "minY": 189.5, "maxX": 135.625, "maxY": 199.25}, "class_id": 2, "box_caption": "car 0.013", "scores": {"class_score": 0.012847900390625}, "domain": "pixel"}, {"position": {"minX": 125.4375, "minY": 190.125, "maxX": 132.625, "maxY": 196.875}, "class_id": 0, "box_caption": "person 0.013", "scores": {"class_score": 0.0126190185546875}, "domain": "pixel"}, {"position": {"minX": 495.5, "minY": 191.75, "maxX": 523.0, "maxY": 207.25}, "class_id": 7, "box_caption": "truck 0.012", "scores": {"class_score": 0.012237548828125}, "domain": "pixel"}, {"position": {"minX": 498.25, "minY": 173.25, "maxX": 519.0, "maxY": 182.75}, "class_id": 2, "box_caption": "car 0.012", "scores": {"class_score": 0.0122222900390625}, "domain": "pixel"}, {"position": {"minX": 436.0, "minY": 181.25, "maxX": 449.0, "maxY": 189.25}, "class_id": 2, "box_caption": "car 0.012", "scores": {"class_score": 0.01194000244140625}, "domain": "pixel"}, {"position": {"minX": 539.0, "minY": 188.875, "maxX": 568.0, "maxY": 203.625}, "class_id": 7, "box_caption": "truck 0.012", "scores": {"class_score": 0.011932373046875}, "domain": "pixel"}, {"position": {"minX": 52.34375, "minY": 198.375, "maxX": 66.5, "maxY": 214.375}, "class_id": 1, "box_caption": "bicycle 0.012", "scores": {"class_score": 0.0118560791015625}, "domain": "pixel"}, {"position": {"minX": 295.5, "minY": 125.5, "maxX": 335.0, "maxY": 151.25}, "class_id": 0, "box_caption": "person 0.012", "scores": {"class_score": 0.01171112060546875}, "domain": "pixel"}, {"position": {"minX": 467.5, "minY": 182.375, "maxX": 481.0, "maxY": 189.375}, "class_id": 7, "box_caption": "truck 0.012", "scores": {"class_score": 0.01165008544921875}, "domain": "pixel"}, {"position": {"minX": 545.5, "minY": 183.125, "maxX": 568.5, "maxY": 190.125}, "class_id": 2, "box_caption": "car 0.011", "scores": {"class_score": 0.01141357421875}, "domain": "pixel"}, {"position": {"minX": 526.5, "minY": 183.75, "maxX": 553.5, "maxY": 193.0}, "class_id": 2, "box_caption": "car 0.011", "scores": {"class_score": 0.01129150390625}, "domain": "pixel"}, {"position": {"minX": 1.75, "minY": 5.375, "maxX": 615.0, "maxY": 429.5}, "class_id": 2, "box_caption": "car 0.010", "scores": {"class_score": 0.010406494140625}, "domain": "pixel"}, {"position": {"minX": 494.0, "minY": 181.0, "maxX": 523.0, "maxY": 193.75}, "class_id": 4, "box_caption": "airplane 0.010", "scores": {"class_score": 0.0100250244140625}, "domain": "pixel"}, {"position": {"minX": 445.0, "minY": 180.5, "maxX": 462.5, "maxY": 188.5}, "class_id": 5, "box_caption": "bus 0.010", "scores": {"class_score": 0.00958251953125}, "domain": "pixel"}, {"position": {"minX": 474.0, "minY": 183.375, "maxX": 491.0, "maxY": 190.125}, "class_id": 7, "box_caption": "truck 0.009", "scores": {"class_score": 0.009490966796875}, "domain": "pixel"}, {"position": {"minX": 124.5, "minY": 175.875, "maxX": 183.25, "maxY": 194.125}, "class_id": 7, "box_caption": "truck 0.009", "scores": {"class_score": 0.00931549072265625}, "domain": "pixel"}, {"position": {"minX": 102.4375, "minY": 176.125, "maxX": 172.25, "maxY": 197.625}, "class_id": 7, "box_caption": "truck 0.009", "scores": {"class_score": 0.00923919677734375}, "domain": "pixel"}, {"position": {"minX": 110.625, "minY": 191.625, "maxX": 136.125, "maxY": 204.625}, "class_id": 2, "box_caption": "car 0.009", "scores": {"class_score": 0.00893402099609375}, "domain": "pixel"}, {"position": {"minX": 510.5, "minY": 182.375, "maxX": 534.5, "maxY": 193.125}, "class_id": 7, "box_caption": "truck 0.009", "scores": {"class_score": 0.00876617431640625}, "domain": "pixel"}, {"position": {"minX": 608.5, "minY": 181.375, "maxX": 620.5, "maxY": 186.375}, "class_id": 2, "box_caption": "car 0.009", "scores": {"class_score": 0.0086822509765625}, "domain": "pixel"}, {"position": {"minX": 517.5, "minY": 181.875, "maxX": 537.5, "maxY": 192.625}, "class_id": 7, "box_caption": "truck 0.009", "scores": {"class_score": 0.00852203369140625}, "domain": "pixel"}, {"position": {"minX": 25.25, "minY": 13.625, "maxX": 463.5, "maxY": 386.5}, "class_id": 4, "box_caption": "airplane 0.009", "scores": {"class_score": 0.00852203369140625}, "domain": "pixel"}, {"position": {"minX": 571.5, "minY": 197.375, "maxX": 588.5, "maxY": 204.125}, "class_id": 7, "box_caption": "truck 0.008", "scores": {"class_score": 0.00844573974609375}, "domain": "pixel"}, {"position": {"minX": 17.09375, "minY": 160.75, "maxX": 124.875, "maxY": 204.75}, "class_id": 7, "box_caption": "truck 0.008", "scores": {"class_score": 0.00841522216796875}, "domain": "pixel"}, {"position": {"minX": 510.0, "minY": 201.375, "maxX": 530.0, "maxY": 209.375}, "class_id": 2, "box_caption": "car 0.008", "scores": {"class_score": 0.008392333984375}, "domain": "pixel"}, {"position": {"minX": 436.25, "minY": 58.375, "maxX": 658.0, "maxY": 156.625}, "class_id": 4, "box_caption": "airplane 0.008", "scores": {"class_score": 0.0082855224609375}, "domain": "pixel"}, {"position": {"minX": 52.34375, "minY": 198.375, "maxX": 66.5, "maxY": 214.375}, "class_id": 16, "box_caption": "dog 0.008", "scores": {"class_score": 0.0081634521484375}, "domain": "pixel"}, {"position": {"minX": 115.0, "minY": 192.375, "maxX": 131.5, "maxY": 203.125}, "class_id": 0, "box_caption": "person 0.008", "scores": {"class_score": 0.00807952880859375}, "domain": "pixel"}, {"position": {"minX": 482.5, "minY": 180.25, "maxX": 503.5, "maxY": 188.25}, "class_id": 2, "box_caption": "car 0.008", "scores": {"class_score": 0.00800323486328125}, "domain": "pixel"}, {"position": {"minX": 586.5, "minY": 179.0, "maxX": 602.5, "maxY": 186.75}, "class_id": 2, "box_caption": "car 0.008", "scores": {"class_score": 0.007701873779296875}, "domain": "pixel"}, {"position": {"minX": 367.75, "minY": 144.0, "maxX": 420.75, "maxY": 174.0}, "class_id": 0, "box_caption": "person 0.008", "scores": {"class_score": 0.007633209228515625}, "domain": "pixel"}, {"position": {"minX": 34.5, "minY": -12.25, "maxX": 636.5, "maxY": 451.25}, "class_id": 7, "box_caption": "truck 0.008", "scores": {"class_score": 0.007572174072265625}, "domain": "pixel"}, {"position": {"minX": 495.0, "minY": 177.125, "maxX": 523.0, "maxY": 198.125}, "class_id": 7, "box_caption": "truck 0.008", "scores": {"class_score": 0.007549285888671875}, "domain": "pixel"}, {"position": {"minX": 125.4375, "minY": 190.125, "maxX": 132.625, "maxY": 196.875}, "class_id": 2, "box_caption": "car 0.008", "scores": {"class_score": 0.00753021240234375}, "domain": "pixel"}, {"position": {"minX": 443.5, "minY": 180.125, "maxX": 464.5, "maxY": 188.875}, "class_id": 4, "box_caption": "airplane 0.007", "scores": {"class_score": 0.00748443603515625}, "domain": "pixel"}, {"position": {"minX": 531.5, "minY": 193.375, "maxX": 565.5, "maxY": 212.125}, "class_id": 5, "box_caption": "bus 0.007", "scores": {"class_score": 0.00742340087890625}, "domain": "pixel"}, {"position": {"minX": 607.5, "minY": 182.5, "maxX": 619.5, "maxY": 187.5}, "class_id": 2, "box_caption": "car 0.007", "scores": {"class_score": 0.007213592529296875}, "domain": "pixel"}, {"position": {"minX": 374.25, "minY": 146.125, "maxX": 409.25, "maxY": 162.125}, "class_id": 0, "box_caption": "person 0.007", "scores": {"class_score": 0.00711822509765625}, "domain": "pixel"}, {"position": {"minX": 108.0, "minY": 188.25, "maxX": 147.625, "maxY": 202.75}, "class_id": 2, "box_caption": "car 0.007", "scores": {"class_score": 0.007091522216796875}, "domain": "pixel"}, {"position": {"minX": 492.5, "minY": 192.25, "maxX": 509.5, "maxY": 202.5}, "class_id": 2, "box_caption": "car 0.007", "scores": {"class_score": 0.007022857666015625}, "domain": "pixel"}, {"position": {"minX": 464.0, "minY": 182.0, "maxX": 483.0, "maxY": 190.5}, "class_id": 7, "box_caption": "truck 0.007", "scores": {"class_score": 0.00681304931640625}, "domain": "pixel"}, {"position": {"minX": 503.0, "minY": 200.0, "maxX": 536.0, "maxY": 210.0}, "class_id": 2, "box_caption": "car 0.007", "scores": {"class_score": 0.00672149658203125}, "domain": "pixel"}, {"position": {"minX": 627.0, "minY": 181.25, "maxX": 648.0, "maxY": 187.0}, "class_id": 4, "box_caption": "airplane 0.007", "scores": {"class_score": 0.00670623779296875}, "domain": "pixel"}, {"position": {"minX": 480.25, "minY": 183.25, "maxX": 499.75, "maxY": 190.0}, "class_id": 7, "box_caption": "truck 0.007", "scores": {"class_score": 0.006572723388671875}, "domain": "pixel"}, {"position": {"minX": 636.5, "minY": 180.75, "maxX": 653.5, "maxY": 186.5}, "class_id": 4, "box_caption": "airplane 0.007", "scores": {"class_score": 0.006557464599609375}, "domain": "pixel"}, {"position": {"minX": 52.34375, "minY": 198.375, "maxX": 66.5, "maxY": 214.375}, "class_id": 3, "box_caption": "motorcycle 0.007", "scores": {"class_score": 0.00650787353515625}, "domain": "pixel"}, {"position": {"minX": 532.0, "minY": 194.375, "maxX": 564.0, "maxY": 211.125}, "class_id": 0, "box_caption": "person 0.006", "scores": {"class_score": 0.00647735595703125}, "domain": "pixel"}, {"position": {"minX": 494.25, "minY": 185.0, "maxX": 548.0, "maxY": 199.25}, "class_id": 2, "box_caption": "car 0.006", "scores": {"class_score": 0.006237030029296875}, "domain": "pixel"}, {"position": {"minX": 487.75, "minY": 199.875, "maxX": 551.5, "maxY": 210.375}, "class_id": 7, "box_caption": "truck 0.006", "scores": {"class_score": 0.006191253662109375}, "domain": "pixel"}, {"position": {"minX": 115.0, "minY": 192.375, "maxX": 131.5, "maxY": 203.125}, "class_id": 2, "box_caption": "car 0.006", "scores": {"class_score": 0.00615692138671875}, "domain": "pixel"}, {"position": {"minX": 439.0, "minY": 177.5, "maxX": 465.5, "maxY": 189.25}, "class_id": 7, "box_caption": "truck 0.006", "scores": {"class_score": 0.006145477294921875}, "domain": "pixel"}, {"position": {"minX": 105.375, "minY": 200.0, "maxX": 156.125, "maxY": 220.0}, "class_id": 2, "box_caption": "car 0.006", "scores": {"class_score": 0.006023406982421875}, "domain": "pixel"}, {"position": {"minX": 494.75, "minY": 177.625, "maxX": 518.5, "maxY": 189.875}, "class_id": 5, "box_caption": "bus 0.006", "scores": {"class_score": 0.005825042724609375}, "domain": "pixel"}, {"position": {"minX": 371.5, "minY": 143.375, "maxX": 415.5, "maxY": 165.625}, "class_id": 16, "box_caption": "dog 0.006", "scores": {"class_score": 0.005695343017578125}, "domain": "pixel"}, {"position": {"minX": 515.0, "minY": 180.625, "maxX": 534.0, "maxY": 191.375}, "class_id": 7, "box_caption": "truck 0.006", "scores": {"class_score": 0.005603790283203125}, "domain": "pixel"}, {"position": {"minX": 498.25, "minY": 173.25, "maxX": 519.0, "maxY": 182.75}, "class_id": 7, "box_caption": "truck 0.006", "scores": {"class_score": 0.005584716796875}, "domain": "pixel"}, {"position": {"minX": 53.8125, "minY": 199.625, "maxX": 65.875, "maxY": 213.125}, "class_id": 24, "box_caption": "backpack 0.006", "scores": {"class_score": 0.005573272705078125}, "domain": "pixel"}, {"position": {"minX": 496.25, "minY": 172.375, "maxX": 520.5, "maxY": 183.625}, "class_id": 4, "box_caption": "airplane 0.006", "scores": {"class_score": 0.0055694580078125}, "domain": "pixel"}, {"position": {"minX": 148.625, "minY": 177.125, "maxX": 177.875, "maxY": 194.875}, "class_id": 7, "box_caption": "truck 0.005", "scores": {"class_score": 0.005462646484375}, "domain": "pixel"}, {"position": {"minX": 571.0, "minY": 194.25, "maxX": 590.0, "maxY": 204.5}, "class_id": 2, "box_caption": "car 0.005", "scores": {"class_score": 0.00543212890625}, "domain": "pixel"}, {"position": {"minX": 54.09375, "minY": 199.375, "maxX": 66.75, "maxY": 213.125}, "class_id": 9, "box_caption": "traffic light 0.005", "scores": {"class_score": 0.0054168701171875}, "domain": "pixel"}, {"position": {"minX": 530.5, "minY": 198.75, "maxX": 551.5, "maxY": 210.5}, "class_id": 7, "box_caption": "truck 0.005", "scores": {"class_score": 0.00533294677734375}, "domain": "pixel"}, {"position": {"minX": 465.5, "minY": 181.5, "maxX": 483.0, "maxY": 190.0}, "class_id": 4, "box_caption": "airplane 0.005", "scores": {"class_score": 0.00527191162109375}, "domain": "pixel"}, {"position": {"minX": 616.0, "minY": 125.4375, "maxX": 627.0, "maxY": 144.5}, "class_id": 9, "box_caption": "traffic light 0.005", "scores": {"class_score": 0.005222320556640625}, "domain": "pixel"}, {"position": {"minX": 439.0, "minY": 40.5, "maxX": 664.0, "maxY": 301.0}, "class_id": 4, "box_caption": "airplane 0.005", "scores": {"class_score": 0.005146026611328125}, "domain": "pixel"}, {"position": {"minX": 118.0625, "minY": 201.0, "maxX": 162.25, "maxY": 214.0}, "class_id": 2, "box_caption": "car 0.005", "scores": {"class_score": 0.005146026611328125}, "domain": "pixel"}, {"position": {"minX": 110.625, "minY": 191.625, "maxX": 136.125, "maxY": 204.625}, "class_id": 0, "box_caption": "person 0.005", "scores": {"class_score": 0.005126953125}, "domain": "pixel"}, {"position": {"minX": 495.5, "minY": 180.0, "maxX": 512.0, "maxY": 191.5}, "class_id": 4, "box_caption": "airplane 0.005", "scores": {"class_score": 0.00511932373046875}, "domain": "pixel"}, {"position": {"minX": 620.5, "minY": 179.625, "maxX": 651.5, "maxY": 188.125}, "class_id": 4, "box_caption": "airplane 0.005", "scores": {"class_score": 0.005084991455078125}, "domain": "pixel"}, {"position": {"minX": 579.5, "minY": 199.125, "maxX": 588.5, "maxY": 204.375}, "class_id": 2, "box_caption": "car 0.005", "scores": {"class_score": 0.00506591796875}, "domain": "pixel"}, {"position": {"minX": 636.5, "minY": 180.75, "maxX": 653.5, "maxY": 186.5}, "class_id": 2, "box_caption": "car 0.005", "scores": {"class_score": 0.00489044189453125}, "domain": "pixel"}, {"position": {"minX": 460.5, "minY": 181.0, "maxX": 478.5, "maxY": 189.75}, "class_id": 4, "box_caption": "airplane 0.005", "scores": {"class_score": 0.00489044189453125}, "domain": "pixel"}, {"position": {"minX": 70.75, "minY": 201.0, "maxX": 157.375, "maxY": 231.5}, "class_id": 4, "box_caption": "airplane 0.005", "scores": {"class_score": 0.0048370361328125}, "domain": "pixel"}, {"position": {"minX": 384.75, "minY": 145.375, "maxX": 417.75, "maxY": 170.125}, "class_id": 0, "box_caption": "person 0.005", "scores": {"class_score": 0.00475311279296875}, "domain": "pixel"}, {"position": {"minX": 548.0, "minY": 184.0, "maxX": 566.0, "maxY": 189.25}, "class_id": 7, "box_caption": "truck 0.005", "scores": {"class_score": 0.004673004150390625}, "domain": "pixel"}, {"position": {"minX": 295.25, "minY": 129.5, "maxX": 321.25, "maxY": 151.0}, "class_id": 0, "box_caption": "person 0.005", "scores": {"class_score": 0.004657745361328125}, "domain": "pixel"}, {"position": {"minX": 617.0, "minY": 129.25, "maxX": 626.0, "maxY": 142.75}, "class_id": 9, "box_caption": "traffic light 0.005", "scores": {"class_score": 0.004627227783203125}, "domain": "pixel"}, {"position": {"minX": 123.5, "minY": 189.0, "maxX": 136.0, "maxY": 197.5}, "class_id": 7, "box_caption": "truck 0.005", "scores": {"class_score": 0.004566192626953125}, "domain": "pixel"}, {"position": {"minX": 523.0, "minY": 182.875, "maxX": 556.0, "maxY": 194.625}, "class_id": 7, "box_caption": "truck 0.005", "scores": {"class_score": 0.004558563232421875}, "domain": "pixel"}, {"position": {"minX": 125.4375, "minY": 190.125, "maxX": 132.625, "maxY": 196.875}, "class_id": 7, "box_caption": "truck 0.005", "scores": {"class_score": 0.004543304443359375}, "domain": "pixel"}, {"position": {"minX": 88.9375, "minY": 193.75, "maxX": 144.5, "maxY": 212.5}, "class_id": 2, "box_caption": "car 0.005", "scores": {"class_score": 0.0045166015625}, "domain": "pixel"}, {"position": {"minX": 53.8125, "minY": 199.625, "maxX": 65.875, "maxY": 213.125}, "class_id": 28, "box_caption": "suitcase 0.004", "scores": {"class_score": 0.00449371337890625}, "domain": "pixel"}, {"position": {"minX": 311.5, "minY": 122.625, "maxX": 335.5, "maxY": 149.125}, "class_id": 0, "box_caption": "person 0.004", "scores": {"class_score": 0.00441741943359375}, "domain": "pixel"}, {"position": {"minX": 413.5, "minY": 110.9375, "maxX": 420.0, "maxY": 119.0625}, "class_id": 9, "box_caption": "traffic light 0.004", "scores": {"class_score": 0.00440216064453125}, "domain": "pixel"}, {"position": {"minX": 108.0, "minY": 188.25, "maxX": 147.625, "maxY": 202.75}, "class_id": 7, "box_caption": "truck 0.004", "scores": {"class_score": 0.004375457763671875}, "domain": "pixel"}, {"position": {"minX": 644.0, "minY": 180.625, "maxX": 655.0, "maxY": 186.375}, "class_id": 4, "box_caption": "airplane 0.004", "scores": {"class_score": 0.00437164306640625}, "domain": "pixel"}, {"position": {"minX": 627.0, "minY": 180.25, "maxX": 647.0, "maxY": 185.75}, "class_id": 2, "box_caption": "car 0.004", "scores": {"class_score": 0.004344940185546875}, "domain": "pixel"}, {"position": {"minX": 545.5, "minY": 183.125, "maxX": 568.5, "maxY": 190.125}, "class_id": 7, "box_caption": "truck 0.004", "scores": {"class_score": 0.00434112548828125}, "domain": "pixel"}, {"position": {"minX": 546.5, "minY": 191.625, "maxX": 565.5, "maxY": 209.375}, "class_id": 0, "box_caption": "person 0.004", "scores": {"class_score": 0.004291534423828125}, "domain": "pixel"}, {"position": {"minX": 609.5, "minY": 179.25, "maxX": 648.5, "maxY": 189.25}, "class_id": 4, "box_caption": "airplane 0.004", "scores": {"class_score": 0.00424957275390625}, "domain": "pixel"}, {"position": {"minX": 586.0, "minY": 182.0, "maxX": 596.0, "maxY": 188.0}, "class_id": 2, "box_caption": "car 0.004", "scores": {"class_score": 0.00421905517578125}, "domain": "pixel"}, {"position": {"minX": 526.5, "minY": 200.625, "maxX": 538.5, "maxY": 209.625}, "class_id": 2, "box_caption": "car 0.004", "scores": {"class_score": 0.00414276123046875}, "domain": "pixel"}, {"position": {"minX": 136.875, "minY": 203.25, "maxX": 156.125, "maxY": 211.75}, "class_id": 2, "box_caption": "car 0.004", "scores": {"class_score": 0.004058837890625}, "domain": "pixel"}, {"position": {"minX": 495.5, "minY": 180.375, "maxX": 521.5, "maxY": 193.875}, "class_id": 5, "box_caption": "bus 0.004", "scores": {"class_score": 0.004039764404296875}, "domain": "pixel"}, {"position": {"minX": 50.875, "minY": 199.75, "maxX": 62.75, "maxY": 212.25}, "class_id": 2, "box_caption": "car 0.004", "scores": {"class_score": 0.00396728515625}, "domain": "pixel"}, {"position": {"minX": 502.25, "minY": 185.25, "maxX": 526.0, "maxY": 197.25}, "class_id": 5, "box_caption": "bus 0.004", "scores": {"class_score": 0.003917694091796875}, "domain": "pixel"}, {"position": {"minX": 633.5, "minY": 179.625, "maxX": 656.5, "maxY": 187.625}, "class_id": 4, "box_caption": "airplane 0.004", "scores": {"class_score": 0.00391387939453125}, "domain": "pixel"}, {"position": {"minX": 353.0, "minY": 140.375, "maxX": 415.0, "maxY": 157.625}, "class_id": 0, "box_caption": "person 0.004", "scores": {"class_score": 0.0038928985595703125}, "domain": "pixel"}, {"position": {"minX": 50.875, "minY": 199.75, "maxX": 62.75, "maxY": 212.25}, "class_id": 58, "box_caption": "potted plant 0.004", "scores": {"class_score": 0.0038013458251953125}, "domain": "pixel"}, {"position": {"minX": 559.0, "minY": 182.875, "maxX": 570.0, "maxY": 190.375}, "class_id": 0, "box_caption": "person 0.004", "scores": {"class_score": 0.003795623779296875}, "domain": "pixel"}, {"position": {"minX": 495.0, "minY": 179.5, "maxX": 512.5, "maxY": 188.75}, "class_id": 5, "box_caption": "bus 0.004", "scores": {"class_score": 0.00376129150390625}, "domain": "pixel"}, {"position": {"minX": 119.4375, "minY": 189.5, "maxX": 135.625, "maxY": 199.25}, "class_id": 0, "box_caption": "person 0.004", "scores": {"class_score": 0.0037403106689453125}, "domain": "pixel"}, {"position": {"minX": 617.0, "minY": 181.0, "maxX": 643.0, "maxY": 187.5}, "class_id": 4, "box_caption": "airplane 0.004", "scores": {"class_score": 0.003734588623046875}, "domain": "pixel"}, {"position": {"minX": 592.0, "minY": 180.0, "maxX": 609.0, "maxY": 186.0}, "class_id": 2, "box_caption": "car 0.004", "scores": {"class_score": 0.00363922119140625}, "domain": "pixel"}, {"position": {"minX": 121.75, "minY": 197.5, "maxX": 144.75, "maxY": 210.5}, "class_id": 0, "box_caption": "person 0.004", "scores": {"class_score": 0.00360870361328125}, "domain": "pixel"}, {"position": {"minX": 644.0, "minY": 180.625, "maxX": 655.0, "maxY": 186.375}, "class_id": 2, "box_caption": "car 0.004", "scores": {"class_score": 0.0035915374755859375}, "domain": "pixel"}, {"position": {"minX": 529.5, "minY": 189.5, "maxX": 565.5, "maxY": 212.5}, "class_id": 4, "box_caption": "airplane 0.004", "scores": {"class_score": 0.003582000732421875}, "domain": "pixel"}, {"position": {"minX": 514.0, "minY": 181.75, "maxX": 559.0, "maxY": 207.5}, "class_id": 7, "box_caption": "truck 0.004", "scores": {"class_score": 0.0035266876220703125}, "domain": "pixel"}, {"position": {"minX": 123.5, "minY": 189.0, "maxX": 136.0, "maxY": 197.5}, "class_id": 0, "box_caption": "person 0.004", "scores": {"class_score": 0.0035190582275390625}, "domain": "pixel"}, {"position": {"minX": 436.5, "minY": 179.25, "maxX": 447.0, "maxY": 187.25}, "class_id": 2, "box_caption": "car 0.004", "scores": {"class_score": 0.0035076141357421875}, "domain": "pixel"}, {"position": {"minX": 514.0, "minY": 181.75, "maxX": 559.0, "maxY": 207.5}, "class_id": 2, "box_caption": "car 0.003", "scores": {"class_score": 0.003498077392578125}, "domain": "pixel"}, {"position": {"minX": 120.75, "minY": 189.375, "maxX": 133.75, "maxY": 199.125}, "class_id": 7, "box_caption": "truck 0.003", "scores": {"class_score": 0.003414154052734375}, "domain": "pixel"}, {"position": {"minX": 184.5, "minY": 19.5, "maxX": 668.0, "maxY": 288.0}, "class_id": 4, "box_caption": "airplane 0.003", "scores": {"class_score": 0.0033893585205078125}, "domain": "pixel"}, {"position": {"minX": 557.5, "minY": 182.75, "maxX": 569.5, "maxY": 190.5}, "class_id": 5, "box_caption": "bus 0.003", "scores": {"class_score": 0.0033855438232421875}, "domain": "pixel"}, {"position": {"minX": 487.75, "minY": 199.875, "maxX": 551.5, "maxY": 210.375}, "class_id": 5, "box_caption": "bus 0.003", "scores": {"class_score": 0.00335693359375}, "domain": "pixel"}, {"position": {"minX": 568.0, "minY": 192.5, "maxX": 588.0, "maxY": 203.25}, "class_id": 2, "box_caption": "car 0.003", "scores": {"class_score": 0.003353118896484375}, "domain": "pixel"}, {"position": {"minX": 187.5, "minY": 180.5, "maxX": 205.0, "maxY": 191.5}, "class_id": 2, "box_caption": "car 0.003", "scores": {"class_score": 0.0033111572265625}, "domain": "pixel"}, {"position": {"minX": 482.5, "minY": 180.25, "maxX": 503.5, "maxY": 188.25}, "class_id": 7, "box_caption": "truck 0.003", "scores": {"class_score": 0.0032749176025390625}, "domain": "pixel"}, {"position": {"minX": 552.5, "minY": 181.5, "maxX": 575.5, "maxY": 194.25}, "class_id": 7, "box_caption": "truck 0.003", "scores": {"class_score": 0.0032253265380859375}, "domain": "pixel"}, {"position": {"minX": 129.25, "minY": -45.125, "maxX": 672.0, "maxY": 414.0}, "class_id": 0, "box_caption": "person 0.003", "scores": {"class_score": 0.0031871795654296875}, "domain": "pixel"}, {"position": {"minX": 34.5, "minY": -12.25, "maxX": 636.5, "maxY": 451.25}, "class_id": 5, "box_caption": "bus 0.003", "scores": {"class_score": 0.0031337738037109375}, "domain": "pixel"}, {"position": {"minX": 456.75, "minY": 176.375, "maxX": 488.25, "maxY": 189.375}, "class_id": 2, "box_caption": "car 0.003", "scores": {"class_score": 0.0031223297119140625}, "domain": "pixel"}, {"position": {"minX": 431.5, "minY": 101.5, "maxX": 652.5, "maxY": 242.0}, "class_id": 4, "box_caption": "airplane 0.003", "scores": {"class_score": 0.00312042236328125}, "domain": "pixel"}, {"position": {"minX": 52.4375, "minY": 198.125, "maxX": 66.3125, "maxY": 213.875}, "class_id": 7, "box_caption": "truck 0.003", "scores": {"class_score": 0.003108978271484375}, "domain": "pixel"}, {"position": {"minX": 47.25, "minY": 162.0, "maxX": 165.75, "maxY": 208.5}, "class_id": 7, "box_caption": "truck 0.003", "scores": {"class_score": 0.003101348876953125}, "domain": "pixel"}, {"position": {"minX": 149.375, "minY": 178.375, "maxX": 169.625, "maxY": 192.625}, "class_id": 7, "box_caption": "truck 0.003", "scores": {"class_score": 0.0030574798583984375}, "domain": "pixel"}, {"position": {"minX": 160.25, "minY": 185.75, "maxX": 179.5, "maxY": 196.5}, "class_id": 7, "box_caption": "truck 0.003", "scores": {"class_score": 0.00302886962890625}, "domain": "pixel"}, {"position": {"minX": 53.21875, "minY": 198.5, "maxX": 66.1875, "maxY": 214.0}, "class_id": 12, "box_caption": "parking meter 0.003", "scores": {"class_score": 0.00302886962890625}, "domain": "pixel"}, {"position": {"minX": 412.5, "minY": 109.4375, "maxX": 420.5, "maxY": 120.8125}, "class_id": 9, "box_caption": "traffic light 0.003", "scores": {"class_score": 0.0030078887939453125}, "domain": "pixel"}, {"position": {"minX": 50.875, "minY": 199.75, "maxX": 62.75, "maxY": 212.25}, "class_id": 24, "box_caption": "backpack 0.003", "scores": {"class_score": 0.00296783447265625}, "domain": "pixel"}, {"position": {"minX": 512.5, "minY": 183.875, "maxX": 552.5, "maxY": 197.875}, "class_id": 2, "box_caption": "car 0.003", "scores": {"class_score": 0.0029659271240234375}, "domain": "pixel"}, {"position": {"minX": 476.5, "minY": 175.375, "maxX": 514.5, "maxY": 189.625}, "class_id": 2, "box_caption": "car 0.003", "scores": {"class_score": 0.00295257568359375}, "domain": "pixel"}, {"position": {"minX": 110.5625, "minY": 187.625, "maxX": 144.0, "maxY": 203.875}, "class_id": 0, "box_caption": "person 0.003", "scores": {"class_score": 0.0029296875}, "domain": "pixel"}, {"position": {"minX": 135.0, "minY": 200.25, "maxX": 158.25, "maxY": 215.5}, "class_id": 2, "box_caption": "car 0.003", "scores": {"class_score": 0.0029125213623046875}, "domain": "pixel"}, {"position": {"minX": 436.5, "minY": 181.0, "maxX": 455.5, "maxY": 187.75}, "class_id": 5, "box_caption": "bus 0.003", "scores": {"class_score": 0.002910614013671875}, "domain": "pixel"}, {"position": {"minX": 126.4375, "minY": 202.375, "maxX": 155.25, "maxY": 212.625}, "class_id": 2, "box_caption": "car 0.003", "scores": {"class_score": 0.0029048919677734375}, "domain": "pixel"}, {"position": {"minX": 522.5, "minY": 182.25, "maxX": 536.5, "maxY": 190.25}, "class_id": 7, "box_caption": "truck 0.003", "scores": {"class_score": 0.00289154052734375}, "domain": "pixel"}, {"position": {"minX": 348.0, "minY": 143.125, "maxX": 416.0, "maxY": 168.625}, "class_id": 0, "box_caption": "person 0.003", "scores": {"class_score": 0.0028820037841796875}, "domain": "pixel"}, {"position": {"minX": 110.75, "minY": 190.0, "maxX": 129.375, "maxY": 198.25}, "class_id": 2, "box_caption": "car 0.003", "scores": {"class_score": 0.002864837646484375}, "domain": "pixel"}, {"position": {"minX": 611.5, "minY": 182.375, "maxX": 624.5, "maxY": 187.625}, "class_id": 2, "box_caption": "car 0.003", "scores": {"class_score": 0.0028629302978515625}, "domain": "pixel"}, {"position": {"minX": 66.9375, "minY": 196.875, "maxX": 150.5, "maxY": 221.625}, "class_id": 2, "box_caption": "car 0.003", "scores": {"class_score": 0.0028514862060546875}, "domain": "pixel"}, {"position": {"minX": 550.0, "minY": 195.25, "maxX": 566.0, "maxY": 209.25}, "class_id": 7, "box_caption": "truck 0.003", "scores": {"class_score": 0.0028438568115234375}, "domain": "pixel"}, {"position": {"minX": 486.75, "minY": 195.0, "maxX": 518.5, "maxY": 207.75}, "class_id": 2, "box_caption": "car 0.003", "scores": {"class_score": 0.0028171539306640625}, "domain": "pixel"}, {"position": {"minX": 552.5, "minY": 181.5, "maxX": 575.5, "maxY": 194.25}, "class_id": 2, "box_caption": "car 0.003", "scores": {"class_score": 0.0027675628662109375}, "domain": "pixel"}, {"position": {"minX": 50.75, "minY": 200.125, "maxX": 60.0, "maxY": 212.375}, "class_id": 1, "box_caption": "bicycle 0.003", "scores": {"class_score": 0.00274658203125}, "domain": "pixel"}, {"position": {"minX": 50.875, "minY": 199.75, "maxX": 62.75, "maxY": 212.25}, "class_id": 28, "box_caption": "suitcase 0.003", "scores": {"class_score": 0.0026874542236328125}, "domain": "pixel"}, {"position": {"minX": 511.0, "minY": 186.375, "maxX": 532.0, "maxY": 196.875}, "class_id": 2, "box_caption": "car 0.003", "scores": {"class_score": 0.00267791748046875}, "domain": "pixel"}, {"position": {"minX": 118.1875, "minY": 197.5, "maxX": 148.875, "maxY": 211.0}, "class_id": 2, "box_caption": "car 0.003", "scores": {"class_score": 0.002674102783203125}, "domain": "pixel"}, {"position": {"minX": 477.75, "minY": 185.375, "maxX": 489.75, "maxY": 192.125}, "class_id": 2, "box_caption": "car 0.003", "scores": {"class_score": 0.00263214111328125}, "domain": "pixel"}, {"position": {"minX": 191.875, "minY": 69.25, "maxX": 656.5, "maxY": 185.75}, "class_id": 4, "box_caption": "airplane 0.003", "scores": {"class_score": 0.0026187896728515625}, "domain": "pixel"}, {"position": {"minX": 351.25, "minY": 97.375, "maxX": 358.25, "maxY": 104.625}, "class_id": 0, "box_caption": "person 0.003", "scores": {"class_score": 0.00260162353515625}, "domain": "pixel"}, {"position": {"minX": 108.5, "minY": 190.0, "maxX": 134.75, "maxY": 200.5}, "class_id": 5, "box_caption": "bus 0.003", "scores": {"class_score": 0.0025882720947265625}, "domain": "pixel"}, {"position": {"minX": 578.0, "minY": 193.375, "maxX": 588.0, "maxY": 203.125}, "class_id": 2, "box_caption": "car 0.003", "scores": {"class_score": 0.0025882720947265625}, "domain": "pixel"}, {"position": {"minX": 589.0, "minY": 179.75, "maxX": 600.0, "maxY": 185.75}, "class_id": 7, "box_caption": "truck 0.003", "scores": {"class_score": 0.0025653839111328125}, "domain": "pixel"}, {"position": {"minX": 500.75, "minY": 176.875, "maxX": 523.5, "maxY": 191.375}, "class_id": 5, "box_caption": "bus 0.003", "scores": {"class_score": 0.0025463104248046875}, "domain": "pixel"}, {"position": {"minX": 617.0, "minY": 181.0, "maxX": 643.0, "maxY": 187.5}, "class_id": 2, "box_caption": "car 0.003", "scores": {"class_score": 0.002544403076171875}, "domain": "pixel"}, {"position": {"minX": 605.5, "minY": 180.125, "maxX": 623.5, "maxY": 187.875}, "class_id": 2, "box_caption": "car 0.003", "scores": {"class_score": 0.0025348663330078125}, "domain": "pixel"}, {"position": {"minX": 110.3125, "minY": 190.375, "maxX": 131.875, "maxY": 201.625}, "class_id": 7, "box_caption": "truck 0.003", "scores": {"class_score": 0.0025310516357421875}, "domain": "pixel"}, {"position": {"minX": 436.0, "minY": 181.25, "maxX": 449.0, "maxY": 189.25}, "class_id": 7, "box_caption": "truck 0.002", "scores": {"class_score": 0.0024890899658203125}, "domain": "pixel"}, {"position": {"minX": 609.0, "minY": 182.125, "maxX": 622.0, "maxY": 187.625}, "class_id": 4, "box_caption": "airplane 0.002", "scores": {"class_score": 0.0024662017822265625}, "domain": "pixel"}, {"position": {"minX": 606.5, "minY": 180.75, "maxX": 626.5, "maxY": 189.25}, "class_id": 4, "box_caption": "airplane 0.002", "scores": {"class_score": 0.0024509429931640625}, "domain": "pixel"}, {"position": {"minX": 54.09375, "minY": 199.375, "maxX": 66.75, "maxY": 213.125}, "class_id": 58, "box_caption": "potted plant 0.002", "scores": {"class_score": 0.002445220947265625}, "domain": "pixel"}, {"position": {"minX": 464.0, "minY": 181.875, "maxX": 478.0, "maxY": 188.875}, "class_id": 5, "box_caption": "bus 0.002", "scores": {"class_score": 0.0024261474609375}, "domain": "pixel"}, {"position": {"minX": 54.40625, "minY": 196.875, "maxX": 66.875, "maxY": 209.625}, "class_id": 0, "box_caption": "person 0.002", "scores": {"class_score": 0.002422332763671875}, "domain": "pixel"}, {"position": {"minX": 495.0, "minY": 177.125, "maxX": 523.0, "maxY": 198.125}, "class_id": 4, "box_caption": "airplane 0.002", "scores": {"class_score": 0.002414703369140625}, "domain": "pixel"}, {"position": {"minX": 283.0, "minY": 89.375, "maxX": 669.5, "maxY": 160.125}, "class_id": 4, "box_caption": "airplane 0.002", "scores": {"class_score": 0.002361297607421875}, "domain": "pixel"}, {"position": {"minX": 7.25, "minY": 235.0, "maxX": 672.0, "maxY": 440.0}, "class_id": 4, "box_caption": "airplane 0.002", "scores": {"class_score": 0.0023555755615234375}, "domain": "pixel"}, {"position": {"minX": 58.8125, "minY": 200.5, "maxX": 66.8125, "maxY": 213.75}, "class_id": 10, "box_caption": "fire hydrant 0.002", "scores": {"class_score": 0.0023326873779296875}, "domain": "pixel"}, {"position": {"minX": 496.75, "minY": 172.125, "maxX": 532.0, "maxY": 190.625}, "class_id": 4, "box_caption": "airplane 0.002", "scores": {"class_score": 0.002323150634765625}, "domain": "pixel"}, {"position": {"minX": 496.0, "minY": 181.375, "maxX": 520.5, "maxY": 193.125}, "class_id": 0, "box_caption": "person 0.002", "scores": {"class_score": 0.0023040771484375}, "domain": "pixel"}, {"position": {"minX": 123.5, "minY": 189.0, "maxX": 136.0, "maxY": 197.5}, "class_id": 2, "box_caption": "car 0.002", "scores": {"class_score": 0.0023040771484375}, "domain": "pixel"}, {"position": {"minX": 522.5, "minY": 186.125, "maxX": 542.5, "maxY": 196.375}, "class_id": 2, "box_caption": "car 0.002", "scores": {"class_score": 0.0022220611572265625}, "domain": "pixel"}, {"position": {"minX": 291.5, "minY": 129.0, "maxX": 327.5, "maxY": 156.75}, "class_id": 0, "box_caption": "person 0.002", "scores": {"class_score": 0.0022106170654296875}, "domain": "pixel"}, {"position": {"minX": 161.5, "minY": 186.75, "maxX": 178.0, "maxY": 195.75}, "class_id": 0, "box_caption": "person 0.002", "scores": {"class_score": 0.00217437744140625}, "domain": "pixel"}, {"position": {"minX": 433.5, "minY": 178.625, "maxX": 459.5, "maxY": 193.875}, "class_id": 2, "box_caption": "car 0.002", "scores": {"class_score": 0.00211334228515625}, "domain": "pixel"}, {"position": {"minX": 50.875, "minY": 199.75, "maxX": 62.75, "maxY": 212.25}, "class_id": 11, "box_caption": "stop sign 0.002", "scores": {"class_score": 0.0020923614501953125}, "domain": "pixel"}, {"position": {"minX": 494.25, "minY": 185.0, "maxX": 548.0, "maxY": 199.25}, "class_id": 7, "box_caption": "truck 0.002", "scores": {"class_score": 0.0020885467529296875}, "domain": "pixel"}, {"position": {"minX": 496.0, "minY": 181.125, "maxX": 511.5, "maxY": 190.625}, "class_id": 0, "box_caption": "person 0.002", "scores": {"class_score": 0.002086639404296875}, "domain": "pixel"}, {"position": {"minX": 1.75, "minY": 5.375, "maxX": 615.0, "maxY": 429.5}, "class_id": 61, "box_caption": "toilet 0.002", "scores": {"class_score": 0.002048492431640625}, "domain": "pixel"}, {"position": {"minX": 237.5, "minY": 158.25, "maxX": 249.0, "maxY": 166.5}, "class_id": 2, "box_caption": "car 0.002", "scores": {"class_score": 0.0020198822021484375}, "domain": "pixel"}, {"position": {"minX": 161.5, "minY": 186.75, "maxX": 178.0, "maxY": 195.75}, "class_id": 2, "box_caption": "car 0.002", "scores": {"class_score": 0.0020198822021484375}, "domain": "pixel"}, {"position": {"minX": 477.75, "minY": 182.5, "maxX": 501.75, "maxY": 190.75}, "class_id": 5, "box_caption": "bus 0.002", "scores": {"class_score": 0.0020046234130859375}, "domain": "pixel"}, {"position": {"minX": 113.5, "minY": 182.375, "maxX": 177.5, "maxY": 209.375}, "class_id": 7, "box_caption": "truck 0.002", "scores": {"class_score": 0.002002716064453125}, "domain": "pixel"}, {"position": {"minX": 604.5, "minY": 173.125, "maxX": 658.5, "maxY": 189.125}, "class_id": 4, "box_caption": "airplane 0.002", "scores": {"class_score": 0.00199127197265625}, "domain": "pixel"}, {"position": {"minX": 503.75, "minY": 185.75, "maxX": 524.5, "maxY": 196.0}, "class_id": 0, "box_caption": "person 0.002", "scores": {"class_score": 0.00199127197265625}, "domain": "pixel"}, {"position": {"minX": 557.0, "minY": 179.25, "maxX": 580.0, "maxY": 189.75}, "class_id": 7, "box_caption": "truck 0.002", "scores": {"class_score": 0.0019855499267578125}, "domain": "pixel"}, {"position": {"minX": 558.5, "minY": 180.75, "maxX": 577.5, "maxY": 189.25}, "class_id": 2, "box_caption": "car 0.002", "scores": {"class_score": 0.0019702911376953125}, "domain": "pixel"}, {"position": {"minX": 351.75, "minY": 97.375, "maxX": 358.25, "maxY": 104.375}, "class_id": 9, "box_caption": "traffic light 0.002", "scores": {"class_score": 0.0019683837890625}, "domain": "pixel"}, {"position": {"minX": 467.5, "minY": 182.375, "maxX": 481.0, "maxY": 189.375}, "class_id": 5, "box_caption": "bus 0.002", "scores": {"class_score": 0.0019626617431640625}, "domain": "pixel"}, {"position": {"minX": 453.5, "minY": 35.0, "maxX": 647.5, "maxY": 454.0}, "class_id": 4, "box_caption": "airplane 0.002", "scores": {"class_score": 0.0019521713256835938}, "domain": "pixel"}, {"position": {"minX": 474.0, "minY": 183.375, "maxX": 491.0, "maxY": 190.125}, "class_id": 5, "box_caption": "bus 0.002", "scores": {"class_score": 0.0019435882568359375}, "domain": "pixel"}, {"position": {"minX": 53.8125, "minY": 199.625, "maxX": 65.875, "maxY": 213.125}, "class_id": 36, "box_caption": "skateboard 0.002", "scores": {"class_score": 0.0019330978393554688}, "domain": "pixel"}, {"position": {"minX": 546.0, "minY": 191.125, "maxX": 566.0, "maxY": 210.125}, "class_id": 5, "box_caption": "bus 0.002", "scores": {"class_score": 0.0019130706787109375}, "domain": "pixel"}, {"position": {"minX": 157.875, "minY": 169.25, "maxX": 166.625, "maxY": 174.75}, "class_id": 9, "box_caption": "traffic light 0.002", "scores": {"class_score": 0.0018777847290039062}, "domain": "pixel"}, {"position": {"minX": 49.0625, "minY": 198.625, "maxX": 62.0625, "maxY": 213.625}, "class_id": 1, "box_caption": "bicycle 0.002", "scores": {"class_score": 0.0018596649169921875}, "domain": "pixel"}, {"position": {"minX": 123.3125, "minY": 198.625, "maxX": 141.375, "maxY": 208.875}, "class_id": 2, "box_caption": "car 0.002", "scores": {"class_score": 0.0018587112426757812}, "domain": "pixel"}, {"position": {"minX": 608.5, "minY": 181.375, "maxX": 620.5, "maxY": 186.375}, "class_id": 4, "box_caption": "airplane 0.002", "scores": {"class_score": 0.00185394287109375}, "domain": "pixel"}, {"position": {"minX": 461.25, "minY": 120.125, "maxX": 639.0, "maxY": 221.625}, "class_id": 4, "box_caption": "airplane 0.002", "scores": {"class_score": 0.0018434524536132812}, "domain": "pixel"}, {"position": {"minX": 120.0625, "minY": 201.875, "maxX": 143.125, "maxY": 217.625}, "class_id": 0, "box_caption": "person 0.002", "scores": {"class_score": 0.0018434524536132812}, "domain": "pixel"}, {"position": {"minX": 150.5, "minY": 178.5, "maxX": 177.0, "maxY": 193.75}, "class_id": 0, "box_caption": "person 0.002", "scores": {"class_score": 0.0018281936645507812}, "domain": "pixel"}, {"position": {"minX": 371.0, "minY": 144.5, "maxX": 421.5, "maxY": 172.75}, "class_id": 4, "box_caption": "airplane 0.002", "scores": {"class_score": 0.0018186569213867188}, "domain": "pixel"}, {"position": {"minX": 445.0, "minY": 180.5, "maxX": 462.5, "maxY": 188.5}, "class_id": 8, "box_caption": "boat 0.002", "scores": {"class_score": 0.0017824172973632812}, "domain": "pixel"}, {"position": {"minX": 113.0, "minY": 200.625, "maxX": 149.25, "maxY": 218.875}, "class_id": 0, "box_caption": "person 0.002", "scores": {"class_score": 0.0017786026000976562}, "domain": "pixel"}, {"position": {"minX": 545.5, "minY": 184.0, "maxX": 561.5, "maxY": 191.5}, "class_id": 5, "box_caption": "bus 0.002", "scores": {"class_score": 0.0017766952514648438}, "domain": "pixel"}, {"position": {"minX": 495.0, "minY": 177.125, "maxX": 523.0, "maxY": 198.125}, "class_id": 5, "box_caption": "bus 0.002", "scores": {"class_score": 0.0017366409301757812}, "domain": "pixel"}, {"position": {"minX": 439.0, "minY": 99.1875, "maxX": 659.0, "maxY": 152.5}, "class_id": 71, "box_caption": "sink 0.002", "scores": {"class_score": 0.0017337799072265625}, "domain": "pixel"}, {"position": {"minX": 589.0, "minY": 179.125, "maxX": 613.0, "maxY": 186.625}, "class_id": 2, "box_caption": "car 0.002", "scores": {"class_score": 0.0017251968383789062}, "domain": "pixel"}, {"position": {"minX": 52.34375, "minY": 198.375, "maxX": 66.5, "maxY": 214.375}, "class_id": 2, "box_caption": "car 0.002", "scores": {"class_score": 0.0017232894897460938}, "domain": "pixel"}, {"position": {"minX": 86.6875, "minY": 168.125, "maxX": 192.5, "maxY": 201.875}, "class_id": 7, "box_caption": "truck 0.002", "scores": {"class_score": 0.0017213821411132812}, "domain": "pixel"}, {"position": {"minX": 34.5, "minY": -12.25, "maxX": 636.5, "maxY": 451.25}, "class_id": 6, "box_caption": "train 0.002", "scores": {"class_score": 0.0016870498657226562}, "domain": "pixel"}, {"position": {"minX": 494.75, "minY": 199.0, "maxX": 524.0, "maxY": 210.25}, "class_id": 0, "box_caption": "person 0.002", "scores": {"class_score": 0.0016679763793945312}, "domain": "pixel"}, {"position": {"minX": 120.0625, "minY": 201.875, "maxX": 143.125, "maxY": 217.625}, "class_id": 2, "box_caption": "car 0.002", "scores": {"class_score": 0.0016613006591796875}, "domain": "pixel"}, {"position": {"minX": 15.75, "minY": 159.875, "maxX": 101.8125, "maxY": 202.375}, "class_id": 4, "box_caption": "airplane 0.002", "scores": {"class_score": 0.0016384124755859375}, "domain": "pixel"}, {"position": {"minX": 473.5, "minY": 171.875, "maxX": 511.5, "maxY": 188.875}, "class_id": 4, "box_caption": "airplane 0.002", "scores": {"class_score": 0.00162506103515625}, "domain": "pixel"}, {"position": {"minX": 492.25, "minY": 199.25, "maxX": 512.5, "maxY": 210.5}, "class_id": 7, "box_caption": "truck 0.002", "scores": {"class_score": 0.0016193389892578125}, "domain": "pixel"}, {"position": {"minX": 89.9375, "minY": 201.625, "maxX": 148.5, "maxY": 230.375}, "class_id": 2, "box_caption": "car 0.002", "scores": {"class_score": 0.0016040802001953125}, "domain": "pixel"}, {"position": {"minX": 493.75, "minY": 179.5, "maxX": 522.0, "maxY": 207.5}, "class_id": 4, "box_caption": "airplane 0.002", "scores": {"class_score": 0.0016002655029296875}, "domain": "pixel"}, {"position": {"minX": 571.0, "minY": 194.25, "maxX": 590.0, "maxY": 204.5}, "class_id": 7, "box_caption": "truck 0.002", "scores": {"class_score": 0.0015888214111328125}, "domain": "pixel"}, {"position": {"minX": 107.0625, "minY": 195.0, "maxX": 121.4375, "maxY": 207.0}, "class_id": 0, "box_caption": "person 0.002", "scores": {"class_score": 0.0015869140625}, "domain": "pixel"}, {"position": {"minX": 510.5, "minY": 182.375, "maxX": 534.5, "maxY": 193.125}, "class_id": 5, "box_caption": "bus 0.002", "scores": {"class_score": 0.00157928466796875}, "domain": "pixel"}, {"position": {"minX": 576.5, "minY": 197.875, "maxX": 591.5, "maxY": 204.875}, "class_id": 2, "box_caption": "car 0.002", "scores": {"class_score": 0.00157928466796875}, "domain": "pixel"}, {"position": {"minX": 68.3125, "minY": 199.125, "maxX": 162.25, "maxY": 230.875}, "class_id": 5, "box_caption": "bus 0.002", "scores": {"class_score": 0.0015535354614257812}, "domain": "pixel"}, {"position": {"minX": 110.5625, "minY": 190.25, "maxX": 133.25, "maxY": 200.5}, "class_id": 12, "box_caption": "parking meter 0.002", "scores": {"class_score": 0.0015439987182617188}, "domain": "pixel"}, {"position": {"minX": 88.9375, "minY": 193.75, "maxX": 144.5, "maxY": 212.5}, "class_id": 0, "box_caption": "person 0.002", "scores": {"class_score": 0.0015153884887695312}, "domain": "pixel"}, {"position": {"minX": 461.25, "minY": 120.125, "maxX": 639.0, "maxY": 221.625}, "class_id": 7, "box_caption": "truck 0.002", "scores": {"class_score": 0.001506805419921875}, "domain": "pixel"}, {"position": {"minX": 102.125, "minY": 194.0, "maxX": 130.25, "maxY": 210.25}, "class_id": 2, "box_caption": "car 0.002", "scores": {"class_score": 0.001506805419921875}, "domain": "pixel"}, {"position": {"minX": 496.75, "minY": 172.125, "maxX": 532.0, "maxY": 190.625}, "class_id": 2, "box_caption": "car 0.001", "scores": {"class_score": 0.0014934539794921875}, "domain": "pixel"}, {"position": {"minX": 477.75, "minY": 182.5, "maxX": 501.75, "maxY": 190.75}, "class_id": 4, "box_caption": "airplane 0.001", "scores": {"class_score": 0.0014791488647460938}, "domain": "pixel"}], "class_labels": {"0": "person", "1": "bicycle", "2": "car", "3": "motorcycle", "4": "airplane", "5": "bus", "6": "train", "7": "truck", "8": "boat", "9": "traffic light", "10": "fire hydrant", "11": "stop sign", "12": "parking meter", "13": "bench", "14": "bird", "15": "cat", "16": "dog", "17": "horse", "18": "sheep", "19": "cow", "20": "elephant", "21": "bear", "22": "zebra", "23": "giraffe", "24": "backpack", "25": "umbrella", "26": "handbag", "27": "tie", "28": "suitcase", "29": "frisbee", "30": "skis", "31": "snowboard", "32": "sports ball", "33": "kite", "34": "baseball bat", "35": "baseball glove", "36": "skateboard", "37": "surfboard", "38": "tennis racket", "39": "bottle", "40": "wine glass", "41": "cup", "42": "fork", "43": "knife", "44": "spoon", "45": "bowl", "46": "banana", "47": "apple", "48": "sandwich", "49": "orange", "50": "broccoli", "51": "carrot", "52": "hot dog", "53": "pizza", "54": "donut", "55": "cake", "56": "chair", "57": "couch", "58": "potted plant", "59": "bed", "60": "dining table", "61": "toilet", "62": "tv", "63": "laptop", "64": "mouse", "65": "remote", "66": "keyboard", "67": "cell phone", "68": "microwave", "69": "oven", "70": "toaster", "71": "sink", "72": "refrigerator", "73": "book", "74": "clock", "75": "vase", "76": "scissors", "77": "teddy bear", "78": "hair drier", "79": "toothbrush"}}