{"box_data": [{"position": {"minX": 72.3125, "minY": 198.5, "maxX": 153.75, "maxY": 234.25}, "class_id": 2, "box_caption": "car 0.875", "scores": {"class_score": 0.87548828125}, "domain": "pixel"}, {"position": {"minX": 436.75, "minY": 100.875, "maxX": 656.5, "maxY": 159.125}, "class_id": 4, "box_caption": "airplane 0.564", "scores": {"class_score": 0.56396484375}, "domain": "pixel"}, {"position": {"minX": 24.75, "minY": 52.625, "maxX": 609.0, "maxY": 431.0}, "class_id": 3, "box_caption": "motorcycle 0.526", "scores": {"class_score": 0.52587890625}, "domain": "pixel"}, {"position": {"minX": 44.25, "minY": 67.75, "maxX": 643.0, "maxY": 432.25}, "class_id": 4, "box_caption": "airplane 0.479", "scores": {"class_score": 0.479248046875}, "domain": "pixel"}, {"position": {"minX": 532.5, "minY": 195.75, "maxX": 564.5, "maxY": 211.0}, "class_id": 7, "box_caption": "truck 0.251", "scores": {"class_score": 0.25146484375}, "domain": "pixel"}, {"position": {"minX": 495.5, "minY": 198.625, "maxX": 523.0, "maxY": 210.625}, "class_id": 2, "box_caption": "car 0.245", "scores": {"class_score": 0.2451171875}, "domain": "pixel"}, {"position": {"minX": 533.5, "minY": 195.875, "maxX": 564.5, "maxY": 210.875}, "class_id": 2, "box_caption": "car 0.243", "scores": {"class_score": 0.2430419921875}, "domain": "pixel"}, {"position": {"minX": 56.75, "minY": 199.625, "maxX": 66.125, "maxY": 213.625}, "class_id": 0, "box_caption": "person 0.242", "scores": {"class_score": 0.2421875}, "domain": "pixel"}, {"position": {"minX": 512.5, "minY": 194.625, "maxX": 565.5, "maxY": 210.375}, "class_id": 7, "box_caption": "truck 0.206", "scores": {"class_score": 0.2061767578125}, "domain": "pixel"}, {"position": {"minX": 445.25, "minY": 180.375, "maxX": 462.25, "maxY": 188.375}, "class_id": 2, "box_caption": "car 0.186", "scores": {"class_score": 0.18603515625}, "domain": "pixel"}, {"position": {"minX": 495.0, "minY": 198.5, "maxX": 523.0, "maxY": 210.5}, "class_id": 7, "box_caption": "truck 0.174", "scores": {"class_score": 0.1744384765625}, "domain": "pixel"}, {"position": {"minX": 493.75, "minY": 193.75, "maxX": 554.5, "maxY": 210.0}, "class_id": 7, "box_caption": "truck 0.161", "scores": {"class_score": 0.161376953125}, "domain": "pixel"}, {"position": {"minX": 558.5, "minY": 183.375, "maxX": 569.5, "maxY": 190.625}, "class_id": 2, "box_caption": "car 0.139", "scores": {"class_score": 0.13916015625}, "domain": "pixel"}, {"position": {"minX": 436.25, "minY": 181.625, "maxX": 456.25, "maxY": 188.125}, "class_id": 2, "box_caption": "car 0.110", "scores": {"class_score": 0.110107421875}, "domain": "pixel"}, {"position": {"minX": 489.25, "minY": 187.625, "maxX": 561.5, "maxY": 208.875}, "class_id": 7, "box_caption": "truck 0.100", "scores": {"class_score": 0.10003662109375}, "domain": "pixel"}, {"position": {"minX": 558.5, "minY": 183.375, "maxX": 569.5, "maxY": 190.625}, "class_id": 7, "box_caption": "truck 0.100", "scores": {"class_score": 0.09991455078125}, "domain": "pixel"}, {"position": {"minX": 50.5, "minY": 199.875, "maxX": 61.75, "maxY": 213.125}, "class_id": 0, "box_caption": "person 0.099", "scores": {"class_score": 0.0986328125}, "domain": "pixel"}, {"position": {"minX": 110.5, "minY": 190.5, "maxX": 133.375, "maxY": 200.5}, "class_id": 2, "box_caption": "car 0.092", "scores": {"class_score": 0.0919189453125}, "domain": "pixel"}, {"position": {"minX": 445.25, "minY": 180.375, "maxX": 462.25, "maxY": 188.375}, "class_id": 7, "box_caption": "truck 0.078", "scores": {"class_score": 0.07830810546875}, "domain": "pixel"}, {"position": {"minX": 69.8125, "minY": 199.375, "maxX": 150.5, "maxY": 232.625}, "class_id": 7, "box_caption": "truck 0.074", "scores": {"class_score": 0.07415771484375}, "domain": "pixel"}, {"position": {"minX": 53.46875, "minY": 197.625, "maxX": 66.375, "maxY": 214.875}, "class_id": 0, "box_caption": "person 0.069", "scores": {"class_score": 0.06939697265625}, "domain": "pixel"}, {"position": {"minX": 464.25, "minY": 181.625, "maxX": 479.25, "maxY": 188.875}, "class_id": 2, "box_caption": "car 0.068", "scores": {"class_score": 0.06768798828125}, "domain": "pixel"}, {"position": {"minX": 495.5, "minY": 196.0, "maxX": 563.5, "maxY": 210.0}, "class_id": 2, "box_caption": "car 0.065", "scores": {"class_score": 0.06451416015625}, "domain": "pixel"}, {"position": {"minX": 15.1875, "minY": 163.625, "maxX": 106.6875, "maxY": 207.375}, "class_id": 7, "box_caption": "truck 0.061", "scores": {"class_score": 0.0609130859375}, "domain": "pixel"}, {"position": {"minX": 492.0, "minY": 186.0, "maxX": 566.0, "maxY": 209.5}, "class_id": 5, "box_caption": "bus 0.054", "scores": {"class_score": 0.053741455078125}, "domain": "pixel"}, {"position": {"minX": 50.71875, "minY": 199.5, "maxX": 61.53125, "maxY": 213.5}, "class_id": 10, "box_caption": "fire hydrant 0.054", "scores": {"class_score": 0.0535888671875}, "domain": "pixel"}, {"position": {"minX": 14.5, "minY": 4.75, "maxX": 590.0, "maxY": 446.75}, "class_id": 7, "box_caption": "truck 0.045", "scores": {"class_score": 0.044891357421875}, "domain": "pixel"}, {"position": {"minX": 512.5, "minY": 194.625, "maxX": 565.5, "maxY": 210.375}, "class_id": 5, "box_caption": "bus 0.045", "scores": {"class_score": 0.044677734375}, "domain": "pixel"}, {"position": {"minX": 437.0, "minY": 94.0, "maxX": 656.0, "maxY": 193.0}, "class_id": 4, "box_caption": "airplane 0.044", "scores": {"class_score": 0.043975830078125}, "domain": "pixel"}, {"position": {"minX": 436.25, "minY": 181.625, "maxX": 456.25, "maxY": 188.125}, "class_id": 7, "box_caption": "truck 0.040", "scores": {"class_score": 0.040283203125}, "domain": "pixel"}, {"position": {"minX": 111.625, "minY": 190.0, "maxX": 135.875, "maxY": 199.25}, "class_id": 7, "box_caption": "truck 0.040", "scores": {"class_score": 0.0401611328125}, "domain": "pixel"}, {"position": {"minX": 492.75, "minY": 176.875, "maxX": 520.5, "maxY": 189.875}, "class_id": 4, "box_caption": "airplane 0.039", "scores": {"class_score": 0.039276123046875}, "domain": "pixel"}, {"position": {"minX": 486.5, "minY": 172.75, "maxX": 520.0, "maxY": 188.5}, "class_id": 4, "box_caption": "airplane 0.038", "scores": {"class_score": 0.03814697265625}, "domain": "pixel"}, {"position": {"minX": 495.75, "minY": 180.125, "maxX": 522.0, "maxY": 192.625}, "class_id": 4, "box_caption": "airplane 0.038", "scores": {"class_score": 0.03778076171875}, "domain": "pixel"}, {"position": {"minX": 143.875, "minY": 175.25, "maxX": 179.625, "maxY": 194.75}, "class_id": 7, "box_caption": "truck 0.036", "scores": {"class_score": 0.03631591796875}, "domain": "pixel"}, {"position": {"minX": 52.34375, "minY": 199.375, "maxX": 66.25, "maxY": 213.875}, "class_id": 10, "box_caption": "fire hydrant 0.035", "scores": {"class_score": 0.03509521484375}, "domain": "pixel"}, {"position": {"minX": 495.25, "minY": 192.5, "maxX": 523.0, "maxY": 209.0}, "class_id": 7, "box_caption": "truck 0.034", "scores": {"class_score": 0.034332275390625}, "domain": "pixel"}, {"position": {"minX": 372.5, "minY": 142.875, "maxX": 414.5, "maxY": 166.125}, "class_id": 0, "box_caption": "person 0.034", "scores": {"class_score": 0.03363037109375}, "domain": "pixel"}, {"position": {"minX": 467.5, "minY": 182.75, "maxX": 481.5, "maxY": 189.25}, "class_id": 2, "box_caption": "car 0.032", "scores": {"class_score": 0.0323486328125}, "domain": "pixel"}, {"position": {"minX": 14.5, "minY": 4.75, "maxX": 590.0, "maxY": 446.75}, "class_id": 2, "box_caption": "car 0.032", "scores": {"class_score": 0.0322265625}, "domain": "pixel"}, {"position": {"minX": 493.75, "minY": 193.75, "maxX": 554.5, "maxY": 210.0}, "class_id": 5, "box_caption": "bus 0.032", "scores": {"class_score": 0.03216552734375}, "domain": "pixel"}, {"position": {"minX": 514.0, "minY": 194.625, "maxX": 559.0, "maxY": 209.375}, "class_id": 2, "box_caption": "car 0.032", "scores": {"class_score": 0.03192138671875}, "domain": "pixel"}, {"position": {"minX": 90.8125, "minY": 290.75, "maxX": 100.9375, "maxY": 305.25}, "class_id": 0, "box_caption": "person 0.030", "scores": {"class_score": 0.0302734375}, "domain": "pixel"}, {"position": {"minX": 544.5, "minY": 191.875, "maxX": 565.5, "maxY": 209.875}, "class_id": 7, "box_caption": "truck 0.030", "scores": {"class_score": 0.0297393798828125}, "domain": "pixel"}, {"position": {"minX": 495.25, "minY": 192.5, "maxX": 523.0, "maxY": 209.0}, "class_id": 2, "box_caption": "car 0.029", "scores": {"class_score": 0.02947998046875}, "domain": "pixel"}, {"position": {"minX": 545.5, "minY": 192.125, "maxX": 565.5, "maxY": 209.875}, "class_id": 2, "box_caption": "car 0.029", "scores": {"class_score": 0.0294036865234375}, "domain": "pixel"}, {"position": {"minX": 471.25, "minY": 183.125, "maxX": 492.75, "maxY": 190.375}, "class_id": 2, "box_caption": "car 0.029", "scores": {"class_score": 0.02935791015625}, "domain": "pixel"}, {"position": {"minX": 491.5, "minY": 183.875, "maxX": 555.5, "maxY": 208.625}, "class_id": 4, "box_caption": "airplane 0.028", "scores": {"class_score": 0.0282745361328125}, "domain": "pixel"}, {"position": {"minX": 445.0, "minY": 180.125, "maxX": 462.5, "maxY": 188.375}, "class_id": 4, "box_caption": "airplane 0.028", "scores": {"class_score": 0.0279541015625}, "domain": "pixel"}, {"position": {"minX": 530.5, "minY": 198.5, "maxX": 552.5, "maxY": 211.25}, "class_id": 2, "box_caption": "car 0.028", "scores": {"class_score": 0.02764892578125}, "domain": "pixel"}, {"position": {"minX": 492.0, "minY": 186.0, "maxX": 566.0, "maxY": 209.5}, "class_id": 2, "box_caption": "car 0.027", "scores": {"class_score": 0.0269775390625}, "domain": "pixel"}, {"position": {"minX": 476.0, "minY": 171.75, "maxX": 590.0, "maxY": 208.25}, "class_id": 4, "box_caption": "airplane 0.026", "scores": {"class_score": 0.02606201171875}, "domain": "pixel"}, {"position": {"minX": 53.5, "minY": 199.5, "maxX": 65.625, "maxY": 213.75}, "class_id": 3, "box_caption": "motorcycle 0.026", "scores": {"class_score": 0.0256805419921875}, "domain": "pixel"}, {"position": {"minX": 604.5, "minY": 178.0, "maxX": 652.5, "maxY": 189.5}, "class_id": 4, "box_caption": "airplane 0.025", "scores": {"class_score": 0.025299072265625}, "domain": "pixel"}, {"position": {"minX": 109.75, "minY": 185.125, "maxX": 136.5, "maxY": 200.625}, "class_id": 7, "box_caption": "truck 0.023", "scores": {"class_score": 0.0233306884765625}, "domain": "pixel"}, {"position": {"minX": 493.25, "minY": 179.75, "maxX": 515.0, "maxY": 190.75}, "class_id": 4, "box_caption": "airplane 0.023", "scores": {"class_score": 0.0225982666015625}, "domain": "pixel"}, {"position": {"minX": 118.625, "minY": 190.375, "maxX": 133.125, "maxY": 198.875}, "class_id": 0, "box_caption": "person 0.022", "scores": {"class_score": 0.022491455078125}, "domain": "pixel"}, {"position": {"minX": 103.875, "minY": 174.25, "maxX": 174.375, "maxY": 197.75}, "class_id": 7, "box_caption": "truck 0.022", "scores": {"class_score": 0.0220947265625}, "domain": "pixel"}, {"position": {"minX": 111.0, "minY": 190.5, "maxX": 133.125, "maxY": 200.5}, "class_id": 0, "box_caption": "person 0.021", "scores": {"class_score": 0.021453857421875}, "domain": "pixel"}, {"position": {"minX": 499.0, "minY": 187.5, "maxX": 530.0, "maxY": 202.25}, "class_id": 7, "box_caption": "truck 0.021", "scores": {"class_score": 0.0213623046875}, "domain": "pixel"}, {"position": {"minX": 56.75, "minY": 199.625, "maxX": 66.125, "maxY": 213.625}, "class_id": 26, "box_caption": "handbag 0.021", "scores": {"class_score": 0.0210418701171875}, "domain": "pixel"}, {"position": {"minX": 461.75, "minY": 181.5, "maxX": 478.25, "maxY": 189.25}, "class_id": 4, "box_caption": "airplane 0.021", "scores": {"class_score": 0.02056884765625}, "domain": "pixel"}, {"position": {"minX": 495.75, "minY": 180.625, "maxX": 520.5, "maxY": 192.625}, "class_id": 2, "box_caption": "car 0.021", "scores": {"class_score": 0.0205535888671875}, "domain": "pixel"}, {"position": {"minX": 499.0, "minY": 180.75, "maxX": 564.0, "maxY": 198.25}, "class_id": 4, "box_caption": "airplane 0.020", "scores": {"class_score": 0.020416259765625}, "domain": "pixel"}, {"position": {"minX": 492.25, "minY": 181.0, "maxX": 555.5, "maxY": 197.0}, "class_id": 7, "box_caption": "truck 0.020", "scores": {"class_score": 0.01995849609375}, "domain": "pixel"}, {"position": {"minX": 496.0, "minY": 180.125, "maxX": 521.5, "maxY": 192.625}, "class_id": 7, "box_caption": "truck 0.019", "scores": {"class_score": 0.0194244384765625}, "domain": "pixel"}, {"position": {"minX": 530.5, "minY": 197.75, "maxX": 560.5, "maxY": 210.75}, "class_id": 5, "box_caption": "bus 0.019", "scores": {"class_score": 0.019317626953125}, "domain": "pixel"}, {"position": {"minX": 464.25, "minY": 181.625, "maxX": 479.25, "maxY": 188.875}, "class_id": 7, "box_caption": "truck 0.019", "scores": {"class_score": 0.01861572265625}, "domain": "pixel"}, {"position": {"minX": 494.75, "minY": 198.875, "maxX": 527.5, "maxY": 210.125}, "class_id": 5, "box_caption": "bus 0.018", "scores": {"class_score": 0.0182952880859375}, "domain": "pixel"}, {"position": {"minX": 296.75, "minY": 123.9375, "maxX": 334.25, "maxY": 151.375}, "class_id": 0, "box_caption": "person 0.018", "scores": {"class_score": 0.018157958984375}, "domain": "pixel"}, {"position": {"minX": 43.625, "minY": 198.625, "maxX": 73.4375, "maxY": 214.125}, "class_id": 7, "box_caption": "truck 0.018", "scores": {"class_score": 0.0180511474609375}, "domain": "pixel"}, {"position": {"minX": 118.625, "minY": 190.375, "maxX": 133.125, "maxY": 198.875}, "class_id": 2, "box_caption": "car 0.018", "scores": {"class_score": 0.0176544189453125}, "domain": "pixel"}, {"position": {"minX": 466.75, "minY": 182.125, "maxX": 482.25, "maxY": 189.375}, "class_id": 4, "box_caption": "airplane 0.017", "scores": {"class_score": 0.0173492431640625}, "domain": "pixel"}, {"position": {"minX": 537.0, "minY": 186.625, "maxX": 568.0, "maxY": 203.375}, "class_id": 7, "box_caption": "truck 0.017", "scores": {"class_score": 0.0171661376953125}, "domain": "pixel"}, {"position": {"minX": 74.75, "minY": 201.125, "maxX": 152.5, "maxY": 234.375}, "class_id": 0, "box_caption": "person 0.017", "scores": {"class_score": 0.0170745849609375}, "domain": "pixel"}, {"position": {"minX": 571.5, "minY": 196.625, "maxX": 588.5, "maxY": 204.375}, "class_id": 2, "box_caption": "car 0.017", "scores": {"class_score": 0.0169677734375}, "domain": "pixel"}, {"position": {"minX": 571.5, "minY": 196.625, "maxX": 588.5, "maxY": 204.375}, "class_id": 7, "box_caption": "truck 0.016", "scores": {"class_score": 0.0164947509765625}, "domain": "pixel"}, {"position": {"minX": 493.5, "minY": 176.75, "maxX": 520.0, "maxY": 190.0}, "class_id": 7, "box_caption": "truck 0.016", "scores": {"class_score": 0.0163116455078125}, "domain": "pixel"}, {"position": {"minX": 523.5, "minY": 189.25, "maxX": 561.5, "maxY": 210.25}, "class_id": 7, "box_caption": "truck 0.016", "scores": {"class_score": 0.01617431640625}, "domain": "pixel"}, {"position": {"minX": 437.25, "minY": 178.0, "maxX": 465.75, "maxY": 189.5}, "class_id": 2, "box_caption": "car 0.016", "scores": {"class_score": 0.016082763671875}, "domain": "pixel"}, {"position": {"minX": 113.0625, "minY": 192.0, "maxX": 133.0, "maxY": 204.25}, "class_id": 2, "box_caption": "car 0.016", "scores": {"class_score": 0.0159759521484375}, "domain": "pixel"}, {"position": {"minX": 50.9375, "minY": 197.375, "maxX": 67.0625, "maxY": 214.625}, "class_id": 7, "box_caption": "truck 0.015", "scores": {"class_score": 0.01470947265625}, "domain": "pixel"}, {"position": {"minX": 500.0, "minY": 184.5, "maxX": 523.5, "maxY": 194.0}, "class_id": 2, "box_caption": "car 0.015", "scores": {"class_score": 0.014556884765625}, "domain": "pixel"}, {"position": {"minX": 372.5, "minY": 142.875, "maxX": 414.5, "maxY": 166.125}, "class_id": 16, "box_caption": "dog 0.014", "scores": {"class_score": 0.0140380859375}, "domain": "pixel"}, {"position": {"minX": 24.5, "minY": 23.25, "maxX": 454.5, "maxY": 362.75}, "class_id": 4, "box_caption": "airplane 0.014", "scores": {"class_score": 0.0139923095703125}, "domain": "pixel"}, {"position": {"minX": 114.25, "minY": 192.25, "maxX": 131.5, "maxY": 203.25}, "class_id": 0, "box_caption": "person 0.014", "scores": {"class_score": 0.0135345458984375}, "domain": "pixel"}, {"position": {"minX": 446.25, "minY": 117.375, "maxX": 652.0, "maxY": 225.625}, "class_id": 4, "box_caption": "airplane 0.013", "scores": {"class_score": 0.0132598876953125}, "domain": "pixel"}, {"position": {"minX": 471.0, "minY": 170.5, "maxX": 518.5, "maxY": 188.5}, "class_id": 4, "box_caption": "airplane 0.013", "scores": {"class_score": 0.013031005859375}, "domain": "pixel"}, {"position": {"minX": 50.5, "minY": 199.875, "maxX": 61.75, "maxY": 213.125}, "class_id": 2, "box_caption": "car 0.013", "scores": {"class_score": 0.0127410888671875}, "domain": "pixel"}, {"position": {"minX": 536.0, "minY": 193.25, "maxX": 565.0, "maxY": 210.25}, "class_id": 0, "box_caption": "person 0.012", "scores": {"class_score": 0.0121612548828125}, "domain": "pixel"}, {"position": {"minX": 596.0, "minY": 174.375, "maxX": 658.0, "maxY": 190.375}, "class_id": 4, "box_caption": "airplane 0.012", "scores": {"class_score": 0.0120849609375}, "domain": "pixel"}, {"position": {"minX": 499.25, "minY": 184.375, "maxX": 527.0, "maxY": 194.625}, "class_id": 7, "box_caption": "truck 0.012", "scores": {"class_score": 0.01203155517578125}, "domain": "pixel"}, {"position": {"minX": 620.5, "minY": 179.75, "maxX": 652.5, "maxY": 187.5}, "class_id": 4, "box_caption": "airplane 0.012", "scores": {"class_score": 0.011932373046875}, "domain": "pixel"}, {"position": {"minX": 534.0, "minY": 182.875, "maxX": 564.0, "maxY": 192.625}, "class_id": 7, "box_caption": "truck 0.011", "scores": {"class_score": 0.0114593505859375}, "domain": "pixel"}, {"position": {"minX": 475.0, "minY": 175.375, "maxX": 513.5, "maxY": 189.375}, "class_id": 4, "box_caption": "airplane 0.011", "scores": {"class_score": 0.01139068603515625}, "domain": "pixel"}, {"position": {"minX": 499.5, "minY": 187.75, "maxX": 526.5, "maxY": 201.25}, "class_id": 2, "box_caption": "car 0.011", "scores": {"class_score": 0.0113067626953125}, "domain": "pixel"}, {"position": {"minX": 471.25, "minY": 183.125, "maxX": 492.75, "maxY": 190.375}, "class_id": 7, "box_caption": "truck 0.011", "scores": {"class_score": 0.011260986328125}, "domain": "pixel"}, {"position": {"minX": 475.75, "minY": 181.875, "maxX": 507.25, "maxY": 190.875}, "class_id": 4, "box_caption": "airplane 0.011", "scores": {"class_score": 0.0111541748046875}, "domain": "pixel"}, {"position": {"minX": 53.5625, "minY": 199.75, "maxX": 65.6875, "maxY": 213.75}, "class_id": 28, "box_caption": "suitcase 0.011", "scores": {"class_score": 0.01108551025390625}, "domain": "pixel"}, {"position": {"minX": 291.0, "minY": 117.875, "maxX": 342.0, "maxY": 153.875}, "class_id": 0, "box_caption": "person 0.011", "scores": {"class_score": 0.01070404052734375}, "domain": "pixel"}, {"position": {"minX": 471.0, "minY": 182.75, "maxX": 495.0, "maxY": 190.5}, "class_id": 4, "box_caption": "airplane 0.011", "scores": {"class_score": 0.01058197021484375}, "domain": "pixel"}, {"position": {"minX": 494.0, "minY": 180.125, "maxX": 513.5, "maxY": 190.625}, "class_id": 2, "box_caption": "car 0.011", "scores": {"class_score": 0.0105133056640625}, "domain": "pixel"}, {"position": {"minX": 437.75, "minY": 177.625, "maxX": 467.25, "maxY": 189.125}, "class_id": 4, "box_caption": "airplane 0.010", "scores": {"class_score": 0.01043701171875}, "domain": "pixel"}, {"position": {"minX": 530.5, "minY": 198.5, "maxX": 552.5, "maxY": 211.25}, "class_id": 7, "box_caption": "truck 0.010", "scores": {"class_score": 0.01013946533203125}, "domain": "pixel"}, {"position": {"minX": 109.4375, "minY": 187.25, "maxX": 154.25, "maxY": 204.5}, "class_id": 2, "box_caption": "car 0.010", "scores": {"class_score": 0.01012420654296875}, "domain": "pixel"}, {"position": {"minX": 116.3125, "minY": 199.5, "maxX": 163.125, "maxY": 214.75}, "class_id": 2, "box_caption": "car 0.010", "scores": {"class_score": 0.01003265380859375}, "domain": "pixel"}, {"position": {"minX": 50.5, "minY": 199.875, "maxX": 61.75, "maxY": 213.125}, "class_id": 58, "box_caption": "potted plant 0.010", "scores": {"class_score": 0.01000213623046875}, "domain": "pixel"}, {"position": {"minX": 492.25, "minY": 181.0, "maxX": 555.5, "maxY": 197.0}, "class_id": 2, "box_caption": "car 0.010", "scores": {"class_score": 0.0099639892578125}, "domain": "pixel"}, {"position": {"minX": 467.5, "minY": 182.75, "maxX": 481.5, "maxY": 189.25}, "class_id": 7, "box_caption": "truck 0.010", "scores": {"class_score": 0.00988006591796875}, "domain": "pixel"}, {"position": {"minX": 493.5, "minY": 176.75, "maxX": 520.0, "maxY": 190.0}, "class_id": 2, "box_caption": "car 0.010", "scores": {"class_score": 0.00983428955078125}, "domain": "pixel"}, {"position": {"minX": 493.75, "minY": 193.75, "maxX": 554.5, "maxY": 210.0}, "class_id": 4, "box_caption": "airplane 0.010", "scores": {"class_score": 0.00966644287109375}, "domain": "pixel"}, {"position": {"minX": 352.75, "minY": 144.625, "maxX": 413.25, "maxY": 167.125}, "class_id": 0, "box_caption": "person 0.010", "scores": {"class_score": 0.0095367431640625}, "domain": "pixel"}, {"position": {"minX": 15.125, "minY": 163.25, "maxX": 97.125, "maxY": 205.75}, "class_id": 4, "box_caption": "airplane 0.009", "scores": {"class_score": 0.009429931640625}, "domain": "pixel"}, {"position": {"minX": 375.75, "minY": 143.625, "maxX": 410.25, "maxY": 160.375}, "class_id": 0, "box_caption": "person 0.009", "scores": {"class_score": 0.009368896484375}, "domain": "pixel"}, {"position": {"minX": 630.5, "minY": 180.125, "maxX": 655.5, "maxY": 187.125}, "class_id": 4, "box_caption": "airplane 0.009", "scores": {"class_score": 0.00919342041015625}, "domain": "pixel"}, {"position": {"minX": 477.25, "minY": 182.5, "maxX": 503.75, "maxY": 190.5}, "class_id": 2, "box_caption": "car 0.009", "scores": {"class_score": 0.00910186767578125}, "domain": "pixel"}, {"position": {"minX": 549.5, "minY": 179.125, "maxX": 584.5, "maxY": 194.875}, "class_id": 7, "box_caption": "truck 0.009", "scores": {"class_score": 0.0090179443359375}, "domain": "pixel"}, {"position": {"minX": 494.0, "minY": 180.125, "maxX": 513.5, "maxY": 190.625}, "class_id": 7, "box_caption": "truck 0.009", "scores": {"class_score": 0.0089263916015625}, "domain": "pixel"}, {"position": {"minX": 499.25, "minY": 184.375, "maxX": 527.0, "maxY": 194.625}, "class_id": 4, "box_caption": "airplane 0.009", "scores": {"class_score": 0.0087738037109375}, "domain": "pixel"}, {"position": {"minX": 435.25, "minY": 181.25, "maxX": 450.25, "maxY": 189.5}, "class_id": 2, "box_caption": "car 0.009", "scores": {"class_score": 0.0086212158203125}, "domain": "pixel"}, {"position": {"minX": 475.75, "minY": 181.875, "maxX": 507.25, "maxY": 190.875}, "class_id": 7, "box_caption": "truck 0.009", "scores": {"class_score": 0.00855255126953125}, "domain": "pixel"}, {"position": {"minX": 50.34375, "minY": 199.5, "maxX": 62.28125, "maxY": 213.5}, "class_id": 7, "box_caption": "truck 0.009", "scores": {"class_score": 0.00852203369140625}, "domain": "pixel"}, {"position": {"minX": 521.5, "minY": 188.5, "maxX": 563.5, "maxY": 210.5}, "class_id": 2, "box_caption": "car 0.009", "scores": {"class_score": 0.00850677490234375}, "domain": "pixel"}, {"position": {"minX": 50.5, "minY": 199.875, "maxX": 61.75, "maxY": 213.125}, "class_id": 26, "box_caption": "handbag 0.008", "scores": {"class_score": 0.008209228515625}, "domain": "pixel"}, {"position": {"minX": 449.0, "minY": 175.5, "maxX": 498.5, "maxY": 189.25}, "class_id": 4, "box_caption": "airplane 0.008", "scores": {"class_score": 0.008148193359375}, "domain": "pixel"}, {"position": {"minX": 123.125, "minY": 189.875, "maxX": 134.875, "maxY": 197.375}, "class_id": 0, "box_caption": "person 0.008", "scores": {"class_score": 0.0079803466796875}, "domain": "pixel"}, {"position": {"minX": 187.75, "minY": 180.0, "maxX": 205.25, "maxY": 192.25}, "class_id": 2, "box_caption": "car 0.008", "scores": {"class_score": 0.00788116455078125}, "domain": "pixel"}, {"position": {"minX": 52.75, "minY": 199.5, "maxX": 65.75, "maxY": 213.75}, "class_id": 16, "box_caption": "dog 0.008", "scores": {"class_score": 0.00783538818359375}, "domain": "pixel"}, {"position": {"minX": 383.75, "minY": 145.125, "maxX": 417.75, "maxY": 169.875}, "class_id": 0, "box_caption": "person 0.008", "scores": {"class_score": 0.007793426513671875}, "domain": "pixel"}, {"position": {"minX": 294.75, "minY": 126.3125, "maxX": 322.75, "maxY": 151.75}, "class_id": 0, "box_caption": "person 0.008", "scores": {"class_score": 0.0077362060546875}, "domain": "pixel"}, {"position": {"minX": 437.25, "minY": 178.0, "maxX": 465.75, "maxY": 189.5}, "class_id": 7, "box_caption": "truck 0.008", "scores": {"class_score": 0.0077056884765625}, "domain": "pixel"}, {"position": {"minX": 475.0, "minY": 175.375, "maxX": 513.5, "maxY": 189.375}, "class_id": 7, "box_caption": "truck 0.008", "scores": {"class_score": 0.0076904296875}, "domain": "pixel"}, {"position": {"minX": 495.0, "minY": 172.125, "maxX": 521.0, "maxY": 184.125}, "class_id": 4, "box_caption": "airplane 0.008", "scores": {"class_score": 0.00760650634765625}, "domain": "pixel"}, {"position": {"minX": 310.75, "minY": 122.875, "maxX": 336.75, "maxY": 149.125}, "class_id": 0, "box_caption": "person 0.008", "scores": {"class_score": 0.0075225830078125}, "domain": "pixel"}, {"position": {"minX": 106.0, "minY": 199.875, "maxX": 156.75, "maxY": 222.125}, "class_id": 2, "box_caption": "car 0.007", "scores": {"class_score": 0.007343292236328125}, "domain": "pixel"}, {"position": {"minX": 56.75, "minY": 199.625, "maxX": 66.125, "maxY": 213.625}, "class_id": 24, "box_caption": "backpack 0.007", "scores": {"class_score": 0.0073394775390625}, "domain": "pixel"}, {"position": {"minX": 471.25, "minY": 180.875, "maxX": 499.75, "maxY": 189.875}, "class_id": 7, "box_caption": "truck 0.007", "scores": {"class_score": 0.00727081298828125}, "domain": "pixel"}, {"position": {"minX": 613.0, "minY": 179.0, "maxX": 646.0, "maxY": 188.5}, "class_id": 4, "box_caption": "airplane 0.007", "scores": {"class_score": 0.00724029541015625}, "domain": "pixel"}, {"position": {"minX": 536.0, "minY": 183.0, "maxX": 564.0, "maxY": 191.75}, "class_id": 2, "box_caption": "car 0.007", "scores": {"class_score": 0.007205963134765625}, "domain": "pixel"}, {"position": {"minX": 69.8125, "minY": 199.375, "maxX": 150.5, "maxY": 232.625}, "class_id": 4, "box_caption": "airplane 0.007", "scores": {"class_score": 0.007080078125}, "domain": "pixel"}, {"position": {"minX": 48.0, "minY": 161.375, "maxX": 169.75, "maxY": 207.125}, "class_id": 7, "box_caption": "truck 0.007", "scores": {"class_score": 0.007015228271484375}, "domain": "pixel"}, {"position": {"minX": 546.5, "minY": 183.375, "maxX": 568.5, "maxY": 189.375}, "class_id": 2, "box_caption": "car 0.007", "scores": {"class_score": 0.0068206787109375}, "domain": "pixel"}, {"position": {"minX": 485.0, "minY": 172.875, "maxX": 566.0, "maxY": 217.125}, "class_id": 4, "box_caption": "airplane 0.007", "scores": {"class_score": 0.006622314453125}, "domain": "pixel"}, {"position": {"minX": 446.25, "minY": 117.375, "maxX": 652.0, "maxY": 225.625}, "class_id": 7, "box_caption": "truck 0.007", "scores": {"class_score": 0.00661468505859375}, "domain": "pixel"}, {"position": {"minX": 157.125, "minY": 184.625, "maxX": 181.375, "maxY": 196.875}, "class_id": 7, "box_caption": "truck 0.007", "scores": {"class_score": 0.006519317626953125}, "domain": "pixel"}, {"position": {"minX": 543.0, "minY": 182.375, "maxX": 571.0, "maxY": 189.625}, "class_id": 7, "box_caption": "truck 0.006", "scores": {"class_score": 0.0064239501953125}, "domain": "pixel"}, {"position": {"minX": 114.0625, "minY": 188.625, "maxX": 146.5, "maxY": 198.375}, "class_id": 7, "box_caption": "truck 0.006", "scores": {"class_score": 0.0064239501953125}, "domain": "pixel"}, {"position": {"minX": 50.4375, "minY": 199.5, "maxX": 59.875, "maxY": 213.5}, "class_id": 3, "box_caption": "motorcycle 0.006", "scores": {"class_score": 0.006267547607421875}, "domain": "pixel"}, {"position": {"minX": 561.0, "minY": 183.0, "maxX": 569.0, "maxY": 190.0}, "class_id": 0, "box_caption": "person 0.006", "scores": {"class_score": 0.0061798095703125}, "domain": "pixel"}, {"position": {"minX": 557.0, "minY": 183.875, "maxX": 567.0, "maxY": 195.875}, "class_id": 2, "box_caption": "car 0.006", "scores": {"class_score": 0.006137847900390625}, "domain": "pixel"}, {"position": {"minX": 494.75, "minY": 197.375, "maxX": 522.0, "maxY": 210.125}, "class_id": 4, "box_caption": "airplane 0.006", "scores": {"class_score": 0.006134033203125}, "domain": "pixel"}, {"position": {"minX": 109.4375, "minY": 187.25, "maxX": 154.25, "maxY": 204.5}, "class_id": 7, "box_caption": "truck 0.006", "scores": {"class_score": 0.00597381591796875}, "domain": "pixel"}, {"position": {"minX": 371.0, "minY": 138.0, "maxX": 419.5, "maxY": 175.25}, "class_id": 0, "box_caption": "person 0.006", "scores": {"class_score": 0.005889892578125}, "domain": "pixel"}, {"position": {"minX": 537.0, "minY": 186.625, "maxX": 568.0, "maxY": 203.375}, "class_id": 2, "box_caption": "car 0.006", "scores": {"class_score": 0.005889892578125}, "domain": "pixel"}, {"position": {"minX": 147.0, "minY": 175.875, "maxX": 178.0, "maxY": 193.875}, "class_id": 0, "box_caption": "person 0.006", "scores": {"class_score": 0.0056610107421875}, "domain": "pixel"}, {"position": {"minX": 523.5, "minY": 189.25, "maxX": 561.5, "maxY": 210.25}, "class_id": 5, "box_caption": "bus 0.006", "scores": {"class_score": 0.005615234375}, "domain": "pixel"}, {"position": {"minX": 522.0, "minY": 188.125, "maxX": 559.0, "maxY": 210.625}, "class_id": 4, "box_caption": "airplane 0.005", "scores": {"class_score": 0.005481719970703125}, "domain": "pixel"}, {"position": {"minX": 52.75, "minY": 199.5, "maxX": 65.75, "maxY": 213.75}, "class_id": 2, "box_caption": "car 0.005", "scores": {"class_score": 0.0054473876953125}, "domain": "pixel"}, {"position": {"minX": 501.0, "minY": 181.625, "maxX": 546.0, "maxY": 195.875}, "class_id": 4, "box_caption": "airplane 0.005", "scores": {"class_score": 0.005420684814453125}, "domain": "pixel"}, {"position": {"minX": 27.921875, "minY": 169.0, "maxX": 91.875, "maxY": 215.25}, "class_id": 7, "box_caption": "truck 0.005", "scores": {"class_score": 0.00531005859375}, "domain": "pixel"}, {"position": {"minX": 516.5, "minY": 182.375, "maxX": 562.5, "maxY": 196.875}, "class_id": 7, "box_caption": "truck 0.005", "scores": {"class_score": 0.005306243896484375}, "domain": "pixel"}, {"position": {"minX": 568.0, "minY": 188.75, "maxX": 589.0, "maxY": 203.5}, "class_id": 7, "box_caption": "truck 0.005", "scores": {"class_score": 0.00530242919921875}, "domain": "pixel"}, {"position": {"minX": 518.5, "minY": 198.0, "maxX": 546.5, "maxY": 208.75}, "class_id": 7, "box_caption": "truck 0.005", "scores": {"class_score": 0.0052490234375}, "domain": "pixel"}, {"position": {"minX": 352.75, "minY": 140.0, "maxX": 414.75, "maxY": 158.25}, "class_id": 0, "box_caption": "person 0.005", "scores": {"class_score": 0.005199432373046875}, "domain": "pixel"}, {"position": {"minX": 111.5, "minY": 181.25, "maxX": 179.5, "maxY": 211.0}, "class_id": 7, "box_caption": "truck 0.005", "scores": {"class_score": 0.005126953125}, "domain": "pixel"}, {"position": {"minX": 495.25, "minY": 199.25, "maxX": 524.0, "maxY": 209.75}, "class_id": 0, "box_caption": "person 0.005", "scores": {"class_score": 0.00511932373046875}, "domain": "pixel"}, {"position": {"minX": 493.75, "minY": 199.5, "maxX": 512.0, "maxY": 210.5}, "class_id": 2, "box_caption": "car 0.005", "scores": {"class_score": 0.0051116943359375}, "domain": "pixel"}, {"position": {"minX": 491.0, "minY": 173.75, "maxX": 522.5, "maxY": 193.0}, "class_id": 7, "box_caption": "truck 0.005", "scores": {"class_score": 0.0051116943359375}, "domain": "pixel"}, {"position": {"minX": 488.75, "minY": 172.25, "maxX": 573.0, "maxY": 216.75}, "class_id": 7, "box_caption": "truck 0.005", "scores": {"class_score": 0.005062103271484375}, "domain": "pixel"}, {"position": {"minX": 499.0, "minY": 187.5, "maxX": 530.0, "maxY": 202.25}, "class_id": 5, "box_caption": "bus 0.005", "scores": {"class_score": 0.00498199462890625}, "domain": "pixel"}, {"position": {"minX": 53.5, "minY": 199.5, "maxX": 66.375, "maxY": 213.75}, "class_id": 58, "box_caption": "potted plant 0.005", "scores": {"class_score": 0.004852294921875}, "domain": "pixel"}, {"position": {"minX": 392.25, "minY": 41.25, "maxX": 673.0, "maxY": 341.5}, "class_id": 4, "box_caption": "airplane 0.005", "scores": {"class_score": 0.004791259765625}, "domain": "pixel"}, {"position": {"minX": 159.25, "minY": 185.625, "maxX": 178.5, "maxY": 195.875}, "class_id": 0, "box_caption": "person 0.005", "scores": {"class_score": 0.004779815673828125}, "domain": "pixel"}, {"position": {"minX": 642.5, "minY": 180.25, "maxX": 655.5, "maxY": 187.0}, "class_id": 4, "box_caption": "airplane 0.005", "scores": {"class_score": 0.0045623779296875}, "domain": "pixel"}, {"position": {"minX": 518.5, "minY": 198.0, "maxX": 546.5, "maxY": 208.75}, "class_id": 2, "box_caption": "car 0.005", "scores": {"class_score": 0.004558563232421875}, "domain": "pixel"}, {"position": {"minX": 43.625, "minY": 198.625, "maxX": 73.4375, "maxY": 214.125}, "class_id": 0, "box_caption": "person 0.004", "scores": {"class_score": 0.0044708251953125}, "domain": "pixel"}, {"position": {"minX": 99.75, "minY": 166.625, "maxX": 181.5, "maxY": 202.625}, "class_id": 7, "box_caption": "truck 0.004", "scores": {"class_score": 0.004390716552734375}, "domain": "pixel"}, {"position": {"minX": 72.5, "minY": 198.0, "maxX": 144.25, "maxY": 218.5}, "class_id": 2, "box_caption": "car 0.004", "scores": {"class_score": 0.004375457763671875}, "domain": "pixel"}, {"position": {"minX": 109.75, "minY": 185.125, "maxX": 136.5, "maxY": 200.625}, "class_id": 2, "box_caption": "car 0.004", "scores": {"class_score": 0.004306793212890625}, "domain": "pixel"}, {"position": {"minX": 146.0, "minY": 175.5, "maxX": 179.25, "maxY": 194.25}, "class_id": 5, "box_caption": "bus 0.004", "scores": {"class_score": 0.00424957275390625}, "domain": "pixel"}, {"position": {"minX": 115.0625, "minY": 197.25, "maxX": 153.875, "maxY": 212.25}, "class_id": 2, "box_caption": "car 0.004", "scores": {"class_score": 0.004146575927734375}, "domain": "pixel"}, {"position": {"minX": 461.5, "minY": 157.125, "maxX": 573.5, "maxY": 198.625}, "class_id": 4, "box_caption": "airplane 0.004", "scores": {"class_score": 0.004085540771484375}, "domain": "pixel"}, {"position": {"minX": 511.0, "minY": 174.5, "maxX": 566.0, "maxY": 210.0}, "class_id": 7, "box_caption": "truck 0.004", "scores": {"class_score": 0.00408172607421875}, "domain": "pixel"}, {"position": {"minX": 558.0, "minY": 178.0, "maxX": 583.0, "maxY": 189.5}, "class_id": 7, "box_caption": "truck 0.004", "scores": {"class_score": 0.0040130615234375}, "domain": "pixel"}, {"position": {"minX": 310.5, "minY": 116.5, "maxX": 370.5, "maxY": 152.5}, "class_id": 0, "box_caption": "person 0.004", "scores": {"class_score": 0.003948211669921875}, "domain": "pixel"}, {"position": {"minX": 50.5, "minY": 199.875, "maxX": 61.75, "maxY": 213.125}, "class_id": 11, "box_caption": "stop sign 0.004", "scores": {"class_score": 0.0038738250732421875}, "domain": "pixel"}, {"position": {"minX": 303.75, "minY": 125.3125, "maxX": 344.75, "maxY": 152.0}, "class_id": 0, "box_caption": "person 0.004", "scores": {"class_score": 0.003871917724609375}, "domain": "pixel"}, {"position": {"minX": 53.5, "minY": 199.5, "maxX": 66.375, "maxY": 213.75}, "class_id": 9, "box_caption": "traffic light 0.004", "scores": {"class_score": 0.0038585662841796875}, "domain": "pixel"}, {"position": {"minX": 495.75, "minY": 180.625, "maxX": 520.5, "maxY": 192.625}, "class_id": 0, "box_caption": "person 0.004", "scores": {"class_score": 0.003856658935546875}, "domain": "pixel"}, {"position": {"minX": 132.875, "minY": 199.875, "maxX": 160.125, "maxY": 216.875}, "class_id": 2, "box_caption": "car 0.004", "scores": {"class_score": 0.0038356781005859375}, "domain": "pixel"}, {"position": {"minX": 117.75, "minY": 197.5, "maxX": 150.5, "maxY": 211.75}, "class_id": 0, "box_caption": "person 0.004", "scores": {"class_score": 0.003826141357421875}, "domain": "pixel"}, {"position": {"minX": 136.5, "minY": 201.5, "maxX": 155.75, "maxY": 212.0}, "class_id": 2, "box_caption": "car 0.004", "scores": {"class_score": 0.0038089752197265625}, "domain": "pixel"}, {"position": {"minX": 50.5, "minY": 199.875, "maxX": 61.75, "maxY": 213.125}, "class_id": 24, "box_caption": "backpack 0.004", "scores": {"class_score": 0.0038089752197265625}, "domain": "pixel"}, {"position": {"minX": 509.0, "minY": 182.5, "maxX": 533.0, "maxY": 193.25}, "class_id": 2, "box_caption": "car 0.004", "scores": {"class_score": 0.003780364990234375}, "domain": "pixel"}, {"position": {"minX": 110.125, "minY": 185.875, "maxX": 152.375, "maxY": 206.125}, "class_id": 0, "box_caption": "person 0.004", "scores": {"class_score": 0.0037441253662109375}, "domain": "pixel"}, {"position": {"minX": 50.5, "minY": 200.0, "maxX": 59.875, "maxY": 213.25}, "class_id": 28, "box_caption": "suitcase 0.004", "scores": {"class_score": 0.0037078857421875}, "domain": "pixel"}, {"position": {"minX": 497.25, "minY": 200.375, "maxX": 548.5, "maxY": 209.875}, "class_id": 7, "box_caption": "truck 0.004", "scores": {"class_score": 0.0036830902099609375}, "domain": "pixel"}, {"position": {"minX": 499.5, "minY": 187.75, "maxX": 526.5, "maxY": 201.25}, "class_id": 0, "box_caption": "person 0.004", "scores": {"class_score": 0.0035686492919921875}, "domain": "pixel"}, {"position": {"minX": 118.625, "minY": 190.375, "maxX": 133.125, "maxY": 198.875}, "class_id": 7, "box_caption": "truck 0.003", "scores": {"class_score": 0.003490447998046875}, "domain": "pixel"}, {"position": {"minX": 551.5, "minY": 195.5, "maxX": 564.5, "maxY": 208.75}, "class_id": 2, "box_caption": "car 0.003", "scores": {"class_score": 0.003467559814453125}, "domain": "pixel"}, {"position": {"minX": 147.0, "minY": 175.875, "maxX": 178.0, "maxY": 193.875}, "class_id": 2, "box_caption": "car 0.003", "scores": {"class_score": 0.0034580230712890625}, "domain": "pixel"}, {"position": {"minX": 116.875, "minY": 188.75, "maxX": 142.875, "maxY": 198.25}, "class_id": 0, "box_caption": "person 0.003", "scores": {"class_score": 0.003452301025390625}, "domain": "pixel"}, {"position": {"minX": 516.5, "minY": 182.375, "maxX": 562.5, "maxY": 196.875}, "class_id": 4, "box_caption": "airplane 0.003", "scores": {"class_score": 0.0034198760986328125}, "domain": "pixel"}, {"position": {"minX": 14.5, "minY": 4.75, "maxX": 590.0, "maxY": 446.75}, "class_id": 5, "box_caption": "bus 0.003", "scores": {"class_score": 0.0034046173095703125}, "domain": "pixel"}, {"position": {"minX": 123.125, "minY": 189.875, "maxX": 134.875, "maxY": 197.375}, "class_id": 7, "box_caption": "truck 0.003", "scores": {"class_score": 0.00339508056640625}, "domain": "pixel"}, {"position": {"minX": 609.0, "minY": 181.5, "maxX": 631.0, "maxY": 188.0}, "class_id": 4, "box_caption": "airplane 0.003", "scores": {"class_score": 0.0033893585205078125}, "domain": "pixel"}, {"position": {"minX": 497.25, "minY": 200.375, "maxX": 548.5, "maxY": 209.875}, "class_id": 2, "box_caption": "car 0.003", "scores": {"class_score": 0.0033817291259765625}, "domain": "pixel"}, {"position": {"minX": 121.75, "minY": 198.125, "maxX": 145.0, "maxY": 210.125}, "class_id": 0, "box_caption": "person 0.003", "scores": {"class_score": 0.0033359527587890625}, "domain": "pixel"}, {"position": {"minX": 111.0, "minY": 190.5, "maxX": 133.125, "maxY": 200.5}, "class_id": 25, "box_caption": "umbrella 0.003", "scores": {"class_score": 0.003322601318359375}, "domain": "pixel"}, {"position": {"minX": 551.5, "minY": 195.25, "maxX": 564.5, "maxY": 208.5}, "class_id": 7, "box_caption": "truck 0.003", "scores": {"class_score": 0.003322601318359375}, "domain": "pixel"}, {"position": {"minX": 94.875, "minY": 194.0, "maxX": 138.125, "maxY": 210.0}, "class_id": 2, "box_caption": "car 0.003", "scores": {"class_score": 0.003269195556640625}, "domain": "pixel"}, {"position": {"minX": 68.0625, "minY": 173.75, "maxX": 147.25, "maxY": 205.0}, "class_id": 7, "box_caption": "truck 0.003", "scores": {"class_score": 0.003261566162109375}, "domain": "pixel"}, {"position": {"minX": 445.25, "minY": 180.375, "maxX": 462.25, "maxY": 188.375}, "class_id": 5, "box_caption": "bus 0.003", "scores": {"class_score": 0.0032501220703125}, "domain": "pixel"}, {"position": {"minX": 509.0, "minY": 182.5, "maxX": 533.0, "maxY": 193.25}, "class_id": 7, "box_caption": "truck 0.003", "scores": {"class_score": 0.00322723388671875}, "domain": "pixel"}, {"position": {"minX": 483.75, "minY": 170.375, "maxX": 516.0, "maxY": 183.875}, "class_id": 4, "box_caption": "airplane 0.003", "scores": {"class_score": 0.003204345703125}, "domain": "pixel"}, {"position": {"minX": 471.25, "minY": 180.875, "maxX": 499.75, "maxY": 189.875}, "class_id": 2, "box_caption": "car 0.003", "scores": {"class_score": 0.0031948089599609375}, "domain": "pixel"}, {"position": {"minX": 603.5, "minY": 181.75, "maxX": 623.5, "maxY": 188.0}, "class_id": 4, "box_caption": "airplane 0.003", "scores": {"class_score": 0.0031948089599609375}, "domain": "pixel"}, {"position": {"minX": 151.75, "minY": 46.875, "maxX": 654.0, "maxY": 326.0}, "class_id": 4, "box_caption": "airplane 0.003", "scores": {"class_score": 0.0031585693359375}, "domain": "pixel"}, {"position": {"minX": 449.5, "minY": 172.375, "maxX": 551.0, "maxY": 205.625}, "class_id": 4, "box_caption": "airplane 0.003", "scores": {"class_score": 0.0031299591064453125}, "domain": "pixel"}, {"position": {"minX": 16.90625, "minY": 181.625, "maxX": 85.125, "maxY": 216.375}, "class_id": 7, "box_caption": "truck 0.003", "scores": {"class_score": 0.0031261444091796875}, "domain": "pixel"}, {"position": {"minX": 116.3125, "minY": 199.5, "maxX": 163.125, "maxY": 214.75}, "class_id": 7, "box_caption": "truck 0.003", "scores": {"class_score": 0.00311279296875}, "domain": "pixel"}, {"position": {"minX": 251.625, "minY": 83.75, "maxX": 656.5, "maxY": 417.25}, "class_id": 4, "box_caption": "airplane 0.003", "scores": {"class_score": 0.003082275390625}, "domain": "pixel"}, {"position": {"minX": 55.5, "minY": 197.375, "maxX": 66.125, "maxY": 209.375}, "class_id": 0, "box_caption": "person 0.003", "scores": {"class_score": 0.0030231475830078125}, "domain": "pixel"}, {"position": {"minX": 495.5, "minY": 192.625, "maxX": 522.5, "maxY": 208.625}, "class_id": 0, "box_caption": "person 0.003", "scores": {"class_score": 0.0030078887939453125}, "domain": "pixel"}, {"position": {"minX": 512.0, "minY": 181.0, "maxX": 535.0, "maxY": 191.5}, "class_id": 4, "box_caption": "airplane 0.003", "scores": {"class_score": 0.0029964447021484375}, "domain": "pixel"}, {"position": {"minX": 590.0, "minY": 179.625, "maxX": 600.0, "maxY": 185.875}, "class_id": 2, "box_caption": "car 0.003", "scores": {"class_score": 0.0029926300048828125}, "domain": "pixel"}, {"position": {"minX": 36.25, "minY": 76.5, "maxX": 649.0, "maxY": 433.0}, "class_id": 6, "box_caption": "train 0.003", "scores": {"class_score": 0.002986907958984375}, "domain": "pixel"}, {"position": {"minX": 125.1875, "minY": 200.375, "maxX": 155.75, "maxY": 213.625}, "class_id": 2, "box_caption": "car 0.003", "scores": {"class_score": 0.0029735565185546875}, "domain": "pixel"}, {"position": {"minX": 471.25, "minY": 171.375, "maxX": 520.5, "maxY": 191.875}, "class_id": 7, "box_caption": "truck 0.003", "scores": {"class_score": 0.002956390380859375}, "domain": "pixel"}, {"position": {"minX": 598.5, "minY": 180.75, "maxX": 628.5, "maxY": 188.75}, "class_id": 4, "box_caption": "airplane 0.003", "scores": {"class_score": 0.00281524658203125}, "domain": "pixel"}, {"position": {"minX": 83.5, "minY": 290.0, "maxX": 100.625, "maxY": 308.0}, "class_id": 0, "box_caption": "person 0.003", "scores": {"class_score": 0.0027713775634765625}, "domain": "pixel"}, {"position": {"minX": 515.0, "minY": 181.5, "maxX": 534.0, "maxY": 191.0}, "class_id": 2, "box_caption": "car 0.003", "scores": {"class_score": 0.0027446746826171875}, "domain": "pixel"}, {"position": {"minX": 494.0, "minY": 199.625, "maxX": 513.0, "maxY": 210.375}, "class_id": 7, "box_caption": "truck 0.003", "scores": {"class_score": 0.0027294158935546875}, "domain": "pixel"}, {"position": {"minX": 123.125, "minY": 189.875, "maxX": 134.875, "maxY": 197.375}, "class_id": 2, "box_caption": "car 0.003", "scores": {"class_score": 0.0026702880859375}, "domain": "pixel"}, {"position": {"minX": 73.875, "minY": 196.875, "maxX": 131.125, "maxY": 211.875}, "class_id": 2, "box_caption": "car 0.003", "scores": {"class_score": 0.0026645660400390625}, "domain": "pixel"}, {"position": {"minX": 77.3125, "minY": 292.25, "maxX": 94.1875, "maxY": 306.25}, "class_id": 0, "box_caption": "person 0.003", "scores": {"class_score": 0.0026607513427734375}, "domain": "pixel"}, {"position": {"minX": 600.5, "minY": 179.625, "maxX": 642.5, "maxY": 190.375}, "class_id": 4, "box_caption": "airplane 0.003", "scores": {"class_score": 0.0026531219482421875}, "domain": "pixel"}, {"position": {"minX": 302.5, "minY": 118.25, "maxX": 647.0, "maxY": 251.0}, "class_id": 4, "box_caption": "airplane 0.003", "scores": {"class_score": 0.002635955810546875}, "domain": "pixel"}, {"position": {"minX": 27.921875, "minY": 169.0, "maxX": 91.875, "maxY": 215.25}, "class_id": 0, "box_caption": "person 0.003", "scores": {"class_score": 0.0026302337646484375}, "domain": "pixel"}, {"position": {"minX": 12.375, "minY": 157.125, "maxX": 93.875, "maxY": 195.375}, "class_id": 7, "box_caption": "truck 0.003", "scores": {"class_score": 0.00261688232421875}, "domain": "pixel"}, {"position": {"minX": 16.546875, "minY": 333.25, "maxX": 56.875, "maxY": 369.75}, "class_id": 2, "box_caption": "car 0.003", "scores": {"class_score": 0.0026149749755859375}, "domain": "pixel"}, {"position": {"minX": 541.5, "minY": 171.875, "maxX": 584.5, "maxY": 187.875}, "class_id": 4, "box_caption": "airplane 0.003", "scores": {"class_score": 0.002593994140625}, "domain": "pixel"}, {"position": {"minX": 53.5625, "minY": 199.75, "maxX": 65.6875, "maxY": 213.75}, "class_id": 1, "box_caption": "bicycle 0.003", "scores": {"class_score": 0.0025882720947265625}, "domain": "pixel"}, {"position": {"minX": 515.0, "minY": 181.5, "maxX": 534.0, "maxY": 191.0}, "class_id": 7, "box_caption": "truck 0.003", "scores": {"class_score": 0.00250244140625}, "domain": "pixel"}, {"position": {"minX": 150.125, "minY": 180.5, "maxX": 205.125, "maxY": 196.75}, "class_id": 7, "box_caption": "truck 0.002", "scores": {"class_score": 0.002483367919921875}, "domain": "pixel"}, {"position": {"minX": 22.625, "minY": 183.0, "maxX": 158.375, "maxY": 221.0}, "class_id": 2, "box_caption": "car 0.002", "scores": {"class_score": 0.0024585723876953125}, "domain": "pixel"}, {"position": {"minX": 62.90625, "minY": 176.5, "maxX": 163.125, "maxY": 237.0}, "class_id": 2, "box_caption": "car 0.002", "scores": {"class_score": 0.0024547576904296875}, "domain": "pixel"}, {"position": {"minX": 114.0625, "minY": 188.625, "maxX": 146.5, "maxY": 198.375}, "class_id": 2, "box_caption": "car 0.002", "scores": {"class_score": 0.0024509429931640625}, "domain": "pixel"}, {"position": {"minX": 563.0, "minY": 183.75, "maxX": 589.0, "maxY": 202.75}, "class_id": 7, "box_caption": "truck 0.002", "scores": {"class_score": 0.002407073974609375}, "domain": "pixel"}, {"position": {"minX": 519.0, "minY": 182.25, "maxX": 541.0, "maxY": 194.25}, "class_id": 7, "box_caption": "truck 0.002", "scores": {"class_score": 0.0023746490478515625}, "domain": "pixel"}, {"position": {"minX": 62.0625, "minY": 196.0, "maxX": 132.25, "maxY": 232.25}, "class_id": 2, "box_caption": "car 0.002", "scores": {"class_score": 0.002349853515625}, "domain": "pixel"}, {"position": {"minX": 110.5, "minY": 190.5, "maxX": 133.375, "maxY": 200.5}, "class_id": 5, "box_caption": "bus 0.002", "scores": {"class_score": 0.002346038818359375}, "domain": "pixel"}, {"position": {"minX": 105.75, "minY": 184.0, "maxX": 171.0, "maxY": 205.25}, "class_id": 2, "box_caption": "car 0.002", "scores": {"class_score": 0.0023365020751953125}, "domain": "pixel"}, {"position": {"minX": 134.875, "minY": 172.875, "maxX": 186.625, "maxY": 198.875}, "class_id": 7, "box_caption": "truck 0.002", "scores": {"class_score": 0.0023326873779296875}, "domain": "pixel"}, {"position": {"minX": 156.0, "minY": 187.375, "maxX": 174.5, "maxY": 195.625}, "class_id": 0, "box_caption": "person 0.002", "scores": {"class_score": 0.002330780029296875}, "domain": "pixel"}, {"position": {"minX": 355.25, "minY": 134.0, "maxX": 405.25, "maxY": 160.75}, "class_id": 0, "box_caption": "person 0.002", "scores": {"class_score": 0.0023288726806640625}, "domain": "pixel"}, {"position": {"minX": 494.0, "minY": 180.125, "maxX": 513.5, "maxY": 190.625}, "class_id": 0, "box_caption": "person 0.002", "scores": {"class_score": 0.0023193359375}, "domain": "pixel"}, {"position": {"minX": 327.0, "minY": 112.3125, "maxX": 361.0, "maxY": 149.5}, "class_id": 0, "box_caption": "person 0.002", "scores": {"class_score": 0.002315521240234375}, "domain": "pixel"}, {"position": {"minX": 110.875, "minY": 200.5, "maxX": 152.625, "maxY": 221.25}, "class_id": 0, "box_caption": "person 0.002", "scores": {"class_score": 0.0023136138916015625}, "domain": "pixel"}, {"position": {"minX": 436.0, "minY": 181.125, "maxX": 457.0, "maxY": 188.375}, "class_id": 4, "box_caption": "airplane 0.002", "scores": {"class_score": 0.0023021697998046875}, "domain": "pixel"}, {"position": {"minX": 115.75, "minY": 198.125, "maxX": 168.25, "maxY": 223.625}, "class_id": 2, "box_caption": "car 0.002", "scores": {"class_score": 0.0022907257080078125}, "domain": "pixel"}, {"position": {"minX": 535.0, "minY": 193.375, "maxX": 565.0, "maxY": 210.125}, "class_id": 5, "box_caption": "bus 0.002", "scores": {"class_score": 0.0022735595703125}, "domain": "pixel"}, {"position": {"minX": 371.0, "minY": 138.0, "maxX": 419.5, "maxY": 175.25}, "class_id": 16, "box_caption": "dog 0.002", "scores": {"class_score": 0.002262115478515625}, "domain": "pixel"}, {"position": {"minX": 553.5, "minY": 183.0, "maxX": 570.5, "maxY": 190.5}, "class_id": 4, "box_caption": "airplane 0.002", "scores": {"class_score": 0.0022563934326171875}, "domain": "pixel"}, {"position": {"minX": 58.375, "minY": 200.625, "maxX": 66.0, "maxY": 214.125}, "class_id": 10, "box_caption": "fire hydrant 0.002", "scores": {"class_score": 0.0022449493408203125}, "domain": "pixel"}, {"position": {"minX": 479.0, "minY": 177.375, "maxX": 510.0, "maxY": 188.875}, "class_id": 2, "box_caption": "car 0.002", "scores": {"class_score": 0.0022430419921875}, "domain": "pixel"}, {"position": {"minX": 455.25, "minY": 94.875, "maxX": 659.5, "maxY": 396.5}, "class_id": 4, "box_caption": "airplane 0.002", "scores": {"class_score": 0.002223968505859375}, "domain": "pixel"}, {"position": {"minX": 157.75, "minY": 186.0, "maxX": 196.0, "maxY": 199.0}, "class_id": 7, "box_caption": "truck 0.002", "scores": {"class_score": 0.0022220611572265625}, "domain": "pixel"}, {"position": {"minX": 435.25, "minY": 181.25, "maxX": 450.25, "maxY": 189.5}, "class_id": 7, "box_caption": "truck 0.002", "scores": {"class_score": 0.0022144317626953125}, "domain": "pixel"}, {"position": {"minX": 117.125, "minY": 173.25, "maxX": 184.875, "maxY": 192.75}, "class_id": 7, "box_caption": "truck 0.002", "scores": {"class_score": 0.002162933349609375}, "domain": "pixel"}, {"position": {"minX": 90.625, "minY": 201.75, "maxX": 148.875, "maxY": 231.25}, "class_id": 2, "box_caption": "car 0.002", "scores": {"class_score": 0.0021457672119140625}, "domain": "pixel"}, {"position": {"minX": 49.4375, "minY": 192.5, "maxX": 148.0, "maxY": 236.75}, "class_id": 2, "box_caption": "car 0.002", "scores": {"class_score": 0.0021190643310546875}, "domain": "pixel"}, {"position": {"minX": 199.5, "minY": 79.5, "maxX": 649.0, "maxY": 229.25}, "class_id": 4, "box_caption": "airplane 0.002", "scores": {"class_score": 0.002117156982421875}, "domain": "pixel"}, {"position": {"minX": 411.25, "minY": 110.0625, "maxX": 420.25, "maxY": 120.9375}, "class_id": 0, "box_caption": "person 0.002", "scores": {"class_score": 0.0021152496337890625}, "domain": "pixel"}, {"position": {"minX": 599.5, "minY": 165.25, "maxX": 656.5, "maxY": 193.25}, "class_id": 4, "box_caption": "airplane 0.002", "scores": {"class_score": 0.0020999908447265625}, "domain": "pixel"}, {"position": {"minX": 105.75, "minY": 184.0, "maxX": 171.0, "maxY": 205.25}, "class_id": 7, "box_caption": "truck 0.002", "scores": {"class_score": 0.00206756591796875}, "domain": "pixel"}, {"position": {"minX": 541.5, "minY": 171.875, "maxX": 584.5, "maxY": 187.875}, "class_id": 7, "box_caption": "truck 0.002", "scores": {"class_score": 0.0020656585693359375}, "domain": "pixel"}, {"position": {"minX": 527.5, "minY": 183.125, "maxX": 556.5, "maxY": 194.875}, "class_id": 7, "box_caption": "truck 0.002", "scores": {"class_score": 0.0020465850830078125}, "domain": "pixel"}, {"position": {"minX": 567.0, "minY": 192.0, "maxX": 589.0, "maxY": 203.75}, "class_id": 2, "box_caption": "car 0.002", "scores": {"class_score": 0.002025604248046875}, "domain": "pixel"}, {"position": {"minX": 159.25, "minY": 185.625, "maxX": 178.5, "maxY": 195.875}, "class_id": 2, "box_caption": "car 0.002", "scores": {"class_score": 0.002002716064453125}, "domain": "pixel"}, {"position": {"minX": 36.25, "minY": 76.5, "maxX": 649.0, "maxY": 433.0}, "class_id": 1, "box_caption": "bicycle 0.002", "scores": {"class_score": 0.0019931793212890625}, "domain": "pixel"}, {"position": {"minX": 152.25, "minY": 186.0, "maxX": 176.75, "maxY": 197.25}, "class_id": 7, "box_caption": "truck 0.002", "scores": {"class_score": 0.00199127197265625}, "domain": "pixel"}, {"position": {"minX": 555.5, "minY": 183.25, "maxX": 567.5, "maxY": 196.5}, "class_id": 7, "box_caption": "truck 0.002", "scores": {"class_score": 0.001953125}, "domain": "pixel"}, {"position": {"minX": 473.0, "minY": 173.25, "maxX": 520.0, "maxY": 189.75}, "class_id": 2, "box_caption": "car 0.002", "scores": {"class_score": 0.0019445419311523438}, "domain": "pixel"}, {"position": {"minX": 329.5, "minY": 115.875, "maxX": 378.5, "maxY": 152.625}, "class_id": 0, "box_caption": "person 0.002", "scores": {"class_score": 0.001926422119140625}, "domain": "pixel"}, {"position": {"minX": 500.0, "minY": 184.5, "maxX": 523.5, "maxY": 194.0}, "class_id": 0, "box_caption": "person 0.002", "scores": {"class_score": 0.0019216537475585938}, "domain": "pixel"}, {"position": {"minX": 346.25, "minY": 139.5, "maxX": 416.75, "maxY": 174.25}, "class_id": 0, "box_caption": "person 0.002", "scores": {"class_score": 0.0019092559814453125}, "domain": "pixel"}, {"position": {"minX": 519.0, "minY": 182.25, "maxX": 541.0, "maxY": 194.25}, "class_id": 2, "box_caption": "car 0.002", "scores": {"class_score": 0.001873016357421875}, "domain": "pixel"}, {"position": {"minX": 551.5, "minY": 195.5, "maxX": 564.5, "maxY": 208.75}, "class_id": 0, "box_caption": "person 0.002", "scores": {"class_score": 0.00186920166015625}, "domain": "pixel"}, {"position": {"minX": 118.6875, "minY": 201.375, "maxX": 146.25, "maxY": 219.875}, "class_id": 0, "box_caption": "person 0.002", "scores": {"class_score": 0.0018367767333984375}, "domain": "pixel"}, {"position": {"minX": 69.8125, "minY": 199.375, "maxX": 150.5, "maxY": 232.625}, "class_id": 5, "box_caption": "bus 0.002", "scores": {"class_score": 0.0018358230590820312}, "domain": "pixel"}, {"position": {"minX": 433.0, "minY": 178.75, "maxX": 458.5, "maxY": 193.5}, "class_id": 2, "box_caption": "car 0.002", "scores": {"class_score": 0.0018310546875}, "domain": "pixel"}, {"position": {"minX": 101.0, "minY": 171.5, "maxX": 150.0, "maxY": 197.25}, "class_id": 7, "box_caption": "truck 0.002", "scores": {"class_score": 0.0018253326416015625}, "domain": "pixel"}, {"position": {"minX": 50.71875, "minY": 199.5, "maxX": 61.53125, "maxY": 213.5}, "class_id": 12, "box_caption": "parking meter 0.002", "scores": {"class_score": 0.0018110275268554688}, "domain": "pixel"}, {"position": {"minX": 105.6875, "minY": 198.875, "maxX": 167.25, "maxY": 232.625}, "class_id": 2, "box_caption": "car 0.002", "scores": {"class_score": 0.0017986297607421875}, "domain": "pixel"}, {"position": {"minX": 21.1875, "minY": 157.0, "maxX": 150.5, "maxY": 203.0}, "class_id": 7, "box_caption": "truck 0.002", "scores": {"class_score": 0.0017948150634765625}, "domain": "pixel"}, {"position": {"minX": 103.875, "minY": 174.25, "maxX": 174.375, "maxY": 197.75}, "class_id": 5, "box_caption": "bus 0.002", "scores": {"class_score": 0.00179290771484375}, "domain": "pixel"}, {"position": {"minX": 14.5, "minY": 4.75, "maxX": 590.0, "maxY": 446.75}, "class_id": 61, "box_caption": "toilet 0.002", "scores": {"class_score": 0.001789093017578125}, "domain": "pixel"}, {"position": {"minX": 89.5, "minY": 191.5, "maxX": 134.125, "maxY": 203.0}, "class_id": 2, "box_caption": "car 0.002", "scores": {"class_score": 0.001743316650390625}, "domain": "pixel"}, {"position": {"minX": 351.25, "minY": 97.1875, "maxX": 358.75, "maxY": 105.3125}, "class_id": 0, "box_caption": "person 0.002", "scores": {"class_score": 0.0017404556274414062}, "domain": "pixel"}], "class_labels": {"0": "person", "1": "bicycle", "2": "car", "3": "motorcycle", "4": "airplane", "5": "bus", "6": "train", "7": "truck", "8": "boat", "9": "traffic light", "10": "fire hydrant", "11": "stop sign", "12": "parking meter", "13": "bench", "14": "bird", "15": "cat", "16": "dog", "17": "horse", "18": "sheep", "19": "cow", "20": "elephant", "21": "bear", "22": "zebra", "23": "giraffe", "24": "backpack", "25": "umbrella", "26": "handbag", "27": "tie", "28": "suitcase", "29": "frisbee", "30": "skis", "31": "snowboard", "32": "sports ball", "33": "kite", "34": "baseball bat", "35": "baseball glove", "36": "skateboard", "37": "surfboard", "38": "tennis racket", "39": "bottle", "40": "wine glass", "41": "cup", "42": "fork", "43": "knife", "44": "spoon", "45": "bowl", "46": "banana", "47": "apple", "48": "sandwich", "49": "orange", "50": "broccoli", "51": "carrot", "52": "hot dog", "53": "pizza", "54": "donut", "55": "cake", "56": "chair", "57": "couch", "58": "potted plant", "59": "bed", "60": "dining table", "61": "toilet", "62": "tv", "63": "laptop", "64": "mouse", "65": "remote", "66": "keyboard", "67": "cell phone", "68": "microwave", "69": "oven", "70": "toaster", "71": "sink", "72": "refrigerator", "73": "book", "74": "clock", "75": "vase", "76": "scissors", "77": "teddy bear", "78": "hair drier", "79": "toothbrush"}}