{"box_data": [{"position": {"minX": 394.25, "minY": 78.0, "maxX": 625.0, "maxY": 372.5}, "class_id": 23, "box_caption": "giraffe 0.913", "scores": {"class_score": 0.9130859375}, "domain": "pixel"}, {"position": {"minX": 63.1875, "minY": 370.25, "maxX": 199.0, "maxY": 428.25}, "class_id": 23, "box_caption": "giraffe 0.629", "scores": {"class_score": 0.62939453125}, "domain": "pixel"}, {"position": {"minX": 12.125, "minY": 374.0, "maxX": 181.5, "maxY": 439.5}, "class_id": 23, "box_caption": "giraffe 0.040", "scores": {"class_score": 0.04022216796875}, "domain": "pixel"}, {"position": {"minX": 64.8125, "minY": 378.5, "maxX": 158.0, "maxY": 430.0}, "class_id": 23, "box_caption": "giraffe 0.022", "scores": {"class_score": 0.0217437744140625}, "domain": "pixel"}, {"position": {"minX": 355.0, "minY": 58.25, "maxX": 537.5, "maxY": 390.75}, "class_id": 23, "box_caption": "giraffe 0.020", "scores": {"class_score": 0.0200042724609375}, "domain": "pixel"}, {"position": {"minX": 19.0, "minY": 348.25, "maxX": 211.5, "maxY": 436.75}, "class_id": 23, "box_caption": "giraffe 0.020", "scores": {"class_score": 0.019989013671875}, "domain": "pixel"}, {"position": {"minX": 72.3125, "minY": 360.75, "maxX": 266.5, "maxY": 425.25}, "class_id": 23, "box_caption": "giraffe 0.010", "scores": {"class_score": 0.010467529296875}, "domain": "pixel"}, {"position": {"minX": 263.5, "minY": 37.375, "maxX": 525.0, "maxY": 397.5}, "class_id": 23, "box_caption": "giraffe 0.010", "scores": {"class_score": 0.00965118408203125}, "domain": "pixel"}, {"position": {"minX": 340.25, "minY": 357.0, "maxX": 379.75, "maxY": 392.0}, "class_id": 23, "box_caption": "giraffe 0.006", "scores": {"class_score": 0.005664825439453125}, "domain": "pixel"}, {"position": {"minX": 58.375, "minY": 369.25, "maxX": 279.0, "maxY": 445.25}, "class_id": 23, "box_caption": "giraffe 0.005", "scores": {"class_score": 0.005290985107421875}, "domain": "pixel"}, {"position": {"minX": 56.125, "minY": 357.75, "maxX": 342.5, "maxY": 414.75}, "class_id": 23, "box_caption": "giraffe 0.004", "scores": {"class_score": 0.00443267822265625}, "domain": "pixel"}, {"position": {"minX": 400.25, "minY": 77.25, "maxX": 507.75, "maxY": 338.75}, "class_id": 23, "box_caption": "giraffe 0.004", "scores": {"class_score": 0.00400543212890625}, "domain": "pixel"}, {"position": {"minX": 61.8125, "minY": 387.75, "maxX": 203.25, "maxY": 436.75}, "class_id": 23, "box_caption": "giraffe 0.004", "scores": {"class_score": 0.003826141357421875}, "domain": "pixel"}, {"position": {"minX": 60.09375, "minY": 368.25, "maxX": 177.875, "maxY": 426.25}, "class_id": 53, "box_caption": "pizza 0.004", "scores": {"class_score": 0.0037441253662109375}, "domain": "pixel"}, {"position": {"minX": 100.9375, "minY": 366.25, "maxX": 223.5, "maxY": 416.75}, "class_id": 23, "box_caption": "giraffe 0.004", "scores": {"class_score": 0.0037174224853515625}, "domain": "pixel"}, {"position": {"minX": 155.0, "minY": 371.5, "maxX": 205.5, "maxY": 398.0}, "class_id": 23, "box_caption": "giraffe 0.004", "scores": {"class_score": 0.0035686492919921875}, "domain": "pixel"}, {"position": {"minX": 472.75, "minY": 336.25, "maxX": 485.75, "maxY": 365.25}, "class_id": 23, "box_caption": "giraffe 0.003", "scores": {"class_score": 0.0033130645751953125}, "domain": "pixel"}, {"position": {"minX": 80.0625, "minY": 395.25, "maxX": 160.0, "maxY": 431.25}, "class_id": 23, "box_caption": "giraffe 0.003", "scores": {"class_score": 0.003307342529296875}, "domain": "pixel"}, {"position": {"minX": 57.78125, "minY": 346.5, "maxX": 176.875, "maxY": 423.5}, "class_id": 23, "box_caption": "giraffe 0.003", "scores": {"class_score": 0.0029850006103515625}, "domain": "pixel"}, {"position": {"minX": 53.125, "minY": 335.5, "maxX": 345.5, "maxY": 434.0}, "class_id": 23, "box_caption": "giraffe 0.003", "scores": {"class_score": 0.002841949462890625}, "domain": "pixel"}, {"position": {"minX": 128.625, "minY": 368.75, "maxX": 203.125, "maxY": 413.25}, "class_id": 23, "box_caption": "giraffe 0.002", "scores": {"class_score": 0.002178192138671875}, "domain": "pixel"}, {"position": {"minX": 79.5, "minY": 401.5, "maxX": 200.5, "maxY": 434.5}, "class_id": 23, "box_caption": "giraffe 0.002", "scores": {"class_score": 0.0020275115966796875}, "domain": "pixel"}, {"position": {"minX": 157.5, "minY": 70.875, "maxX": 571.0, "maxY": 453.0}, "class_id": 23, "box_caption": "giraffe 0.002", "scores": {"class_score": 0.0019683837890625}, "domain": "pixel"}, {"position": {"minX": 459.75, "minY": 136.5, "maxX": 611.0, "maxY": 172.0}, "class_id": 23, "box_caption": "giraffe 0.002", "scores": {"class_score": 0.0019054412841796875}, "domain": "pixel"}, {"position": {"minX": -12.75, "minY": 355.75, "maxX": 152.875, "maxY": 442.25}, "class_id": 23, "box_caption": "giraffe 0.002", "scores": {"class_score": 0.00185394287109375}, "domain": "pixel"}, {"position": {"minX": 310.75, "minY": 93.125, "maxX": 473.75, "maxY": 388.5}, "class_id": 23, "box_caption": "giraffe 0.002", "scores": {"class_score": 0.0017910003662109375}, "domain": "pixel"}, {"position": {"minX": 390.0, "minY": 74.125, "maxX": 628.5, "maxY": 373.0}, "class_id": 15, "box_caption": "cat 0.002", "scores": {"class_score": 0.00177764892578125}, "domain": "pixel"}, {"position": {"minX": 308.75, "minY": 102.125, "maxX": 640.0, "maxY": 491.0}, "class_id": 23, "box_caption": "giraffe 0.002", "scores": {"class_score": 0.001766204833984375}, "domain": "pixel"}, {"position": {"minX": 3.9375, "minY": 408.5, "maxX": 203.75, "maxY": 448.0}, "class_id": 23, "box_caption": "giraffe 0.001", "scores": {"class_score": 0.0014238357543945312}, "domain": "pixel"}, {"position": {"minX": 60.09375, "minY": 368.25, "maxX": 177.875, "maxY": 426.25}, "class_id": 6, "box_caption": "train 0.001", "scores": {"class_score": 0.0014200210571289062}, "domain": "pixel"}, {"position": {"minX": 60.09375, "minY": 368.25, "maxX": 177.875, "maxY": 426.25}, "class_id": 18, "box_caption": "sheep 0.001", "scores": {"class_score": 0.0013713836669921875}, "domain": "pixel"}, {"position": {"minX": 406.0, "minY": 76.375, "maxX": 470.5, "maxY": 307.0}, "class_id": 23, "box_caption": "giraffe 0.001", "scores": {"class_score": 0.0012960433959960938}, "domain": "pixel"}, {"position": {"minX": 9.125, "minY": 386.75, "maxX": 156.5, "maxY": 432.25}, "class_id": 23, "box_caption": "giraffe 0.001", "scores": {"class_score": 0.0012760162353515625}, "domain": "pixel"}, {"position": {"minX": 397.75, "minY": 81.5, "maxX": 620.0, "maxY": 365.0}, "class_id": 6, "box_caption": "train 0.001", "scores": {"class_score": 0.0012359619140625}, "domain": "pixel"}, {"position": {"minX": 168.375, "minY": 374.0, "maxX": 201.125, "maxY": 396.5}, "class_id": 23, "box_caption": "giraffe 0.001", "scores": {"class_score": 0.0012159347534179688}, "domain": "pixel"}, {"position": {"minX": 38.125, "minY": 355.5, "maxX": 305.5, "maxY": 461.5}, "class_id": 23, "box_caption": "giraffe 0.001", "scores": {"class_score": 0.0011806488037109375}, "domain": "pixel"}, {"position": {"minX": 397.75, "minY": 81.5, "maxX": 620.0, "maxY": 365.0}, "class_id": 53, "box_caption": "pizza 0.001", "scores": {"class_score": 0.0011568069458007812}, "domain": "pixel"}, {"position": {"minX": 61.25, "minY": 405.5, "maxX": 174.75, "maxY": 432.5}, "class_id": 23, "box_caption": "giraffe 0.001", "scores": {"class_score": 0.0011548995971679688}, "domain": "pixel"}, {"position": {"minX": 447.5, "minY": 8.921875, "maxX": 539.0, "maxY": 31.765625}, "class_id": 9, "box_caption": "traffic light 0.001", "scores": {"class_score": 0.0011501312255859375}, "domain": "pixel"}, {"position": {"minX": 464.75, "minY": 334.25, "maxX": 488.25, "maxY": 365.75}, "class_id": 23, "box_caption": "giraffe 0.001", "scores": {"class_score": 0.0011386871337890625}, "domain": "pixel"}, {"position": {"minX": 60.09375, "minY": 368.25, "maxX": 177.875, "maxY": 426.25}, "class_id": 21, "box_caption": "bear 0.001", "scores": {"class_score": 0.00106048583984375}, "domain": "pixel"}], "class_labels": {"0": "person", "1": "bicycle", "2": "car", "3": "motorcycle", "4": "airplane", "5": "bus", "6": "train", "7": "truck", "8": "boat", "9": "traffic light", "10": "fire hydrant", "11": "stop sign", "12": "parking meter", "13": "bench", "14": "bird", "15": "cat", "16": "dog", "17": "horse", "18": "sheep", "19": "cow", "20": "elephant", "21": "bear", "22": "zebra", "23": "giraffe", "24": "backpack", "25": "umbrella", "26": "handbag", "27": "tie", "28": "suitcase", "29": "frisbee", "30": "skis", "31": "snowboard", "32": "sports ball", "33": "kite", "34": "baseball bat", "35": "baseball glove", "36": "skateboard", "37": "surfboard", "38": "tennis racket", "39": "bottle", "40": "wine glass", "41": "cup", "42": "fork", "43": "knife", "44": "spoon", "45": "bowl", "46": "banana", "47": "apple", "48": "sandwich", "49": "orange", "50": "broccoli", "51": "carrot", "52": "hot dog", "53": "pizza", "54": "donut", "55": "cake", "56": "chair", "57": "couch", "58": "potted plant", "59": "bed", "60": "dining table", "61": "toilet", "62": "tv", "63": "laptop", "64": "mouse", "65": "remote", "66": "keyboard", "67": "cell phone", "68": "microwave", "69": "oven", "70": "toaster", "71": "sink", "72": "refrigerator", "73": "book", "74": "clock", "75": "vase", "76": "scissors", "77": "teddy bear", "78": "hair drier", "79": "toothbrush"}}