{"box_data": [{"position": {"minX": 390.75, "minY": 238.75, "maxX": 486.75, "maxY": 404.75}, "class_id": 27, "box_caption": "tie 0.924", "scores": {"class_score": 0.92431640625}, "domain": "pixel"}, {"position": {"minX": 236.25, "minY": 73.25, "maxX": 594.0, "maxY": 406.75}, "class_id": 0, "box_caption": "person 0.907", "scores": {"class_score": 0.90673828125}, "domain": "pixel"}, {"position": {"minX": 415.5, "minY": 277.0, "maxX": 592.0, "maxY": 403.0}, "class_id": 55, "box_caption": "cake 0.897", "scores": {"class_score": 0.8974609375}, "domain": "pixel"}, {"position": {"minX": 390.25, "minY": 241.25, "maxX": 489.75, "maxY": 404.75}, "class_id": 55, "box_caption": "cake 0.043", "scores": {"class_score": 0.04290771484375}, "domain": "pixel"}, {"position": {"minX": -26.0, "minY": 48.125, "maxX": 644.5, "maxY": 401.0}, "class_id": 0, "box_caption": "person 0.043", "scores": {"class_score": 0.042724609375}, "domain": "pixel"}, {"position": {"minX": 412.5, "minY": 293.25, "maxX": 454.0, "maxY": 401.75}, "class_id": 27, "box_caption": "tie 0.009", "scores": {"class_score": 0.00923919677734375}, "domain": "pixel"}, {"position": {"minX": 251.25, "minY": 80.0, "maxX": 610.0, "maxY": 407.0}, "class_id": 27, "box_caption": "tie 0.007", "scores": {"class_score": 0.007244110107421875}, "domain": "pixel"}, {"position": {"minX": 391.0, "minY": 239.25, "maxX": 483.5, "maxY": 400.75}, "class_id": 14, "box_caption": "bird 0.006", "scores": {"class_score": 0.0059356689453125}, "domain": "pixel"}, {"position": {"minX": 390.0, "minY": 242.75, "maxX": 484.0, "maxY": 399.25}, "class_id": 0, "box_caption": "person 0.006", "scores": {"class_score": 0.00577545166015625}, "domain": "pixel"}, {"position": {"minX": 416.0, "minY": 274.0, "maxX": 591.5, "maxY": 406.0}, "class_id": 54, "box_caption": "donut 0.005", "scores": {"class_score": 0.0050201416015625}, "domain": "pixel"}, {"position": {"minX": 392.5, "minY": 247.75, "maxX": 483.0, "maxY": 311.75}, "class_id": 27, "box_caption": "tie 0.004", "scores": {"class_score": 0.00441741943359375}, "domain": "pixel"}, {"position": {"minX": 404.5, "minY": 254.0, "maxX": 440.0, "maxY": 398.0}, "class_id": 27, "box_caption": "tie 0.004", "scores": {"class_score": 0.00431060791015625}, "domain": "pixel"}, {"position": {"minX": 441.0, "minY": 282.5, "maxX": 562.5, "maxY": 370.0}, "class_id": 55, "box_caption": "cake 0.004", "scores": {"class_score": 0.0037975311279296875}, "domain": "pixel"}, {"position": {"minX": 416.0, "minY": 274.0, "maxX": 591.5, "maxY": 406.0}, "class_id": 26, "box_caption": "handbag 0.003", "scores": {"class_score": 0.0034942626953125}, "domain": "pixel"}, {"position": {"minX": 390.0, "minY": 242.75, "maxX": 484.0, "maxY": 399.25}, "class_id": 24, "box_caption": "backpack 0.003", "scores": {"class_score": 0.003246307373046875}, "domain": "pixel"}, {"position": {"minX": 6.375, "minY": 41.5, "maxX": 372.5, "maxY": 391.75}, "class_id": 0, "box_caption": "person 0.003", "scores": {"class_score": 0.003173828125}, "domain": "pixel"}, {"position": {"minX": 391.0, "minY": 239.25, "maxX": 483.5, "maxY": 400.75}, "class_id": 76, "box_caption": "scissors 0.003", "scores": {"class_score": 0.0030059814453125}, "domain": "pixel"}, {"position": {"minX": -26.0, "minY": 48.125, "maxX": 644.5, "maxY": 401.0}, "class_id": 60, "box_caption": "dining table 0.003", "scores": {"class_score": 0.0025768280029296875}, "domain": "pixel"}, {"position": {"minX": 416.25, "minY": 280.0, "maxX": 594.0, "maxY": 401.5}, "class_id": 60, "box_caption": "dining table 0.003", "scores": {"class_score": 0.002567291259765625}, "domain": "pixel"}, {"position": {"minX": 391.5, "minY": 240.625, "maxX": 488.5, "maxY": 406.0}, "class_id": 77, "box_caption": "teddy bear 0.003", "scores": {"class_score": 0.002529144287109375}, "domain": "pixel"}, {"position": {"minX": 227.375, "minY": 289.5, "maxX": 638.0, "maxY": 402.5}, "class_id": 27, "box_caption": "tie 0.002", "scores": {"class_score": 0.0024547576904296875}, "domain": "pixel"}, {"position": {"minX": -26.0, "minY": 48.125, "maxX": 644.5, "maxY": 401.0}, "class_id": 57, "box_caption": "couch 0.002", "scores": {"class_score": 0.002452850341796875}, "domain": "pixel"}, {"position": {"minX": 416.25, "minY": 280.0, "maxX": 594.0, "maxY": 401.5}, "class_id": 77, "box_caption": "teddy bear 0.002", "scores": {"class_score": 0.002410888671875}, "domain": "pixel"}, {"position": {"minX": 427.5, "minY": 279.0, "maxX": 592.5, "maxY": 401.5}, "class_id": 43, "box_caption": "knife 0.002", "scores": {"class_score": 0.0023059844970703125}, "domain": "pixel"}, {"position": {"minX": 388.25, "minY": 236.375, "maxX": 484.25, "maxY": 401.0}, "class_id": 50, "box_caption": "broccoli 0.002", "scores": {"class_score": 0.002288818359375}, "domain": "pixel"}, {"position": {"minX": 307.5, "minY": 237.5, "maxX": 548.5, "maxY": 405.5}, "class_id": 27, "box_caption": "tie 0.002", "scores": {"class_score": 0.002239227294921875}, "domain": "pixel"}, {"position": {"minX": 251.25, "minY": 284.0, "maxX": 294.75, "maxY": 356.5}, "class_id": 65, "box_caption": "remote 0.002", "scores": {"class_score": 0.0020923614501953125}, "domain": "pixel"}, {"position": {"minX": 236.625, "minY": 75.75, "maxX": 593.5, "maxY": 405.25}, "class_id": 56, "box_caption": "chair 0.002", "scores": {"class_score": 0.0019817352294921875}, "domain": "pixel"}, {"position": {"minX": -26.0, "minY": 48.125, "maxX": 644.5, "maxY": 401.0}, "class_id": 25, "box_caption": "umbrella 0.002", "scores": {"class_score": 0.0019521713256835938}, "domain": "pixel"}, {"position": {"minX": 416.0, "minY": 274.0, "maxX": 591.5, "maxY": 406.0}, "class_id": 48, "box_caption": "sandwich 0.002", "scores": {"class_score": 0.0019407272338867188}, "domain": "pixel"}, {"position": {"minX": 408.0, "minY": 267.5, "maxX": 468.0, "maxY": 400.5}, "class_id": 27, "box_caption": "tie 0.002", "scores": {"class_score": 0.001827239990234375}, "domain": "pixel"}, {"position": {"minX": 246.875, "minY": 287.75, "maxX": 615.5, "maxY": 404.75}, "class_id": 60, "box_caption": "dining table 0.002", "scores": {"class_score": 0.0017681121826171875}, "domain": "pixel"}, {"position": {"minX": 389.75, "minY": 241.375, "maxX": 484.75, "maxY": 398.5}, "class_id": 26, "box_caption": "handbag 0.002", "scores": {"class_score": 0.0016651153564453125}, "domain": "pixel"}, {"position": {"minX": 393.25, "minY": 239.25, "maxX": 482.25, "maxY": 402.25}, "class_id": 40, "box_caption": "wine glass 0.002", "scores": {"class_score": 0.0016241073608398438}, "domain": "pixel"}, {"position": {"minX": 390.5, "minY": 241.375, "maxX": 486.0, "maxY": 400.0}, "class_id": 56, "box_caption": "chair 0.002", "scores": {"class_score": 0.0016155242919921875}, "domain": "pixel"}, {"position": {"minX": 389.0, "minY": 241.375, "maxX": 486.5, "maxY": 400.5}, "class_id": 60, "box_caption": "dining table 0.002", "scores": {"class_score": 0.001613616943359375}, "domain": "pixel"}, {"position": {"minX": 415.0, "minY": 278.0, "maxX": 597.5, "maxY": 403.0}, "class_id": 63, "box_caption": "laptop 0.002", "scores": {"class_score": 0.0016088485717773438}, "domain": "pixel"}, {"position": {"minX": 390.75, "minY": 242.25, "maxX": 449.75, "maxY": 393.25}, "class_id": 27, "box_caption": "tie 0.002", "scores": {"class_score": 0.0016050338745117188}, "domain": "pixel"}, {"position": {"minX": 394.0, "minY": 242.75, "maxX": 479.0, "maxY": 402.75}, "class_id": 38, "box_caption": "tennis racket 0.002", "scores": {"class_score": 0.0015802383422851562}, "domain": "pixel"}, {"position": {"minX": 388.25, "minY": 240.75, "maxX": 487.75, "maxY": 402.75}, "class_id": 66, "box_caption": "keyboard 0.002", "scores": {"class_score": 0.001552581787109375}, "domain": "pixel"}, {"position": {"minX": 416.25, "minY": 280.0, "maxX": 594.0, "maxY": 401.5}, "class_id": 56, "box_caption": "chair 0.001", "scores": {"class_score": 0.0014352798461914062}, "domain": "pixel"}, {"position": {"minX": 416.0, "minY": 274.0, "maxX": 591.5, "maxY": 406.0}, "class_id": 45, "box_caption": "bowl 0.001", "scores": {"class_score": 0.0014324188232421875}, "domain": "pixel"}, {"position": {"minX": 416.0, "minY": 274.0, "maxX": 591.5, "maxY": 406.0}, "class_id": 53, "box_caption": "pizza 0.001", "scores": {"class_score": 0.0013980865478515625}, "domain": "pixel"}, {"position": {"minX": 394.25, "minY": 244.0, "maxX": 478.75, "maxY": 401.5}, "class_id": 33, "box_caption": "kite 0.001", "scores": {"class_score": 0.0013866424560546875}, "domain": "pixel"}, {"position": {"minX": 416.0, "minY": 275.0, "maxX": 591.0, "maxY": 405.5}, "class_id": 17, "box_caption": "horse 0.001", "scores": {"class_score": 0.0013608932495117188}, "domain": "pixel"}, {"position": {"minX": 414.25, "minY": 279.0, "maxX": 595.5, "maxY": 402.0}, "class_id": 6, "box_caption": "train 0.001", "scores": {"class_score": 0.0013360977172851562}, "domain": "pixel"}, {"position": {"minX": 389.75, "minY": 241.375, "maxX": 484.75, "maxY": 398.5}, "class_id": 16, "box_caption": "dog 0.001", "scores": {"class_score": 0.0012683868408203125}, "domain": "pixel"}, {"position": {"minX": 414.25, "minY": 279.0, "maxX": 595.5, "maxY": 402.0}, "class_id": 33, "box_caption": "kite 0.001", "scores": {"class_score": 0.0012655258178710938}, "domain": "pixel"}, {"position": {"minX": 495.75, "minY": 253.5, "maxX": 533.0, "maxY": 287.0}, "class_id": 56, "box_caption": "chair 0.001", "scores": {"class_score": 0.0012607574462890625}, "domain": "pixel"}, {"position": {"minX": 391.5, "minY": 240.625, "maxX": 488.5, "maxY": 406.0}, "class_id": 54, "box_caption": "donut 0.001", "scores": {"class_score": 0.001255035400390625}, "domain": "pixel"}, {"position": {"minX": 416.0, "minY": 275.0, "maxX": 591.0, "maxY": 405.5}, "class_id": 25, "box_caption": "umbrella 0.001", "scores": {"class_score": 0.0011501312255859375}, "domain": "pixel"}, {"position": {"minX": 427.5, "minY": 279.0, "maxX": 592.5, "maxY": 401.5}, "class_id": 42, "box_caption": "fork 0.001", "scores": {"class_score": 0.0011396408081054688}, "domain": "pixel"}, {"position": {"minX": 391.0, "minY": 239.25, "maxX": 483.5, "maxY": 400.75}, "class_id": 79, "box_caption": "toothbrush 0.001", "scores": {"class_score": 0.0011119842529296875}, "domain": "pixel"}, {"position": {"minX": -26.0, "minY": 48.125, "maxX": 644.5, "maxY": 401.0}, "class_id": 59, "box_caption": "bed 0.001", "scores": {"class_score": 0.0010662078857421875}, "domain": "pixel"}, {"position": {"minX": 414.25, "minY": 279.0, "maxX": 595.5, "maxY": 402.0}, "class_id": 46, "box_caption": "banana 0.001", "scores": {"class_score": 0.00104522705078125}, "domain": "pixel"}, {"position": {"minX": 389.75, "minY": 241.375, "maxX": 484.75, "maxY": 398.5}, "class_id": 22, "box_caption": "zebra 0.001", "scores": {"class_score": 0.0010271072387695312}, "domain": "pixel"}], "class_labels": {"0": "person", "1": "bicycle", "2": "car", "3": "motorcycle", "4": "airplane", "5": "bus", "6": "train", "7": "truck", "8": "boat", "9": "traffic light", "10": "fire hydrant", "11": "stop sign", "12": "parking meter", "13": "bench", "14": "bird", "15": "cat", "16": "dog", "17": "horse", "18": "sheep", "19": "cow", "20": "elephant", "21": "bear", "22": "zebra", "23": "giraffe", "24": "backpack", "25": "umbrella", "26": "handbag", "27": "tie", "28": "suitcase", "29": "frisbee", "30": "skis", "31": "snowboard", "32": "sports ball", "33": "kite", "34": "baseball bat", "35": "baseball glove", "36": "skateboard", "37": "surfboard", "38": "tennis racket", "39": "bottle", "40": "wine glass", "41": "cup", "42": "fork", "43": "knife", "44": "spoon", "45": "bowl", "46": "banana", "47": "apple", "48": "sandwich", "49": "orange", "50": "broccoli", "51": "carrot", "52": "hot dog", "53": "pizza", "54": "donut", "55": "cake", "56": "chair", "57": "couch", "58": "potted plant", "59": "bed", "60": "dining table", "61": "toilet", "62": "tv", "63": "laptop", "64": "mouse", "65": "remote", "66": "keyboard", "67": "cell phone", "68": "microwave", "69": "oven", "70": "toaster", "71": "sink", "72": "refrigerator", "73": "book", "74": "clock", "75": "vase", "76": "scissors", "77": "teddy bear", "78": "hair drier", "79": "toothbrush"}}